Lab2/refactor/seven_segment_controller.v

module seven_segment_controller(
                                input            clk,
                                input            reset_n,
                                input [31:0]     scan_codes,
                                output [7:0] seven_segment_number,
                                output [7:0] seven_segment_enable
                                );

   reg [1:0] seg_counter;
   reg [7:0] single_scan_code;
   localparam shifter = 8;
   reg [7:0]  int_seven_segment_number;
   reg [7:0]  int_seven_segment_enable;

   always @(posedge clk, negedge reset_n) begin

      if(~reset_n) begin
         seg_counter <= 0;


      end else begin
         seg_counter <= seg_counter + 1;
         if (seg_counter == 2'b11) begin
            seg_counter <= 2'b00;

         end

      end // else: !if(~reset_n)


   end

   // make a loop for cycling through which letter to flash
   // make a loop to match scan code to seven segment
   always @ (clk) begin

      //shift this in every clk
      single_scan_code = scan_codes[7:0];

      case(single_scan_code)
        8'h45 : int_seven_segment_number = 8'b11000000; //0

        8'h16 :  int_seven_segment_number = 8'b11111001; //1

        8'h1e:  int_seven_segment_number = 8'b10100100; //2

        8'h26:  int_seven_segment_number = 8'b10110000; //...

        8'h25:  int_seven_segment_number = 8'b10011001;

        8'h2e:  int_seven_segment_number = 8'b10010010;

        8'h36: int_seven_segment_number = 8'b10000010;

        8'h3d: int_seven_segment_number = 8'b11111000;

        8'h3e: int_seven_segment_number = 8'b10000000;

        8'h46: int_seven_segment_number = 8'b10010000; //9

        8'h0 : int_seven_segment_number = 8'b11111111; //off

        default : int_seven_segment_number = 8'b10000110; //error

      endcase // case (sel)
   end // always @ (binary_in)


   // Block to send a scancode and flash one of the lights
   // then flash next light
   //reduce states and just shift and add 1 instead.
   always @(clk) begin
      case (seg_counter)
        2'b00: begin
           int_seven_segment_enable <= 4'b1110;
           //           int_seven_segment_number <= scan_codes[31:24]; //convert follow mapping below
        end
        2'b01: begin
           int_seven_segment_enable <= 4'b1101;
           //           int_seven_segment_number <= scan_codes[23:16];
        end
        2'b10: begin
           int_seven_segment_enable <= 4'b1011;
           //           int_seven_segment_number <= scan_codes[15:8];
        end
        2'b11: begin
           int_seven_segment_enable <= 4'b0111;
           //           int_seven_segment_number <= scan_codes[7:0];
        end
        default: begin
           int_seven_segment_enable <= 4'b0000;
           //           int_seven_segment_number <= scan_codes[7:0];
        end

      endcase  // case (seg_counter)
   end

   assign seven_segment_number = int_seven_segment_number;

   assign seven_segment_enable = int_seven_segment_enable;

   localparam SCAN_CODE_0 = 8'h45;

   localparam SCAN_CODE_1 = 8'h16;

   localparam SCAN_CODE_2 = 8'h1e;

   localparam SCAN_CODE_3 = 8'h26;

   localparam SCAN_CODE_4 = 8'h25;

   localparam SCAN_CODE_5 = 8'h2e;

   localparam SCAN_CODE_6 = 8'h36;

   localparam SCAN_CODE_7 = 8'h3d;

   localparam SCAN_CODE_8 = 8'h3e;

   localparam SCAN_CODE_9 = 8'h46;

   localparam SCAN_CODE_RESET = 8'h0;

   localparam SEVEN_SEGMENT_0 = 8'b1100_0000;
   localparam SEVEN_SEGMENT_1 = 8'b1111_1001;
   localparam SEVEN_SEGMENT_2 = 8'b1010_0100;
   localparam SEVEN_SEGMENT_3 = 8'b1011_0000;
   localparam SEVEN_SEGMENT_4 = 8'b1001_1001;
   localparam SEVEN_SEGMENT_5 = 8'b1001_0010;
   localparam SEVEN_SEGMENT_6 = 8'b1000_0010;
   localparam SEVEN_SEGMENT_7 = 8'b1111_1000;
   localparam SEVEN_SEGMENT_8 = 8'b1000_0000;
   localparam SEVEN_SEGMENT_9 = 8'b1001_0000;
   localparam SEVEN_SEGMENT_F = 8'b1000_1110;
   localparam SEVEN_SEGMENT_EMPTY = 8'b1111_1111;



endmodule

Lab2/refactor/keyboard_controller.v
module keyboard_controller(
    input clk,
    input reset_n,
    input valid_scan_code,
    input [7:0] scan_code,
    output [31:0] scan_codes
);


   reg [1:0] state, next_state;
   reg [31:0] int_scan_codes;
   // Debug variables
   reg [8:0]  TEST_CTRL_1 = 0;
   reg [8:0]  TEST_CTRL_2 = 0;
   reg [8:0]  TEST_CTRL_3 = 0;
   reg [8:0]  TEST_CTRL_4 = 0;

   // Immediately after negedge valid_scan_code the valid scan code appears on input
   // so it looks like following

   reg [8:0]  temp_code = 0;

   always @(posedge clk, negedge reset_n)
     // Setup if reset
     if (~reset_n) begin
        state <= 0;
        next_state <= 0;
        int_scan_codes <= 0;
        //temp_code <= 0;

     end else begin
        //update state on every clock cycle
        state <= next_state;
     end

   // Might need to change to positive, check signals
   // valid code looks at something,
   always @(negedge valid_scan_code) begin
      if (~valid_scan_code) begin
         case (state)
           2'b00: begin // we dont enter this state because we reach it one clk cycle too early
              int_scan_codes = int_scan_codes << 8;
              next_state = 2'b01;
              temp_code = scan_code;
           end

           2'b01: begin
           if (scan_code == 8'hF0)
              int_scan_codes[7:0] <= temp_code;
             next_state <= 2'b10;
           end

           2'b10: begin
              if (scan_code == temp_code) begin
              next_state <= 2'b00;
              end else begin
                 next_state <= 2'b00;
                 end
           end


         endcase  // case (state)
      end  // if (valid_code)

end

   assign scan_codes = int_scan_codes;


endmodule

Lab2/refactor/serial_to_scancode.v
module serial_to_scancode(
    input clk,
    input reset_n,
    input sample_ready,
    input serial_data,
    output reg valid_scan_code,
    output [7:0] scan_code
);


reg [3:0] counter = 4'b0000;
reg [3:0] next_counter = 4'b0000;
reg [7:0] int_scan_code;

always @(posedge clk or negedge reset_n) begin
    if (~reset_n) begin
        counter <= 4'b0000;
       int_scan_code <= 0;

    end else if (sample_ready) begin
        counter <= next_counter;
    end
end

always @(counter) begin
    int_scan_code[6:0] <= int_scan_code[7:1];
    int_scan_code[7] <= serial_data;
    valid_scan_code = 1'b0;
    if (counter == 4'b1010) begin
        valid_scan_code = 1'b1;
    end
end

always @(counter) begin
    next_counter = counter + 1;
    if (counter == 4'b1010) begin
        next_counter = 4'b0000;
    end
end

assign scan_code = int_scan_code;


endmodule

Lab2/refactor/falling_edge_detector.v
//mitten data stabil

module falling_edge_detector(
    input clk,
    input reset_n,
    input in,
    output edge_found
);

   //detect a falling edge on an input
   reg in_d; //one cc delay
   reg int_edge_found;

   always @(posedge clk or negedge reset_n)
     if(~reset_n) begin
        in_d <= 0;
     end else begin
        in_d <= in;
        int_edge_found <= (~in && in_d);
     end

   assign edge_found = int_edge_found;


endmodule

Lab2/refactor/synchronizer.v
module synchronizer(
    input clk,
    input reset_n,
    input unsynched,
    output reg synched
);

reg in_buffed;

  always @ (posedge clk)
  begin
    in_buffed <= unsynched;
    synched <= in_buffed;
  end




endmodule

Lab2/refactor/keyboard_top.v
module keyboard_top(
    input clk,
    input reset_n,
    input keyboard_clk,
    input keyboard_data,
    output [7:0] led_scancode_debug,
    output [7:0] seven_segment_number,
    output [7:0] seven_segment_enable
);

    wire keyboard_clk_synched;
    wire keyboard_data_synched;

    wire keyboard_clk_edge_found;

    wire valid_scan_code;
    wire [7:0] scan_code;
    wire [31:0] scan_codes;


    synchronizer kb_clk_synchronizer(
        .clk(clk),
        .reset_n(reset_n),
        .unsynched(keyboard_clk),
        .synched(keyboard_clk_synched)
    );

    synchronizer kb_data_synchronizer(
        .clk(clk),
        .reset_n(reset_n),
        .unsynched(keyboard_data),
        .synched(keyboard_data_synched)
    );

    falling_edge_detector kb_clk_edge_detector(
        .clk(clk),
        .reset_n(reset_n),
        .in(keyboard_clk_synched),
        .edge_found(keyboard_clk_edge_found)
    );

    serial_to_scancode serial_to_scancode_converter(
        .clk(clk),
        .reset_n(reset_n),
        .sample_ready(keyboard_clk_edge_found),
        .serial_data(keyboard_data_synched),
        .valid_scan_code(valid_scan_code),
        .scan_code(scan_code)
    );

    keyboard_controller inst_keyboard_controller(
        .clk(clk),
        .reset_n(reset_n),
        .valid_scan_code(valid_scan_code),
        .scan_code(scan_code),
        .scan_codes(scan_codes)
    );

    seven_segment_controller inst_seven_segment_controller(
        .clk(clk),
        .reset_n(reset_n),
        .scan_codes(scan_codes),
        .seven_segment_number(seven_segment_number),
        .seven_segment_enable(seven_segment_enable)
    );

   // change this one to valid_scancode or whatever to check functionality between blocks
    assign led_scancode_debug = scan_code;

endmodule

Lab2/refactor/testbench_top.v
`timescale 1ns / 1ps


module testbench_top();
    localparam INPUT_FILE = "input.txt";

    localparam INIT = 3'b000;
    localparam SHIFT = 3'b001;
    localparam WAIT = 3'b010;
    localparam WAIT2 = 3'b011;
    localparam FINISH = 3'b100;

    localparam NUM_KEYS = 12;

    reg [2:0] state;

    reg [7:0] memory [0:NUM_KEYS-1]; // 8 bit memory with 16 entries
    integer memory_index = 0;

    reg clk = 1'b0;
    reg reset_n = 1'b0;

    reg clk_slow = 1'b0;
    reg clk_keyboard = 1'b1;
    reg data_keyboard = 1'b0;

    wire [7:0] scan_code_debug;
    wire [7:0] seven_segment_number;
    wire [7:0] seven_segment_enable;

    reg [32:0] key_all;
    reg start_shifting = 1'b0;
    integer bit_index = 0;


    keyboard_top inst_keyboard_top(
        .clk(clk),
        .reset_n(reset_n),
        .keyboard_clk(clk_keyboard),
        .keyboard_data(data_keyboard),
        .led_scancode_debug(scan_code_debug),
        .seven_segment_number(seven_segment_number),
        .seven_segment_enable(seven_segment_enable)
    );


    always #10 clk = ~clk;
    always #100 clk_slow = ~clk_slow;


    initial begin
        $readmemh(INPUT_FILE, memory);
           $dumpfile("test.vcd");
           $dumpvars(0,testbench_top);


        reset_n = 1'b0;
        @(negedge clk);
        @(negedge clk);
        @(negedge clk);
        reset_n = 1'b1;
    end


    always @(posedge clk or negedge reset_n)
    begin
        if (!reset_n) begin
            data_keyboard <= 1'b0;
            key_all <= 0;
            memory_index <= 0;
            start_shifting <= 1'b0;
            bit_index <= 0;
            clk_keyboard <= 1'b1;
            state <= INIT;
        end else begin
            case (state)
                INIT:
                begin
                    key_all <= {1'b11, memory[memory_index], 2'b0, 1'b11, 8'hf0, 2'b0, 1'b11, memory[memory_index], 2'b0};
                    memory_index <= memory_index + 1;
                    state <= SHIFT;
                    bit_index <= 0;
                end

                SHIFT:
                begin
                    data_keyboard <= key_all[bit_index];
                    bit_index <= bit_index + 1;
                    state <= WAIT;
                end

                WAIT:
                begin
                    if (!clk_slow) begin
                        clk_keyboard <= 1'b0;
                        state <= WAIT2;
                    end
                end

                WAIT2:
                begin
                    if (clk_slow) begin
                        clk_keyboard <= 1'b1;
                        state <= SHIFT;
                        if (bit_index == 32) begin
                            state <= INIT;
                            if (memory_index == NUM_KEYS) begin
                                state <= FINISH;
                            end
                        end
                    end
                end

                FINISH:
                begin
                    $display("Finished!");
                   $finish;

                    $stop;
                end
            endcase
        end
    end


    always @(posedge clk_keyboard)
    begin
        if (bit_index == 12 & scan_code_debug != memory[memory_index-1]) begin
            $display("Failure!");
            $display("DUT Scan code = %x is not equal to expected = %x!", scan_code_debug, memory[memory_index-1]);
           //        $finish;
           // $stop;
        end
    end

endmodule

Lab2/refactor/test.vcd
$date
	Tue Sep 19 16:45:15 2023
$end
$version
	Icarus Verilog
$end
$timescale
	1ps
$end
$scope module testbench_top $end
$var wire 8 ! seven_segment_number [7:0] $end
$var wire 8 " seven_segment_enable [7:0] $end
$var wire 8 # scan_code_debug [7:0] $end
$var parameter 3 $ FINISH $end
$var parameter 3 % INIT $end
$var parameter 72 & INPUT_FILE $end
$var parameter 32 ' NUM_KEYS $end
$var parameter 3 ( SHIFT $end
$var parameter 3 ) WAIT $end
$var parameter 3 * WAIT2 $end
$var reg 1 + clk $end
$var reg 1 , clk_keyboard $end
$var reg 1 - clk_slow $end
$var reg 1 . data_keyboard $end
$var reg 33 / key_all [32:0] $end
$var reg 1 0 reset_n $end
$var reg 1 1 start_shifting $end
$var reg 3 2 state [2:0] $end
$var integer 32 3 bit_index [31:0] $end
$var integer 32 4 memory_index [31:0] $end
$scope module inst_keyboard_top $end
$var wire 1 + clk $end
$var wire 1 , keyboard_clk $end
$var wire 1 . keyboard_data $end
$var wire 8 5 led_scancode_debug [7:0] $end
$var wire 1 0 reset_n $end
$var wire 1 6 valid_scan_code $end
$var wire 8 7 seven_segment_number [7:0] $end
$var wire 8 8 seven_segment_enable [7:0] $end
$var wire 32 9 scan_codes [31:0] $end
$var wire 8 : scan_code [7:0] $end
$var wire 1 ; keyboard_data_synched $end
$var wire 1 < keyboard_clk_synched $end
$var wire 1 = keyboard_clk_edge_found $end
$scope module inst_keyboard_controller $end
$var wire 1 + clk $end
$var wire 1 0 reset_n $end
$var wire 32 > scan_codes [31:0] $end
$var wire 1 6 valid_scan_code $end
$var wire 8 ? scan_code [7:0] $end
$var reg 9 @ TEST_CTRL_1 [8:0] $end
$var reg 9 A TEST_CTRL_2 [8:0] $end
$var reg 9 B TEST_CTRL_3 [8:0] $end
$var reg 9 C TEST_CTRL_4 [8:0] $end
$var reg 32 D int_scan_codes [31:0] $end
$var reg 2 E next_state [1:0] $end
$var reg 2 F state [1:0] $end
$var reg 9 G temp_code [8:0] $end
$upscope $end
$scope module inst_seven_segment_controller $end
$var wire 1 + clk $end
$var wire 1 0 reset_n $end
$var wire 32 H scan_codes [31:0] $end
$var wire 8 I seven_segment_enable [7:0] $end
$var wire 8 J seven_segment_number [7:0] $end
$var parameter 8 K SCAN_CODE_0 $end
$var parameter 8 L SCAN_CODE_1 $end
$var parameter 8 M SCAN_CODE_2 $end
$var parameter 8 N SCAN_CODE_3 $end
$var parameter 8 O SCAN_CODE_4 $end
$var parameter 8 P SCAN_CODE_5 $end
$var parameter 8 Q SCAN_CODE_6 $end
$var parameter 8 R SCAN_CODE_7 $end
$var parameter 8 S SCAN_CODE_8 $end
$var parameter 8 T SCAN_CODE_9 $end
$var parameter 8 U SCAN_CODE_RESET $end
$var parameter 8 V SEVEN_SEGMENT_0 $end
$var parameter 8 W SEVEN_SEGMENT_1 $end
$var parameter 8 X SEVEN_SEGMENT_2 $end
$var parameter 8 Y SEVEN_SEGMENT_3 $end
$var parameter 8 Z SEVEN_SEGMENT_4 $end
$var parameter 8 [ SEVEN_SEGMENT_5 $end
$var parameter 8 \ SEVEN_SEGMENT_6 $end
$var parameter 8 ] SEVEN_SEGMENT_7 $end
$var parameter 8 ^ SEVEN_SEGMENT_8 $end
$var parameter 8 _ SEVEN_SEGMENT_9 $end
$var parameter 8 ` SEVEN_SEGMENT_EMPTY $end
$var parameter 8 a SEVEN_SEGMENT_F $end
$var parameter 32 b shifter $end
$var reg 8 c int_seven_segment_enable [7:0] $end
$var reg 8 d int_seven_segment_number [7:0] $end
$var reg 2 e seg_counter [1:0] $end
$var reg 8 f single_scan_code [7:0] $end
$upscope $end
$scope module kb_clk_edge_detector $end
$var wire 1 + clk $end
$var wire 1 = edge_found $end
$var wire 1 0 reset_n $end
$var wire 1 < in $end
$var reg 1 g in_d $end
$var reg 1 h int_edge_found $end
$upscope $end
$scope module kb_clk_synchronizer $end
$var wire 1 + clk $end
$var wire 1 0 reset_n $end
$var wire 1 , unsynched $end
$var reg 1 i in_buffed $end
$var reg 1 < synched $end
$upscope $end
$scope module kb_data_synchronizer $end
$var wire 1 + clk $end
$var wire 1 0 reset_n $end
$var wire 1 . unsynched $end
$var reg 1 j in_buffed $end
$var reg 1 ; synched $end
$upscope $end
$scope module serial_to_scancode_converter $end
$var wire 1 + clk $end
$var wire 1 0 reset_n $end
$var wire 1 = sample_ready $end
$var wire 8 k scan_code [7:0] $end
$var wire 1 ; serial_data $end
$var reg 4 l counter [3:0] $end
$var reg 8 m int_scan_code [7:0] $end
$var reg 4 n next_counter [3:0] $end
$var reg 1 6 valid_scan_code $end
$upscope $end
$upscope $end
$upscope $end
$enddefinitions $end
$comment Show the parameter values. $end
$dumpall
b1000 b
b10001110 a
b11111111 `
b10010000 _
b10000000 ^
b11111000 ]
b10000010 \
b10010010 [
b10011001 Z
b10110000 Y
b10100100 X
b11111001 W
b11000000 V
b0 U
b1000110 T
b111110 S
b111101 R
b110110 Q
b101110 P
b100101 O
b100110 N
b11110 M
b10110 L
b1000101 K
b11 *
b10 )
b1 (
b1100 '
b11010010110111001110000011101010111010000101110011101000111100001110100 &
b0 %
b100 $
$end
#0
$dumpvars
b1 n
b0 m
b0 l
b0 k
xj
xi
xh
0g
bx f
b0 e
b10000110 d
b0 c
b10000110 J
b0 I
b0 H
b0 G
b0 F
b0 E
b0 D
b0 C
b0 B
b0 A
b0 @
b0 ?
b0 >
x=
x<
x;
b0 :
b0 9
b0 8
b10000110 7
06
b0 5
b0 4
b0 3
bx 2
01
00
bx /
0.
0-
1,
0+
b0 #
b0 "
b10000110 !
$end
#10000
b0 2
b0 /
b1110 "
b1110 8
b1110 I
b1110 c
1i
0j
b11111111 !
b11111111 7
b11111111 J
b11111111 d
b0 f
1+
#20000
0+
#30000
0;
1<
1+
#40000
0+
#50000
1+
#60000
10
0+
#70000
0=
0h
1g
b1 e
b1 2
b1 4
b100010110001111100000010001011000 /
1+
#80000
b1101 "
b1101 8
b1101 I
b1101 c
0+
#90000
b10 2
b1 3
b10 e
1+
#100000
b1011 "
b1011 8
b1011 I
b1011 c
0+
1-
#110000
b11 e
1+
#120000
b0 e
b111 "
b111 8
b111 I
b111 c
0+
#130000
b1 e
b1110 "
b1110 8
b1110 I
b1110 c
1+
#140000
b1101 "
b1101 8
b1101 I
b1101 c
0+
#150000
b10 e
1+
#160000
b1011 "
b1011 8
b1011 I
b1011 c
0+
#170000
b11 e
1+
#180000
b0 e
b111 "
b111 8
b111 I
b111 c
0+
#190000
b1 e
b1110 "
b1110 8
b1110 I
b1110 c
1+
#200000
b1101 "
b1101 8
b1101 I
b1101 c
0+
0-
#210000
b11 2
0,
b10 e
1+
#220000
b1011 "
b1011 8
b1011 I
b1011 c
0+
#230000
b11 e
0i
1+
#240000
b0 e
b111 "
b111 8
b111 I
b111 c
0+
#250000
b1 e
b1110 "
b1110 8
b1110 I
b1110 c
0<
1+
#260000
b1101 "
b1101 8
b1101 I
b1101 c
0+
#270000
1=
1h
0g
b10 e
1+
#280000
b1011 "
b1011 8
b1011 I
b1011 c
0+
#290000
b10 n
b11 e
b1 l
0=
0h
1+
#300000
b0 e
b111 "
b111 8
b111 I
b111 c
0+
1-
#310000
b1 e
b1 2
1,
b1110 "
b1110 8
b1110 I
b1110 c
1+
#320000
b1101 "
b1101 8
b1101 I
b1101 c
0+
#330000
b10 2
b10 3
b10 e
1i
1+
#340000
b1011 "
b1011 8
b1011 I
b1011 c
0+
#350000
b11 e
1<
1+
#360000
b0 e
b111 "
b111 8
b111 I
b111 c
0+
#370000
b1 e
1g
b1110 "
b1110 8
b1110 I
b1110 c
1+
#380000
b1101 "
b1101 8
b1101 I
b1101 c
0+
#390000
b10 e
1+
#400000
b1011 "
b1011 8
b1011 I
b1011 c
0+
0-
#410000
b11 2
0,
b11 e
1+
#420000
b0 e
b111 "
b111 8
b111 I
b111 c
0+
#430000
b1 e
b1110 "
b1110 8
b1110 I
b1110 c
0i
1+
#440000
b1101 "
b1101 8
b1101 I
b1101 c
0+
#450000
b10 e
0<
1+
#460000
b1011 "
b1011 8
b1011 I
b1011 c
0+
#470000
1=
1h
0g
b11 e
1+
#480000
b0 e
b111 "
b111 8
b111 I
b111 c
0+
#490000
b11 n
b1 e
b10 l
0=
0h
b1110 "
b1110 8
b1110 I
b1110 c
1+
#500000
b1101 "
b1101 8
b1101 I
b1101 c
0+
1-
#510000
b10 e
b1 2
1,
1+
#520000
b1011 "
b1011 8
b1011 I
b1011 c
0+
#530000
b10 2
b11 3
b11 e
1i
1+
#540000
b0 e
b111 "
b111 8
b111 I
b111 c
0+
#550000
b1 e
b1110 "
b1110 8
b1110 I
b1110 c
1<
1+
#560000
b1101 "
b1101 8
b1101 I
b1101 c
0+
#570000
b10 e
1g
1+
#580000
b1011 "
b1011 8
b1011 I
b1011 c
0+
#590000
b11 e
1+
#600000
b0 e
b111 "
b111 8
b111 I
b111 c
0+
0-
#610000
b11 2
0,
b1 e
b1110 "
b1110 8
b1110 I
b1110 c
1+
#620000
b1101 "
b1101 8
b1101 I
b1101 c
0+
#630000
b10 e
0i
1+
#640000
b1011 "
b1011 8
b1011 I
b1011 c
0+
#650000
b11 e
0<
1+
#660000
b0 e
b111 "
b111 8
b111 I
b111 c
0+
#670000
1=
1h
0g
b1 e
b1110 "
b1110 8
b1110 I
b1110 c
1+
#680000
b1101 "
b1101 8
b1101 I
b1101 c
0+
#690000
b100 n
b10 e
b11 l
0=
0h
1+
#700000
b1011 "
b1011 8
b1011 I
b1011 c
0+
1-
#710000
b11 e
b1 2
1,
1+
#720000
b0 e
b111 "
b111 8
b111 I
b111 c
0+
#730000
b10 2
b100 3
1.
b1 e
b1110 "
b1110 8
b1110 I
b1110 c
1i
1+
#740000
b1101 "
b1101 8
b1101 I
b1101 c
0+
#750000
b10 e
1j
1<
1+
#760000
b1011 "
b1011 8
b1011 I
b1011 c
0+
#770000
b11 e
1g
1;
1+
#780000
b0 e
b111 "
b111 8
b111 I
b111 c
0+
#790000
b1 e
b1110 "
b1110 8
b1110 I
b1110 c
1+
#800000
b1101 "
b1101 8
b1101 I
b1101 c
0+
0-
#810000
b11 2
0,
b10 e
1+
#820000
b1011 "
b1011 8
b1011 I
b1011 c
0+
#830000
b11 e
0i
1+
#840000
b0 e
b111 "
b111 8
b111 I
b111 c
0+
#850000
b1 e
b1110 "
b1110 8
b1110 I
b1110 c
0<
1+
#860000
b1101 "
b1101 8
b1101 I
b1101 c
0+
#870000
1=
1h
0g
b10 e
1+
#880000
b1011 "
b1011 8
b1011 I
b1011 c
0+
#890000
b10000000 #
b10000000 5
b10000000 :
b10000000 ?
b10000000 k
b10000000 m
b101 n
b11 e
b100 l
0=
0h
1+
#900000
b0 e
b111 "
b111 8
b111 I
b111 c
0+
1-
#910000
b1 e
b1 2
1,
b1110 "
b1110 8
b1110 I
b1110 c
1+
#920000
b1101 "
b1101 8
b1101 I
b1101 c
0+
#930000
b10 2
b101 3
b10 e
1i
1+
#940000
b1011 "
b1011 8
b1011 I
b1011 c
0+
#950000
b11 e
1<
1+
#960000
b0 e
b111 "
b111 8
b111 I
b111 c
0+
#970000
b1 e
1g
b1110 "
b1110 8
b1110 I
b1110 c
1+
#980000
b1101 "
b1101 8
b1101 I
b1101 c
0+
#990000
b10 e
1+
#1000000
b1011 "
b1011 8
b1011 I
b1011 c
0+
0-
#1010000
b11 2
0,
b11 e
1+
#1020000
b0 e
b111 "
b111 8
b111 I
b111 c
0+
#1030000
b1 e
b1110 "
b1110 8
b1110 I
b1110 c
0i
1+
#1040000
b1101 "
b1101 8
b1101 I
b1101 c
0+
#1050000
b10 e
0<
1+
#1060000
b1011 "
b1011 8
b1011 I
b1011 c
0+
#1070000
1=
1h
0g
b11 e
1+
#1080000
b0 e
b111 "
b111 8
b111 I
b111 c
0+
#1090000
b11000000 #
b11000000 5
b11000000 :
b11000000 ?
b11000000 k
b11000000 m
b110 n
b1 e
b101 l
0=
0h
b1110 "
b1110 8
b1110 I
b1110 c
1+
#1100000
b1101 "
b1101 8
b1101 I
b1101 c
0+
1-
#1110000
b10 e
b1 2
1,
1+
#1120000
b1011 "
b1011 8
b1011 I
b1011 c
0+
#1130000
b10 2
b110 3
0.
b11 e
1i
1+
#1140000
b0 e
b111 "
b111 8
b111 I
b111 c
0+
#1150000
b1 e
b1110 "
b1110 8
b1110 I
b1110 c
0j
1<
1+
#1160000
b1101 "
b1101 8
b1101 I
b1101 c
0+
#1170000
b10 e
1g
0;
1+
#1180000
b1011 "
b1011 8
b1011 I
b1011 c
0+
#1190000
b11 e
1+
#1200000
b0 e
b111 "
b111 8
b111 I
b111 c
0+
0-
#1210000
b11 2
0,
b1 e
b1110 "
b1110 8
b1110 I
b1110 c
1+
#1220000
b1101 "
b1101 8
b1101 I
b1101 c
0+
#1230000
b10 e
0i
1+
#1240000
b1011 "
b1011 8
b1011 I
b1011 c
0+
#1250000
b11 e
0<
1+
#1260000
b0 e
b111 "
b111 8
b111 I
b111 c
0+
#1270000
1=
1h
0g
b1 e
b1110 "
b1110 8
b1110 I
b1110 c
1+
#1280000
b1101 "
b1101 8
b1101 I
b1101 c
0+
#1290000
b1100000 #
b1100000 5
b1100000 :
b1100000 ?
b1100000 k
b1100000 m
b111 n
b10 e
b110 l
0=
0h
1+
#1300000
b1011 "
b1011 8
b1011 I
b1011 c
0+
1-
#1310000
b11 e
b1 2
1,
1+
#1320000
b0 e
b111 "
b111 8
b111 I
b111 c
0+
#1330000
b10 2
b111 3
1.
b1 e
b1110 "
b1110 8
b1110 I
b1110 c
1i
1+
#1340000
b1101 "
b1101 8
b1101 I
b1101 c
0+
#1350000
b10 e
1j
1<
1+
#1360000
b1011 "
b1011 8
b1011 I
b1011 c
0+
#1370000
b11 e
1g
1;
1+
#1380000
b0 e
b111 "
b111 8
b111 I
b111 c
0+
#1390000
b1 e
b1110 "
b1110 8
b1110 I
b1110 c
1+
#1400000
b1101 "
b1101 8
b1101 I
b1101 c
0+
0-
#1410000
b11 2
0,
b10 e
1+
#1420000
b1011 "
b1011 8
b1011 I
b1011 c
0+
#1430000
b11 e
0i
1+
#1440000
b0 e
b111 "
b111 8
b111 I
b111 c
0+
#1450000
b1 e
b1110 "
b1110 8
b1110 I
b1110 c
0<
1+
#1460000
b1101 "
b1101 8
b1101 I
b1101 c
0+
#1470000
1=
1h
0g
b10 e
1+
#1480000
b1011 "
b1011 8
b1011 I
b1011 c
0+
#1490000
b10110000 #
b10110000 5
b10110000 :
b10110000 ?
b10110000 k
b10110000 m
b1000 n
b11 e
b111 l
0=
0h
1+
#1500000
b0 e
b111 "
b111 8
b111 I
b111 c
0+
1-
#1510000
b1 e
b1 2
1,
b1110 "
b1110 8
b1110 I
b1110 c
1+
#1520000
b1101 "
b1101 8
b1101 I
b1101 c
0+
#1530000
b10 2
b1000 3
0.
b10 e
1i
1+
#1540000
b1011 "
b1011 8
b1011 I
b1011 c
0+
#1550000
b11 e
0j
1<
1+
#1560000
b0 e
b111 "
b111 8
b111 I
b111 c
0+
#1570000
b1 e
1g
b1110 "
b1110 8
b1110 I
b1110 c
0;
1+
#1580000
b1101 "
b1101 8
b1101 I
b1101 c
0+
#1590000
b10 e
1+
#1600000
b1011 "
b1011 8
b1011 I
b1011 c
0+
0-
#1610000
b11 2
0,
b11 e
1+
#1620000
b0 e
b111 "
b111 8
b111 I
b111 c
0+
#1630000
b1 e
b1110 "
b1110 8
b1110 I
b1110 c
0i
1+
#1640000
b1101 "
b1101 8
b1101 I
b1101 c
0+
#1650000
b10 e
0<
1+
#1660000
b1011 "
b1011 8
b1011 I
b1011 c
0+
#1670000
1=
1h
0g
b11 e
1+
#1680000
b0 e
b111 "
b111 8
b111 I
b111 c
0+
#1690000
b1011000 #
b1011000 5
b1011000 :
b1011000 ?
b1011000 k
b1011000 m
b1001 n
b1 e
b1000 l
0=
0h
b1110 "
b1110 8
b1110 I
b1110 c
1+
#1700000
b1101 "
b1101 8
b1101 I
b1101 c
0+
1-
#1710000
b10 e
b1 2
1,
1+
#1720000
b1011 "
b1011 8
b1011 I
b1011 c
0+
#1730000
b10 2
b1001 3
b11 e
1i
1+
#1740000
b0 e
b111 "
b111 8
b111 I
b111 c
0+
#1750000
b1 e
b1110 "
b1110 8
b1110 I
b1110 c
1<
1+
#1760000
b1101 "
b1101 8
b1101 I
b1101 c
0+
#1770000
b10 e
1g
1+
#1780000
b1011 "
b1011 8
b1011 I
b1011 c
0+
#1790000
b11 e
1+
#1800000
b0 e
b111 "
b111 8
b111 I
b111 c
0+
0-
#1810000
b11 2
0,
b1 e
b1110 "
b1110 8
b1110 I
b1110 c
1+
#1820000
b1101 "
b1101 8
b1101 I
b1101 c
0+
#1830000
b10 e
0i
1+
#1840000
b1011 "
b1011 8
b1011 I
b1011 c
0+
#1850000
b11 e
0<
1+
#1860000
b0 e
b111 "
b111 8
b111 I
b111 c
0+
#1870000
1=
1h
0g
b1 e
b1110 "
b1110 8
b1110 I
b1110 c
1+
#1880000
b1101 "
b1101 8
b1101 I
b1101 c
0+
#1890000
b101100 #
b101100 5
b101100 :
b101100 ?
b101100 k
b101100 m
b1010 n
b10 e
b1001 l
0=
0h
1+
#1900000
b1011 "
b1011 8
b1011 I
b1011 c
0+
1-
#1910000
b11 e
b1 2
1,
1+
#1920000
b0 e
b111 "
b111 8
b111 I
b111 c
0+
#1930000
b10 2
b1010 3
b1 e
b1110 "
b1110 8
b1110 I
b1110 c
1i
1+
#1940000
b1101 "
b1101 8
b1101 I
b1101 c
0+
#1950000
b10 e
1<
1+
#1960000
b1011 "
b1011 8
b1011 I
b1011 c
0+
#1970000
b11 e
1g
1+
#1980000
b0 e
b111 "
b111 8
b111 I
b111 c
0+
#1990000
b1 e
b1110 "
b1110 8
b1110 I
b1110 c
1+
#2000000
b1101 "
b1101 8
b1101 I
b1101 c
0+
0-
#2010000
b11 2
0,
b10 e
1+
#2020000
b1011 "
b1011 8
b1011 I
b1011 c
0+
#2030000
b11 e
0i
1+
#2040000
b0 e
b111 "
b111 8
b111 I
b111 c
0+
#2050000
b1 e
b1110 "
b1110 8
b1110 I
b1110 c
0<
1+
#2060000
b1101 "
b1101 8
b1101 I
b1101 c
0+
#2070000
1=
1h
0g
b10 e
1+
#2080000
b1011 "
b1011 8
b1011 I
b1011 c
0+
#2090000
b10110 #
b10110 5
b10110 :
b10110 ?
b10110 k
b10110 m
b0 n
16
b11 e
b1010 l
0=
0h
1+
#2100000
b0 e
b111 "
b111 8
b111 I
b111 c
0+
1-
#2110000
b1 e
b1 2
1,
b1110 "
b1110 8
b1110 I
b1110 c
1+
#2120000
b1101 "
b1101 8
b1101 I
b1101 c
0+
#2130000
b10 2
b1011 3
1.
b10 e
1i
1+
#2140000
b1011 "
b1011 8
b1011 I
b1011 c
0+
#2150000
b11 e
1j
1<
1+
#2160000
b0 e
b111 "
b111 8
b111 I
b111 c
0+
