Lab2/refactor/seven_segment_controller.v

module seven_segment_controller(
    input clk,
    input reset_n,
    input [31:0] scan_codes,
    output reg [7:0] seven_segment_number,
    output reg [7:0] seven_segment_enable
);

   reg [1:0] seg_counter;
   reg [7:0] single_scan_code;
   localparam shifter = 8;

always @(posedge clk, negedge reset_n) begin

   if(~reset_n) begin
      seg_counter <= 0;


   end else begin
      seg_counter <= seg_counter + 1;


   end // else: !if(~reset_n)


end

   // make a loop for cycling through which letter to flash
   // make a loop to match scan code to seven segment
   always @ (clk) begin

      //shift this in every clk
      single_scan_code = scan_codes[7:0];

      case(single_scan_code)
        8'h45 : seven_segment_number = 8'b11000000; //0

        8'h16 :  seven_segment_number = 8'b11111001; //1

        8'h1e:  seven_segment_number = 8'b10100100; //2

        8'h26:  seven_segment_number = 8'b10110000; //...

        8'h25:  seven_segment_number = 8'b10011001;

        8'h2e:  seven_segment_number = 8'b10010010;

        8'h36: seven_segment_number = 8'b10000010;

        8'h3d: seven_segment_number = 8'b11111000;

        8'h3e: seven_segment_number = 8'b10000000;

        8'h46: seven_segment_number = 8'b10010000; //9

        8'h0 : seven_segment_number = 8'b11111111; //off

        default : seven_segment_number = 8'b10000110; //error

      endcase // case (sel)
   end // always @ (binary_in)


   // Block to send a scancode and flash one of the lights
   // then flash next light
   //reduce states and just shift and add 1 instead.
   always @(clk) begin
      case (seg_counter)
        2'b00: begin
           seven_segment_enable <= 4'b1110;
//           seven_segment_number <= scan_codes[31:24]; //convert follow mapping below
        end
        2'b01: begin
           seven_segment_enable <= 4'b1101;
//           seven_segment_number <= scan_codes[23:16];
        end
        2'b10: begin
           seven_segment_enable <= 4'b1011;
//           seven_segment_number <= scan_codes[15:8];
        end
        2'b11: begin
           seven_segment_enable <= 4'b0111;
//           seven_segment_number <= scan_codes[7:0];
           seg_counter <= 2'b00;
        end
        default: begin
           seven_segment_enable <= 4'b0000;
//           seven_segment_number <= scan_codes[7:0];
        end

      endcase  // case (seg_counter)
   end


localparam SCAN_CODE_0 = 8'h45;

localparam SCAN_CODE_1 = 8'h16;

localparam SCAN_CODE_2 = 8'h1e;

localparam SCAN_CODE_3 = 8'h26;

localparam SCAN_CODE_4 = 8'h25;

localparam SCAN_CODE_5 = 8'h2e;

localparam SCAN_CODE_6 = 8'h36;

localparam SCAN_CODE_7 = 8'h3d;

localparam SCAN_CODE_8 = 8'h3e;

localparam SCAN_CODE_9 = 8'h46;

localparam SCAN_CODE_RESET = 8'h0;

localparam SEVEN_SEGMENT_0 = 8'b1100_0000;
localparam SEVEN_SEGMENT_1 = 8'b1111_1001;
localparam SEVEN_SEGMENT_2 = 8'b1010_0100;
localparam SEVEN_SEGMENT_3 = 8'b1011_0000;
localparam SEVEN_SEGMENT_4 = 8'b1001_1001;
localparam SEVEN_SEGMENT_5 = 8'b1001_0010;
localparam SEVEN_SEGMENT_6 = 8'b1000_0010;
localparam SEVEN_SEGMENT_7 = 8'b1111_1000;
localparam SEVEN_SEGMENT_8 = 8'b1000_0000;
localparam SEVEN_SEGMENT_9 = 8'b1001_0000;
localparam SEVEN_SEGMENT_F = 8'b1000_1110;
localparam SEVEN_SEGMENT_EMPTY = 8'b1111_1111;



endmodule

Lab2/refactor/keyboard_controller.v
module keyboard_controller(
    input clk,
    input reset_n,
    input valid_scan_code,
    input [7:0] scan_code,
    output reg [31:0] scan_codes
);


   reg [1:0] state, next_state;

   // Debug variables
   reg [8:0]  TEST_CTRL_1 = 0;
   reg [8:0]  TEST_CTRL_2 = 0;
   reg [8:0]  TEST_CTRL_3 = 0;
   reg [8:0]  TEST_CTRL_4 = 0;

   // Immediately after negedge valid_scan_code the valid scan code appears on input
   // so it looks like following

   reg [8:0]  temp_code;

   // negedge valid_scan_code
   // scan_code == 16
   // negedge valid_scan_code
   // scan_code == F0
   // negedge valid_scan_code
   // scan_code == 16

   always @(posedge clk, negedge reset_n)
     // Setup if reset
     if (~reset_n) begin
        state <= 0;
        next_state <= 0;
        scan_codes <= 0;
        temp_code <= 0;

     end else begin
        //update state on every clock cycle
        state   <= next_state;
     end

   // valid code looks at something,
   always @(negedge valid_scan_code) begin
      if (~valid_scan_code) begin
         case (state)
           2'b00: begin // we dont enter this state because we reach it one clk cycle too early
              scan_codes = scan_codes << 8;
              next_state = 2'b01;
              temp_code = scan_code;
           end

           2'b01: begin
           if (scan_code == 8'hF0)
             //scan_codes = scan_codes << 8;
              scan_codes[7:0] <= temp_code;
             next_state <= 2'b10;
           end

           2'b10: begin
              if (scan_code == temp_code) begin
              next_state <= 2'b00;
              end else begin
                 next_state <= 2'b00;
                 end
           end


         endcase  // case (state)
      end  // if (valid_code)

end

endmodule

Lab2/refactor/serial_to_scancode.v
module serial_to_scancode(
    input clk,
    input reset_n,
    input sample_ready,
    input serial_data,
    output reg valid_scan_code,
    output reg [7:0] scan_code
);

reg [3:0] counter = 4'b0000;
reg [3:0] next_counter = 4'b0000;

always @(posedge clk or negedge reset_n) begin
    if (~reset_n) begin
        counter <= 4'b0000;
       scan_code <= 0;

    end else if (sample_ready) begin
        counter <= next_counter;
    end
end

always @(counter) begin
    scan_code[6:0] <= scan_code[7:1];
    scan_code[7] <= serial_data;
    valid_scan_code = 1'b0;
    if (counter == 4'b1001) begin // or 4'b1000
        valid_scan_code = 1'b1;
    end
end

always @(counter) begin
    next_counter = counter + 1;
    if (counter == 4'b1010) begin
        next_counter = 4'b0000;
    end
end



endmodule

Lab2/refactor/falling_edge_detector.v
module falling_edge_detector(
    input clk,
    input reset_n,
    input in,
    output reg edge_found
);

   //detect a falling edge on an input
   reg in_d; //one cc delay


   always @(posedge clk or negedge reset_n)
     if(~reset_n) begin
        in_d <= 0;
     end else begin
        in_d <= in;
        edge_found <= (~in && in_d);
     end


endmodule

Lab2/refactor/synchronizer.v
`timescale 1ns / 1ps

module synchronizer(
    input clk,
    input reset_n,
    input unsynched,
    output reg synched
);

reg in_buffed;

  always @ (posedge clk)
  begin
    in_buffed <= unsynched;
    synched <= in_buffed;
  end




endmodule

Lab2/refactor/keyboard_top.v
module keyboard_top(
    input clk,
    input reset_n,
    input keyboard_clk,
    input keyboard_data,
    output [7:0] led_scancode_debug,
    output [7:0] seven_segment_number,
    output [7:0] seven_segment_enable
);

    wire keyboard_clk_synched;
    wire keyboard_data_synched;

    wire keyboard_clk_edge_found;

    wire valid_scan_code;
    wire [7:0] scan_code;
    wire [31:0] scan_codes;
    

    synchronizer kb_clk_synchronizer(
        .clk(clk),
        .reset_n(reset_n),
        .unsynched(keyboard_clk),
        .synched(keyboard_clk_synched)
    );

    synchronizer kb_data_synchronizer(
        .clk(clk),
        .reset_n(reset_n),
        .unsynched(keyboard_data),
        .synched(keyboard_data_synched)
    );   

    falling_edge_detector kb_clk_edge_detector(
        .clk(clk),
        .reset_n(reset_n),
        .in(keyboard_clk_synched),
        .edge_found(keyboard_clk_edge_found)
    );
    
    serial_to_scancode serial_to_scancode_converter(
        .clk(clk),
        .reset_n(reset_n),
        .sample_ready(keyboard_clk_edge_found),
        .serial_data(keyboard_data_synched),
        .valid_scan_code(valid_scan_code),
        .scan_code(scan_code)
    );    

    keyboard_controller inst_keyboard_controller(
        .clk(clk),
        .reset_n(reset_n),
        .valid_scan_code(valid_scan_code),
        .scan_code(scan_code),
        .scan_codes(scan_codes)
    );
    
    seven_segment_controller inst_seven_segment_controller(
        .clk(clk),
        .reset_n(reset_n),
        .scan_codes(scan_codes),  
        .seven_segment_number(seven_segment_number),
        .seven_segment_enable(seven_segment_enable)          
    );

    assign led_scancode_debug = scan_code;

endmodule

Lab2/refactor/testbench_top.v
`timescale 1ns / 1ps


module testbench_top();
    localparam INPUT_FILE = "input.txt";

    localparam INIT = 3'b000;
    localparam SHIFT = 3'b001;
    localparam WAIT = 3'b010;
    localparam WAIT2 = 3'b011;
    localparam FINISH = 3'b100;

    localparam NUM_KEYS = 12;

    reg [2:0] state;

    reg [7:0] memory [0:NUM_KEYS-1]; // 8 bit memory with 16 entries
    integer memory_index = 0;

    reg clk = 1'b0;
    reg reset_n = 1'b0;

    reg clk_slow = 1'b0;
    reg clk_keyboard = 1'b1;
    reg data_keyboard = 1'b0;

    wire [7:0] scan_code_debug;
    wire [7:0] seven_segment_number;
    wire [7:0] seven_segment_enable;

    reg [32:0] key_all;
    reg start_shifting = 1'b0;
    integer bit_index = 0;


    keyboard_top inst_keyboard_top(
        .clk(clk),
        .reset_n(reset_n),
        .keyboard_clk(clk_keyboard),
        .keyboard_data(data_keyboard),
        .led_scancode_debug(scan_code_debug),
        .seven_segment_number(seven_segment_number),
        .seven_segment_enable(seven_segment_enable)
    );


    always #10 clk = ~clk;
    always #100 clk_slow = ~clk_slow;


    initial begin
        $readmemh(INPUT_FILE, memory);
           $dumpfile("test.vcd");
           $dumpvars(0,testbench_top);


        reset_n = 1'b0;
        @(negedge clk);
        @(negedge clk);
        @(negedge clk);
        reset_n = 1'b1;
    end


    always @(posedge clk or negedge reset_n)
    begin
        if (!reset_n) begin
            data_keyboard <= 1'b0;
            key_all <= 0;
            memory_index <= 0;
            start_shifting <= 1'b0;
            bit_index <= 0;
            clk_keyboard <= 1'b1;
            state <= INIT;
        end else begin
            case (state)
                INIT:
                begin
                    key_all <= {1'b11, memory[memory_index], 2'b0, 1'b11, 8'hf0, 2'b0, 1'b11, memory[memory_index], 2'b0};
                    memory_index <= memory_index + 1;
                    state <= SHIFT;
                    bit_index <= 0;
                end

                SHIFT:
                begin
                    data_keyboard <= key_all[bit_index];
                    bit_index <= bit_index + 1;
                    state <= WAIT;
                end

                WAIT:
                begin
                    if (!clk_slow) begin
                        clk_keyboard <= 1'b0;
                        state <= WAIT2;
                    end
                end

                WAIT2:
                begin
                    if (clk_slow) begin
                        clk_keyboard <= 1'b1;
                        state <= SHIFT;
                        if (bit_index == 32) begin
                            state <= INIT;
                            if (memory_index == NUM_KEYS) begin
                                state <= FINISH;
                            end
                        end
                    end
                end

                FINISH:
                begin
                    $display("Finished!");
                   $finish;

                    $stop;
                end
            endcase
        end
    end


    always @(posedge clk_keyboard)
    begin
        if (bit_index == 12 & scan_code_debug != memory[memory_index-1]) begin
            $display("Failure!");
            $display("DUT Scan code = %x is not equal to expected = %x!", scan_code_debug, memory[memory_index-1]);
           //        $finish;
           // $stop;
        end
    end

endmodule

Lab2/refactor/test.vcd
$date
	Tue Sep 19 11:21:59 2023
$end
$version
	Icarus Verilog
$end
$timescale
	1ps
$end
$scope module testbench_top $end
$var wire 8 ! seven_segment_number [7:0] $end
$var wire 8 " seven_segment_enable [7:0] $end
$var wire 8 # scan_code_debug [7:0] $end
$var parameter 3 $ FINISH $end
$var parameter 3 % INIT $end
$var parameter 72 & INPUT_FILE $end
$var parameter 32 ' NUM_KEYS $end
$var parameter 3 ( SHIFT $end
$var parameter 3 ) WAIT $end
$var parameter 3 * WAIT2 $end
$var reg 1 + clk $end
$var reg 1 , clk_keyboard $end
$var reg 1 - clk_slow $end
$var reg 1 . data_keyboard $end
$var reg 33 / key_all [32:0] $end
$var reg 1 0 reset_n $end
$var reg 1 1 start_shifting $end
$var reg 3 2 state [2:0] $end
$var integer 32 3 bit_index [31:0] $end
$var integer 32 4 memory_index [31:0] $end
$scope module inst_keyboard_top $end
$var wire 1 + clk $end
$var wire 1 , keyboard_clk $end
$var wire 1 . keyboard_data $end
$var wire 8 5 led_scancode_debug [7:0] $end
$var wire 1 0 reset_n $end
$var wire 1 6 valid_scan_code $end
$var wire 8 7 seven_segment_number [7:0] $end
$var wire 8 8 seven_segment_enable [7:0] $end
$var wire 32 9 scan_codes [31:0] $end
$var wire 8 : scan_code [7:0] $end
$var wire 1 ; keyboard_data_synched $end
$var wire 1 < keyboard_clk_synched $end
$var wire 1 = keyboard_clk_edge_found $end
$scope module inst_keyboard_controller $end
$var wire 1 + clk $end
$var wire 1 0 reset_n $end
$var wire 1 6 valid_scan_code $end
$var wire 8 > scan_code [7:0] $end
$var reg 9 ? TEST_CTRL_1 [8:0] $end
$var reg 9 @ TEST_CTRL_2 [8:0] $end
$var reg 9 A TEST_CTRL_3 [8:0] $end
$var reg 9 B TEST_CTRL_4 [8:0] $end
$var reg 2 C next_state [1:0] $end
$var reg 32 D scan_codes [31:0] $end
$var reg 2 E state [1:0] $end
$var reg 9 F temp_code [8:0] $end
$upscope $end
$scope module inst_seven_segment_controller $end
$var wire 1 + clk $end
$var wire 1 0 reset_n $end
$var wire 32 G scan_codes [31:0] $end
$var parameter 8 H SCAN_CODE_0 $end
$var parameter 8 I SCAN_CODE_1 $end
$var parameter 8 J SCAN_CODE_2 $end
$var parameter 8 K SCAN_CODE_3 $end
$var parameter 8 L SCAN_CODE_4 $end
$var parameter 8 M SCAN_CODE_5 $end
$var parameter 8 N SCAN_CODE_6 $end
$var parameter 8 O SCAN_CODE_7 $end
$var parameter 8 P SCAN_CODE_8 $end
$var parameter 8 Q SCAN_CODE_9 $end
$var parameter 8 R SCAN_CODE_RESET $end
$var parameter 8 S SEVEN_SEGMENT_0 $end
$var parameter 8 T SEVEN_SEGMENT_1 $end
$var parameter 8 U SEVEN_SEGMENT_2 $end
$var parameter 8 V SEVEN_SEGMENT_3 $end
$var parameter 8 W SEVEN_SEGMENT_4 $end
$var parameter 8 X SEVEN_SEGMENT_5 $end
$var parameter 8 Y SEVEN_SEGMENT_6 $end
$var parameter 8 Z SEVEN_SEGMENT_7 $end
$var parameter 8 [ SEVEN_SEGMENT_8 $end
$var parameter 8 \ SEVEN_SEGMENT_9 $end
$var parameter 8 ] SEVEN_SEGMENT_EMPTY $end
$var parameter 8 ^ SEVEN_SEGMENT_F $end
$var parameter 32 _ shifter $end
$var reg 2 ` seg_counter [1:0] $end
$var reg 8 a seven_segment_enable [7:0] $end
$var reg 8 b seven_segment_number [7:0] $end
$var reg 8 c single_scan_code [7:0] $end
$upscope $end
$scope module kb_clk_edge_detector $end
$var wire 1 + clk $end
$var wire 1 0 reset_n $end
$var wire 1 < in $end
$var reg 1 = edge_found $end
$var reg 1 d in_d $end
$upscope $end
$scope module kb_clk_synchronizer $end
$var wire 1 + clk $end
$var wire 1 0 reset_n $end
$var wire 1 , unsynched $end
$var reg 1 e in_buffed $end
$var reg 1 < synched $end
$upscope $end
$scope module kb_data_synchronizer $end
$var wire 1 + clk $end
$var wire 1 0 reset_n $end
$var wire 1 . unsynched $end
$var reg 1 f in_buffed $end
$var reg 1 ; synched $end
$upscope $end
$scope module serial_to_scancode_converter $end
$var wire 1 + clk $end
$var wire 1 0 reset_n $end
$var wire 1 = sample_ready $end
$var wire 1 ; serial_data $end
$var reg 4 g counter [3:0] $end
$var reg 4 h next_counter [3:0] $end
$var reg 8 i scan_code [7:0] $end
$var reg 1 6 valid_scan_code $end
$upscope $end
$upscope $end
$upscope $end
$enddefinitions $end
$comment Show the parameter values. $end
$dumpall
b1000 _
b10001110 ^
b11111111 ]
b10010000 \
b10000000 [
b11111000 Z
b10000010 Y
b10010010 X
b10011001 W
b10110000 V
b10100100 U
b11111001 T
b11000000 S
b0 R
b1000110 Q
b111110 P
b111101 O
b110110 N
b101110 M
b100101 L
b100110 K
b11110 J
b10110 I
b1000101 H
b11 *
b10 )
b1 (
b1100 '
b11010010110111001110000011101010111010000101110011101000111100001110100 &
b0 %
b100 $
$end
#0
$dumpvars
bx i
b1 h
b0 g
xf
xe
0d
bx c
b10000110 b
b0 a
b0 `
b0 G
bx F
b0 E
b0 D
b0 C
b0 B
b0 A
b0 @
b0 ?
bx >
x=
x<
x;
bx :
b0 9
b0 8
b10000110 7
06
bx 5
b0 4
b0 3
bx 2
01
00
bx /
0.
0-
1,
0+
bx #
b0 "
b10000110 !
$end
#10000
b0 2
b0 /
b1110 "
b1110 8
b1110 a
1e
0f
b11111111 !
b11111111 7
b11111111 b
b0 c
1+
#20000
0+
#30000
0;
1<
1+
#40000
0+
#50000
1+
#60000
10
0+
#70000
0=
1d
b1 `
b1 2
b1 4
b100010110001111100000010001011000 /
1+
#80000
b1101 "
b1101 8
b1101 a
0+
#90000
b10 2
b1 3
b10 `
1+
#100000
b1011 "
b1011 8
b1011 a
0+
1-
#110000
b11 `
1+
#120000
b0 `
b111 "
b111 8
b111 a
0+
#130000
b1 `
b1110 "
b1110 8
b1110 a
1+
#140000
b1101 "
b1101 8
b1101 a
0+
#150000
b10 `
1+
#160000
b1011 "
b1011 8
b1011 a
0+
#170000
b11 `
1+
#180000
b0 `
b111 "
b111 8
b111 a
0+
#190000
b1 `
b1110 "
b1110 8
b1110 a
1+
#200000
b1101 "
b1101 8
b1101 a
0+
0-
#210000
b11 2
0,
b10 `
1+
#220000
b1011 "
b1011 8
b1011 a
0+
#230000
b11 `
0e
1+
#240000
b0 `
b111 "
b111 8
b111 a
0+
#250000
b1 `
b1110 "
b1110 8
b1110 a
0<
1+
#260000
b1101 "
b1101 8
b1101 a
0+
#270000
1=
0d
b10 `
1+
#280000
b1011 "
b1011 8
b1011 a
0+
#290000
b0xxxxxxx #
b0xxxxxxx 5
b0xxxxxxx :
b0xxxxxxx >
b0xxxxxxx i
b10 h
b11 `
b1 g
0=
1+
#300000
b0 `
b111 "
b111 8
b111 a
0+
1-
#310000
b1 `
b1 2
1,
b1110 "
b1110 8
b1110 a
1+
#320000
b1101 "
b1101 8
b1101 a
0+
#330000
b10 2
b10 3
b10 `
1e
1+
#340000
b1011 "
b1011 8
b1011 a
0+
#350000
b11 `
1<
1+
#360000
b0 `
b111 "
b111 8
b111 a
0+
#370000
b1 `
1d
b1110 "
b1110 8
b1110 a
1+
#380000
b1101 "
b1101 8
b1101 a
0+
#390000
b10 `
1+
#400000
b1011 "
b1011 8
b1011 a
0+
0-
#410000
b11 2
0,
b11 `
1+
#420000
b0 `
b111 "
b111 8
b111 a
0+
#430000
b1 `
b1110 "
b1110 8
b1110 a
0e
1+
#440000
b1101 "
b1101 8
b1101 a
0+
#450000
b10 `
0<
1+
#460000
b1011 "
b1011 8
b1011 a
0+
#470000
1=
0d
b11 `
1+
#480000
b0 `
b111 "
b111 8
b111 a
0+
#490000
b0xxxxxx #
b0xxxxxx 5
b0xxxxxx :
b0xxxxxx >
b0xxxxxx i
b11 h
b1 `
b10 g
0=
b1110 "
b1110 8
b1110 a
1+
#500000
b1101 "
b1101 8
b1101 a
0+
1-
#510000
b10 `
b1 2
1,
1+
#520000
b1011 "
b1011 8
b1011 a
0+
#530000
b10 2
b11 3
b11 `
1e
1+
#540000
b0 `
b111 "
b111 8
b111 a
0+
#550000
b1 `
b1110 "
b1110 8
b1110 a
1<
1+
#560000
b1101 "
b1101 8
b1101 a
0+
#570000
b10 `
1d
1+
#580000
b1011 "
b1011 8
b1011 a
0+
#590000
b11 `
1+
#600000
b0 `
b111 "
b111 8
b111 a
0+
0-
#610000
b11 2
0,
b1 `
b1110 "
b1110 8
b1110 a
1+
#620000
b1101 "
b1101 8
b1101 a
0+
#630000
b10 `
0e
1+
#640000
b1011 "
b1011 8
b1011 a
0+
#650000
b11 `
0<
1+
#660000
b0 `
b111 "
b111 8
b111 a
0+
#670000
1=
0d
b1 `
b1110 "
b1110 8
b1110 a
1+
#680000
b1101 "
b1101 8
b1101 a
0+
#690000
b0xxxxx #
b0xxxxx 5
b0xxxxx :
b0xxxxx >
b0xxxxx i
b100 h
b10 `
b11 g
0=
1+
#700000
b1011 "
b1011 8
b1011 a
0+
1-
#710000
b11 `
b1 2
1,
1+
#720000
b0 `
b111 "
b111 8
b111 a
0+
#730000
b10 2
b100 3
1.
b1 `
b1110 "
b1110 8
b1110 a
1e
1+
#740000
b1101 "
b1101 8
b1101 a
0+
#750000
b10 `
1f
1<
1+
#760000
b1011 "
b1011 8
b1011 a
0+
#770000
b11 `
1d
1;
1+
#780000
b0 `
b111 "
b111 8
b111 a
0+
#790000
b1 `
b1110 "
b1110 8
b1110 a
1+
#800000
b1101 "
b1101 8
b1101 a
0+
0-
#810000
b11 2
0,
b10 `
1+
#820000
b1011 "
b1011 8
b1011 a
0+
#830000
b11 `
0e
1+
#840000
b0 `
b111 "
b111 8
b111 a
0+
#850000
b1 `
b1110 "
b1110 8
b1110 a
0<
1+
#860000
b1101 "
b1101 8
b1101 a
0+
#870000
1=
0d
b10 `
1+
#880000
b1011 "
b1011 8
b1011 a
0+
#890000
b1000xxxx #
b1000xxxx 5
b1000xxxx :
b1000xxxx >
b1000xxxx i
b101 h
b11 `
b100 g
0=
1+
#900000
b0 `
b111 "
b111 8
b111 a
0+
1-
#910000
b1 `
b1 2
1,
b1110 "
b1110 8
b1110 a
1+
#920000
b1101 "
b1101 8
b1101 a
0+
#930000
b10 2
b101 3
b10 `
1e
1+
#940000
b1011 "
b1011 8
b1011 a
0+
#950000
b11 `
1<
1+
#960000
b0 `
b111 "
b111 8
b111 a
0+
#970000
b1 `
1d
b1110 "
b1110 8
b1110 a
1+
#980000
b1101 "
b1101 8
b1101 a
0+
#990000
b10 `
1+
#1000000
b1011 "
b1011 8
b1011 a
0+
0-
#1010000
b11 2
0,
b11 `
1+
#1020000
b0 `
b111 "
b111 8
b111 a
0+
#1030000
b1 `
b1110 "
b1110 8
b1110 a
0e
1+
#1040000
b1101 "
b1101 8
b1101 a
0+
#1050000
b10 `
0<
1+
#1060000
b1011 "
b1011 8
b1011 a
0+
#1070000
1=
0d
b11 `
1+
#1080000
b0 `
b111 "
b111 8
b111 a
0+
#1090000
b11000xxx #
b11000xxx 5
b11000xxx :
b11000xxx >
b11000xxx i
b110 h
b1 `
b101 g
0=
b1110 "
b1110 8
b1110 a
1+
#1100000
b1101 "
b1101 8
b1101 a
0+
1-
#1110000
b10 `
b1 2
1,
1+
#1120000
b1011 "
b1011 8
b1011 a
0+
#1130000
b10 2
b110 3
0.
b11 `
1e
1+
#1140000
b0 `
b111 "
b111 8
b111 a
0+
#1150000
b1 `
b1110 "
b1110 8
b1110 a
0f
1<
1+
#1160000
b1101 "
b1101 8
b1101 a
0+
#1170000
b10 `
1d
0;
1+
#1180000
b1011 "
b1011 8
b1011 a
0+
#1190000
b11 `
1+
#1200000
b0 `
b111 "
b111 8
b111 a
0+
0-
#1210000
b11 2
0,
b1 `
b1110 "
b1110 8
b1110 a
1+
#1220000
b1101 "
b1101 8
b1101 a
0+
#1230000
b10 `
0e
1+
#1240000
b1011 "
b1011 8
b1011 a
0+
#1250000
b11 `
0<
1+
#1260000
b0 `
b111 "
b111 8
b111 a
0+
#1270000
1=
0d
b1 `
b1110 "
b1110 8
b1110 a
1+
#1280000
b1101 "
b1101 8
b1101 a
0+
#1290000
b11000xx #
b11000xx 5
b11000xx :
b11000xx >
b11000xx i
b111 h
b10 `
b110 g
0=
1+
#1300000
b1011 "
b1011 8
b1011 a
0+
1-
#1310000
b11 `
b1 2
1,
1+
#1320000
b0 `
b111 "
b111 8
b111 a
0+
#1330000
b10 2
b111 3
1.
b1 `
b1110 "
b1110 8
b1110 a
1e
1+
#1340000
b1101 "
b1101 8
b1101 a
0+
#1350000
b10 `
1f
1<
1+
#1360000
b1011 "
b1011 8
b1011 a
0+
#1370000
b11 `
1d
1;
1+
#1380000
b0 `
b111 "
b111 8
b111 a
0+
#1390000
b1 `
b1110 "
b1110 8
b1110 a
1+
#1400000
b1101 "
b1101 8
b1101 a
0+
0-
#1410000
b11 2
0,
b10 `
1+
#1420000
b1011 "
b1011 8
b1011 a
0+
#1430000
b11 `
0e
1+
#1440000
b0 `
b111 "
b111 8
b111 a
0+
#1450000
b1 `
b1110 "
b1110 8
b1110 a
0<
1+
#1460000
b1101 "
b1101 8
b1101 a
0+
#1470000
1=
0d
b10 `
1+
#1480000
b1011 "
b1011 8
b1011 a
0+
#1490000
b1011000x #
b1011000x 5
b1011000x :
b1011000x >
b1011000x i
b1000 h
b11 `
b111 g
0=
1+
#1500000
b0 `
b111 "
b111 8
b111 a
0+
1-
#1510000
b1 `
b1 2
1,
b1110 "
b1110 8
b1110 a
1+
#1520000
b1101 "
b1101 8
b1101 a
0+
#1530000
b10 2
b1000 3
0.
b10 `
1e
1+
#1540000
b1011 "
b1011 8
b1011 a
0+
#1550000
b11 `
0f
1<
1+
#1560000
b0 `
b111 "
b111 8
b111 a
0+
#1570000
b1 `
1d
b1110 "
b1110 8
b1110 a
0;
1+
#1580000
b1101 "
b1101 8
b1101 a
0+
#1590000
b10 `
1+
#1600000
b1011 "
b1011 8
b1011 a
0+
0-
#1610000
b11 2
0,
b11 `
1+
#1620000
b0 `
b111 "
b111 8
b111 a
0+
#1630000
b1 `
b1110 "
b1110 8
b1110 a
0e
1+
#1640000
b1101 "
b1101 8
b1101 a
0+
#1650000
b10 `
0<
1+
#1660000
b1011 "
b1011 8
b1011 a
0+
#1670000
1=
0d
b11 `
1+
#1680000
b0 `
b111 "
b111 8
b111 a
0+
#1690000
b1011000 #
b1011000 5
b1011000 :
b1011000 >
b1011000 i
b1001 h
b1 `
b1000 g
0=
b1110 "
b1110 8
b1110 a
1+
#1700000
b1101 "
b1101 8
b1101 a
0+
1-
#1710000
b10 `
b1 2
1,
1+
#1720000
b1011 "
b1011 8
b1011 a
0+
#1730000
b10 2
b1001 3
b11 `
1e
1+
#1740000
b0 `
b111 "
b111 8
b111 a
0+
#1750000
b1 `
b1110 "
b1110 8
b1110 a
1<
1+
#1760000
b1101 "
b1101 8
b1101 a
0+
#1770000
b10 `
1d
1+
#1780000
b1011 "
b1011 8
b1011 a
0+
#1790000
b11 `
1+
#1800000
b0 `
b111 "
b111 8
b111 a
0+
0-
#1810000
b11 2
0,
b1 `
b1110 "
b1110 8
b1110 a
1+
#1820000
b1101 "
b1101 8
b1101 a
0+
#1830000
b10 `
0e
1+
#1840000
b1011 "
b1011 8
b1011 a
0+
#1850000
b11 `
0<
1+
#1860000
b0 `
b111 "
b111 8
b111 a
0+
#1870000
1=
0d
b1 `
b1110 "
b1110 8
b1110 a
1+
#1880000
b1101 "
b1101 8
b1101 a
0+
#1890000
b101100 #
b101100 5
b101100 :
b101100 >
b101100 i
b1010 h
b10 `
b1001 g
0=
1+
#1900000
b1011 "
b1011 8
b1011 a
0+
1-
#1910000
b11 `
b1 2
1,
1+
#1920000
b0 `
b111 "
b111 8
b111 a
0+
#1930000
b10 2
b1010 3
b1 `
b1110 "
b1110 8
b1110 a
1e
1+
#1940000
b1101 "
b1101 8
b1101 a
0+
#1950000
b10 `
1<
1+
#1960000
b1011 "
b1011 8
b1011 a
0+
#1970000
b11 `
1d
1+
#1980000
b0 `
b111 "
b111 8
b111 a
0+
#1990000
b1 `
b1110 "
b1110 8
b1110 a
1+
#2000000
b1101 "
b1101 8
b1101 a
0+
0-
#2010000
b11 2
0,
b10 `
1+
#2020000
b1011 "
b1011 8
b1011 a
0+
#2030000
b11 `
0e
1+
#2040000
b0 `
b111 "
b111 8
b111 a
0+
#2050000
b1 `
b1110 "
b1110 8
b1110 a
0<
1+
#2060000
b1101 "
b1101 8
b1101 a
0+
#2070000
1=
0d
b10 `
1+
#2080000
b1011 "
b1011 8
b1011 a
0+
#2090000
b10110 #
b10110 5
b10110 :
b10110 >
b10110 i
b0 h
16
b11 `
b1010 g
0=
1+
#2100000
b0 `
b111 "
b111 8
b111 a
0+
1-
#2110000
b1 `
b1 2
1,
b1110 "
b1110 8
b1110 a
1+
#2120000
b1101 "
b1101 8
b1101 a
0+
#2130000
b10 2
b1011 3
1.
b10 `
1e
1+
#2140000
b1011 "
b1011 8
b1011 a
0+
#2150000
b11 `
1f
1<
1+
#2160000
b0 `
b111 "
b111 8
b111 a
0+
#2170000
b1 `
1d
b1110 "
b1110 8
b1110 a
1;
1+
#2180000
b1101 "
b1101 8
b1101 a
0+
#2190000
b10 `
1+
#2200000
b1011 "
b1011 8
b1011 a
0+
0-
#2210000
b11 2
0,
b11 `
1+
#2220000
b0 `
b111 "
b111 8
b111 a
0+
#2230000
b1 `
b1110 "
b1110 8
b1110 a
0e
1+
#2240000
b1101 "
b1101 8
b1101 a
0+
#2250000
b10 `
0<
1+
#2260000
b1011 "
b1011 8
b1011 a
0+
#2270000
1=
0d
b11 `
1+
#2280000
b0 `
b111 "
b111 8
b111 a
0+
#2290000
b10001011 #
b10001011 5
b10001011 :
b10001011 >
b10001011 i
b10110 F
b1 C
06
b1 h
b1 `
b0 g
0=
b1110 "
b1110 8
b1110 a
1+
#2300000
b1101 "
b1101 8
b1101 a
0+
1-
#2310000
b1 E
b10 `
b1 2
1,
1+
#2320000
b1011 "
b1011 8
b1011 a
0+
#2330000
b10 2
b1100 3
0.
b11 `
1e
1+
#2340000
b0 `
b111 "
b111 8
b111 a
0+
#2350000
b1 `
b1110 "
b1110 8
b1110 a
0f
1<
1+
#2360000
b1101 "
b1101 8
b1101 a
0+
#2370000
b10 `
1d
0;
1+
#2380000
b1011 "
b1011 8
b1011 a
0+
#2390000
b11 `
1+
#2400000
b0 `
b111 "
b111 8
b111 a
0+
0-
#2410000
b11 2
0,
b1 `
b1110 "
b1110 8
b1110 a
1+
#2420000
b1101 "
b1101 8
b1101 a
0+
#2430000
b10 `
0e
1+
#2440000
b1011 "
b1011 8
b1011 a
0+
#2450000
b11 `
0<
1+
#2460000
b0 `
b111 "
b111 8
b111 a
0+
#2470000
1=
0d
b1 `
b1110 "
b1110 8
b1110 a
1+
#2480000
b1101 "
b1101 8
b1101 a
0+
#2490000
b1000101 #
b1000101 5
b1000101 :
b1000101 >
b1000101 i
b10 h
b10 `
b1 g
0=
1+
#2500000
b1011 "
b1011 8
b1011 a
0+
1-
#2510000
b11 `
b1 2
1,
1+
#2520000
b0 `
b111 "
b111 8
b111 a
0+
#2530000
b10 2
b1101 3
b1 `
b1110 "
b1110 8
b1110 a
1e
1+
#2540000
b1101 "
b1101 8
b1101 a
0+
#2550000
b10 `
1<
1+
