Lab2/refactor/seven_segment_controller.v

module seven_segment_controller(
    input clk,
    input reset_n,
    input [31:0] scan_codes,
    output reg [7:0] seven_segment_number,
    output reg [7:0] seven_segment_enable
);


localparam SCAN_CODE_0 = 8'h45;
localparam SCAN_CODE_1 = 8'h16;
localparam SCAN_CODE_2 = 8'h1e;
localparam SCAN_CODE_3 = 8'h26;
localparam SCAN_CODE_4 = 8'h25;
localparam SCAN_CODE_5 = 8'h2e;
localparam SCAN_CODE_6 = 8'h36;
localparam SCAN_CODE_7 = 8'h3d;
localparam SCAN_CODE_8 = 8'h3e;
localparam SCAN_CODE_9 = 8'h46;
localparam SCAN_CODE_RESET = 8'h0;

localparam SEVEN_SEGMENT_0 = 8'b1100_0000;
localparam SEVEN_SEGMENT_1 = 8'b1111_1001;
localparam SEVEN_SEGMENT_2 = 8'b1010_0100;
localparam SEVEN_SEGMENT_3 = 8'b1011_0000;
localparam SEVEN_SEGMENT_4 = 8'b1001_1001;
localparam SEVEN_SEGMENT_5 = 8'b1001_0010;
localparam SEVEN_SEGMENT_6 = 8'b1000_0010;
localparam SEVEN_SEGMENT_7 = 8'b1111_1000;
localparam SEVEN_SEGMENT_8 = 8'b1000_0000;
localparam SEVEN_SEGMENT_9 = 8'b1001_0000;
localparam SEVEN_SEGMENT_F = 8'b1000_1110;
localparam SEVEN_SEGMENT_EMPTY = 8'b1111_1111;


endmodule

Lab2/refactor/keyboard_controller.v
module keyboard_controller(
    input clk,
    input reset_n,
    input valid_scan_code,
    input [7:0] scan_code,
    output reg [31:0] scan_codes
);


   reg [1:0] state, next_state;

   // Debug variables
   reg [8:0]  TEST_CTRL_1 = 0;
   reg [8:0]  TEST_CTRL_2 = 0;
   reg [8:0]  TEST_CTRL_3 = 0;
   reg [8:0]  TEST_CTRL_4 = 0;

   // Immediately after negedge valid_scan_code the valid scan code appears on input
   // so it looks like following

   // negedge valid_scan_code
   // scan_code == 16
   // negedge valid_scan_code
   // scan_code == F0
   // negedge valid_scan_code
   // scan_code == 16

   always @(posedge clk, negedge reset_n)
     // Setup if reset
     if (~reset_n) begin
        state <= 0;
        next_state <= 0;  //not popular
        scan_codes <= 0;


     end else begin
        //update state on every clock cycle
        state   <= next_state;
     end

   // valid code looks at something,
   always @(posedge valid_scan_code or negedge valid_scan_code or valid_scan_code) begin

      if (valid_scan_code) begin
         case (state)

           2'b00: begin // we dont enter this state because we reach it one clk cycle too early
              if (scan_code == 8'h0F) begin //next scan code will be a make code and sent to the display
                 next_state <= 1;

              end else begin

              end
           end

           2'b01: begin //only enter here if prev scan code was 240 == break
              scan_codes[7:0] <= scan_codes;
              next_state <= 0;
           end

         endcase  // case (state)
      end  // if (valid_code)

end

endmodule

Lab2/refactor/serial_to_scancode.v
module serial_to_scancode(
    input clk,
    input reset_n,
    input sample_ready,
    input serial_data,
    output reg valid_scan_code,
    output reg [7:0] scan_code
);


reg [3:0] counter = 4'b0000;
reg [3:0] next_counter = 4'b0000;

always @(posedge clk or negedge reset_n) begin
    if (~reset_n) begin
        counter <= 4'b0000;
       scan_code <= 0;

    end else if (sample_ready) begin
        counter <= next_counter;
    end
end

always @(counter) begin
    scan_code[6:0] <= scan_code[7:1];
    scan_code[7] <= serial_data;
    valid_scan_code = 1'b0;
    if (counter == 4'b1010) begin
        valid_scan_code = 1'b1;
    end
end

always @(counter) begin
    next_counter = counter + 1;
    if (counter == 4'b1010) begin
        next_counter = 4'b0000;
    end
end


endmodule

Lab2/refactor/falling_edge_detector.v
module falling_edge_detector(
    input clk,
    input reset_n,
    input in,
    output reg edge_found
);

   //detect a falling edge on an input
   reg in_d; //one cc delay


   always @(posedge clk or negedge reset_n)
     if(~reset_n) begin
        in_d <= 0;
     end else begin
        in_d <= in;
        edge_found <= (~in && in_d);
     end


endmodule

Lab2/refactor/synchronizer.v
`timescale 1ns / 1ps

module synchronizer(
    input clk,
    input reset_n,
    input unsynched,
    output reg synched
);

reg in_buffed;

  always @ (posedge clk)
  begin
    in_buffed <= unsynched;
    synched <= in_buffed;
  end




endmodule

Lab2/refactor/keyboard_top.v
module keyboard_top(
    input clk,
    input reset_n,
    input keyboard_clk,
    input keyboard_data,
    output [7:0] led_scancode_debug,
    output [7:0] seven_segment_number,
    output [7:0] seven_segment_enable
);

    wire keyboard_clk_synched;
    wire keyboard_data_synched;

    wire keyboard_clk_edge_found;

    wire valid_scan_code;
    wire [7:0] scan_code;
    wire [31:0] scan_codes;
    

    synchronizer kb_clk_synchronizer(
        .clk(clk),
        .reset_n(reset_n),
        .unsynched(keyboard_clk),
        .synched(keyboard_clk_synched)
    );

    synchronizer kb_data_synchronizer(
        .clk(clk),
        .reset_n(reset_n),
        .unsynched(keyboard_data),
        .synched(keyboard_data_synched)
    );   

    falling_edge_detector kb_clk_edge_detector(
        .clk(clk),
        .reset_n(reset_n),
        .in(keyboard_clk_synched),
        .edge_found(keyboard_clk_edge_found)
    );
    
    serial_to_scancode serial_to_scancode_converter(
        .clk(clk),
        .reset_n(reset_n),
        .sample_ready(keyboard_clk_edge_found),
        .serial_data(keyboard_data_synched),
        .valid_scan_code(valid_scan_code),
        .scan_code(scan_code)
    );    

    keyboard_controller inst_keyboard_controller(
        .clk(clk),
        .reset_n(reset_n),
        .valid_scan_code(valid_scan_code),
        .scan_code(scan_code),
        .scan_codes(scan_codes)
    );
    
    seven_segment_controller inst_seven_segment_controller(
        .clk(clk),
        .reset_n(reset_n),
        .scan_codes(scan_codes),  
        .seven_segment_number(seven_segment_number),
        .seven_segment_enable(seven_segment_enable)          
    );

    assign led_scancode_debug = scan_code;

endmodule

Lab2/refactor/testbench_top.v
`timescale 1ns / 1ps


module testbench_top();
    localparam INPUT_FILE = "input.txt";

    localparam INIT = 3'b000;
    localparam SHIFT = 3'b001;
    localparam WAIT = 3'b010;
    localparam WAIT2 = 3'b011;
    localparam FINISH = 3'b100;

    localparam NUM_KEYS = 12;

    reg [2:0] state;

    reg [7:0] memory [0:NUM_KEYS-1]; // 8 bit memory with 16 entries
    integer memory_index = 0;

    reg clk = 1'b0;
    reg reset_n = 1'b0;

    reg clk_slow = 1'b0;
    reg clk_keyboard = 1'b1;
    reg data_keyboard = 1'b0;

    wire [7:0] scan_code_debug;
    wire [7:0] seven_segment_number;
    wire [7:0] seven_segment_enable;

    reg [32:0] key_all;
    reg start_shifting = 1'b0;
    integer bit_index = 0;


    keyboard_top inst_keyboard_top(
        .clk(clk),
        .reset_n(reset_n),
        .keyboard_clk(clk_keyboard),
        .keyboard_data(data_keyboard),
        .led_scancode_debug(scan_code_debug),
        .seven_segment_number(seven_segment_number),
        .seven_segment_enable(seven_segment_enable)
    );


    always #10 clk = ~clk;
    always #100 clk_slow = ~clk_slow;


    initial begin
        $readmemh(INPUT_FILE, memory);
           $dumpfile("test.vcd");
           $dumpvars(0,testbench_top);


        reset_n = 1'b0;
        @(negedge clk);
        @(negedge clk);
        @(negedge clk);
        reset_n = 1'b1;
    end


    always @(posedge clk or negedge reset_n)
    begin
        if (!reset_n) begin
            data_keyboard <= 1'b0;
            key_all <= 0;
            memory_index <= 0;
            start_shifting <= 1'b0;
            bit_index <= 0;
            clk_keyboard <= 1'b1;
            state <= INIT;
        end else begin
            case (state)
                INIT:
                begin
                    key_all <= {1'b0, memory[memory_index], 1'b1, 2'b10, 8'hf0, 2'b11, 1'b0, memory[memory_index], 2'b11};
                    memory_index <= memory_index + 1;
                    state <= SHIFT;
                    bit_index <= 0;
                end

                SHIFT:
                begin
                    data_keyboard <= key_all[bit_index];
                    bit_index <= bit_index + 1;
                    state <= WAIT;
                end

                WAIT:
                begin
                    if (!clk_slow) begin
                        clk_keyboard <= 1'b0;
                        state <= WAIT2;
                    end
                end

                WAIT2:
                begin
                    if (clk_slow) begin
                        clk_keyboard <= 1'b1;
                        state <= SHIFT;
                        if (bit_index == 33) begin
                            state <= INIT;
                            if (memory_index == NUM_KEYS) begin
                                state <= FINISH;
                            end
                        end
                    end
                end

                FINISH:
                begin
                    $display("Finished!");
                   $finish;

                    $stop;
                end
            endcase
        end
    end


    always @(posedge clk_keyboard)
    begin
        if (bit_index == 12 & scan_code_debug != memory[memory_index-1]) begin
            $display("Failure!");
            $display("DUT Scan code = %x is not equal to expected = %x!", scan_code_debug, memory[memory_index-1]);
           //        $finish;
           // $stop;
        end
        else if (bit_index == 12 & scan_code_debug == memory[memory_index-1]) begin
            $display("Sucess!");
            $display("DUT Scan code = %x is equal to expected = %x!", scan_code_debug, memory[memory_index-1]);
           //        $finish;
           // $stop;
        end
    end

endmodule

Lab2/refactor/test.vcd
$date
	Mon Sep 18 17:06:31 2023
$end
$version
	Icarus Verilog
$end
$timescale
	1ps
$end
$scope module testbench_top $end
$var wire 8 ! seven_segment_number [7:0] $end
$var wire 8 " seven_segment_enable [7:0] $end
$var wire 8 # scan_code_debug [7:0] $end
$var parameter 3 $ FINISH $end
$var parameter 3 % INIT $end
$var parameter 72 & INPUT_FILE $end
$var parameter 32 ' NUM_KEYS $end
$var parameter 3 ( SHIFT $end
$var parameter 3 ) WAIT $end
$var parameter 3 * WAIT2 $end
$var reg 1 + clk $end
$var reg 1 , clk_keyboard $end
$var reg 1 - clk_slow $end
$var reg 1 . data_keyboard $end
$var reg 33 / key_all [32:0] $end
$var reg 1 0 reset_n $end
$var reg 1 1 start_shifting $end
$var reg 3 2 state [2:0] $end
$var integer 32 3 bit_index [31:0] $end
$var integer 32 4 memory_index [31:0] $end
$scope module inst_keyboard_top $end
$var wire 1 + clk $end
$var wire 1 , keyboard_clk $end
$var wire 1 . keyboard_data $end
$var wire 8 5 led_scancode_debug [7:0] $end
$var wire 1 0 reset_n $end
$var wire 1 6 valid_scan_code $end
$var wire 8 7 seven_segment_number [7:0] $end
$var wire 8 8 seven_segment_enable [7:0] $end
$var wire 32 9 scan_codes [31:0] $end
$var wire 8 : scan_code [7:0] $end
$var wire 1 ; keyboard_data_synched $end
$var wire 1 < keyboard_clk_synched $end
$var wire 1 = keyboard_clk_edge_found $end
$scope module inst_keyboard_controller $end
$var wire 1 + clk $end
$var wire 1 0 reset_n $end
$var wire 1 6 valid_scan_code $end
$var wire 8 > scan_code [7:0] $end
$var reg 9 ? TEST_CTRL_1 [8:0] $end
$var reg 9 @ TEST_CTRL_2 [8:0] $end
$var reg 9 A TEST_CTRL_3 [8:0] $end
$var reg 9 B TEST_CTRL_4 [8:0] $end
$var reg 2 C next_state [1:0] $end
$var reg 32 D scan_codes [31:0] $end
$var reg 2 E state [1:0] $end
$upscope $end
$scope module inst_seven_segment_controller $end
$var wire 1 + clk $end
$var wire 1 0 reset_n $end
$var wire 32 F scan_codes [31:0] $end
$var parameter 8 G SCAN_CODE_0 $end
$var parameter 8 H SCAN_CODE_1 $end
$var parameter 8 I SCAN_CODE_2 $end
$var parameter 8 J SCAN_CODE_3 $end
$var parameter 8 K SCAN_CODE_4 $end
$var parameter 8 L SCAN_CODE_5 $end
$var parameter 8 M SCAN_CODE_6 $end
$var parameter 8 N SCAN_CODE_7 $end
$var parameter 8 O SCAN_CODE_8 $end
$var parameter 8 P SCAN_CODE_9 $end
$var parameter 8 Q SCAN_CODE_RESET $end
$var parameter 8 R SEVEN_SEGMENT_0 $end
$var parameter 8 S SEVEN_SEGMENT_1 $end
$var parameter 8 T SEVEN_SEGMENT_2 $end
$var parameter 8 U SEVEN_SEGMENT_3 $end
$var parameter 8 V SEVEN_SEGMENT_4 $end
$var parameter 8 W SEVEN_SEGMENT_5 $end
$var parameter 8 X SEVEN_SEGMENT_6 $end
$var parameter 8 Y SEVEN_SEGMENT_7 $end
$var parameter 8 Z SEVEN_SEGMENT_8 $end
$var parameter 8 [ SEVEN_SEGMENT_9 $end
$var parameter 8 \ SEVEN_SEGMENT_EMPTY $end
$var parameter 8 ] SEVEN_SEGMENT_F $end
$var reg 8 ^ seven_segment_enable [7:0] $end
$var reg 8 _ seven_segment_number [7:0] $end
$upscope $end
$scope module kb_clk_edge_detector $end
$var wire 1 + clk $end
$var wire 1 0 reset_n $end
$var wire 1 < in $end
$var reg 1 = edge_found $end
$var reg 1 ` in_d $end
$upscope $end
$scope module kb_clk_synchronizer $end
$var wire 1 + clk $end
$var wire 1 0 reset_n $end
$var wire 1 , unsynched $end
$var reg 1 a in_buffed $end
$var reg 1 < synched $end
$upscope $end
$scope module kb_data_synchronizer $end
$var wire 1 + clk $end
$var wire 1 0 reset_n $end
$var wire 1 . unsynched $end
$var reg 1 b in_buffed $end
$var reg 1 ; synched $end
$upscope $end
$scope module serial_to_scancode_converter $end
$var wire 1 + clk $end
$var wire 1 0 reset_n $end
$var wire 1 = sample_ready $end
$var wire 1 ; serial_data $end
$var reg 4 c counter [3:0] $end
$var reg 4 d next_counter [3:0] $end
$var reg 8 e scan_code [7:0] $end
$var reg 1 6 valid_scan_code $end
$upscope $end
$upscope $end
$upscope $end
$enddefinitions $end
$comment Show the parameter values. $end
$dumpall
b10001110 ]
b11111111 \
b10010000 [
b10000000 Z
b11111000 Y
b10000010 X
b10010010 W
b10011001 V
b10110000 U
b10100100 T
b11111001 S
b11000000 R
b0 Q
b1000110 P
b111110 O
b111101 N
b110110 M
b101110 L
b100101 K
b100110 J
b11110 I
b10110 H
b1000101 G
b11 *
b10 )
b1 (
b1100 '
b11010010110111001110000011101010111010000101110011101000111100001110100 &
b0 %
b100 $
$end
#0
$dumpvars
b0 e
b1 d
b0 c
xb
xa
0`
bx _
bx ^
b0 F
b0 E
b0 D
b0 C
b0 B
b0 A
b0 @
b0 ?
b0 >
x=
x<
x;
b0 :
b0 9
bx 8
bx 7
06
b0 5
b0 4
b0 3
bx 2
01
00
bx /
0.
0-
1,
0+
b0 #
bx "
bx !
$end
#10000
b0 2
b0 /
1a
0b
1+
#20000
0+
#30000
0;
1<
1+
#40000
0+
#50000
1+
#60000
10
0+
#70000
0=
1`
b1 2
b1 4
b10110110111100001100001011011 /
1+
#80000
0+
#90000
b10 2
b1 3
1.
1+
#100000
0+
1-
#110000
1b
1+
#120000
0+
#130000
1;
1+
#140000
0+
#150000
1+
#160000
0+
#170000
1+
#180000
0+
#190000
1+
#200000
0+
0-
#210000
b11 2
0,
1+
#220000
0+
#230000
0a
1+
#240000
0+
#250000
0<
1+
#260000
0+
#270000
1=
0`
1+
#280000
0+
#290000
b10000000 #
b10000000 5
b10000000 :
b10000000 >
b10000000 e
b10 d
b1 c
0=
1+
#300000
0+
1-
#310000
b1 2
1,
1+
#320000
0+
#330000
b10 2
b10 3
1a
1+
#340000
0+
#350000
1<
1+
#360000
0+
#370000
1`
1+
#380000
0+
#390000
1+
#400000
0+
0-
#410000
b11 2
0,
1+
#420000
0+
#430000
0a
1+
#440000
0+
#450000
0<
1+
#460000
0+
#470000
1=
0`
1+
#480000
0+
#490000
b11000000 #
b11000000 5
b11000000 :
b11000000 >
b11000000 e
b11 d
b10 c
0=
1+
#500000
0+
1-
#510000
b1 2
1,
1+
#520000
0+
#530000
b10 2
b11 3
0.
1a
1+
#540000
0+
#550000
0b
1<
1+
#560000
0+
#570000
1`
0;
1+
#580000
0+
#590000
1+
#600000
0+
0-
#610000
b11 2
0,
1+
#620000
0+
#630000
0a
1+
#640000
0+
#650000
0<
1+
#660000
0+
#670000
1=
0`
1+
#680000
0+
#690000
b1100000 #
b1100000 5
b1100000 :
b1100000 >
b1100000 e
b100 d
b11 c
0=
1+
#700000
0+
1-
#710000
b1 2
1,
1+
#720000
0+
#730000
b10 2
b100 3
1.
1a
1+
#740000
0+
#750000
1b
1<
1+
#760000
0+
#770000
1`
1;
1+
#780000
0+
#790000
1+
#800000
0+
0-
#810000
b11 2
0,
1+
#820000
0+
#830000
0a
1+
#840000
0+
#850000
0<
1+
#860000
0+
#870000
1=
0`
1+
#880000
0+
#890000
b10110000 #
b10110000 5
b10110000 :
b10110000 >
b10110000 e
b101 d
b100 c
0=
1+
#900000
0+
1-
#910000
b1 2
1,
1+
#920000
0+
#930000
b10 2
b101 3
1a
1+
#940000
0+
#950000
1<
1+
#960000
0+
#970000
1`
1+
#980000
0+
#990000
1+
#1000000
0+
0-
#1010000
b11 2
0,
1+
#1020000
0+
#1030000
0a
1+
#1040000
0+
#1050000
0<
1+
#1060000
0+
#1070000
1=
0`
1+
#1080000
0+
#1090000
b11011000 #
b11011000 5
b11011000 :
b11011000 >
b11011000 e
b110 d
b101 c
0=
1+
#1100000
0+
1-
#1110000
b1 2
1,
1+
#1120000
0+
#1130000
b10 2
b110 3
0.
1a
1+
#1140000
0+
#1150000
0b
1<
1+
#1160000
0+
#1170000
1`
0;
1+
#1180000
0+
#1190000
1+
#1200000
0+
0-
#1210000
b11 2
0,
1+
#1220000
0+
#1230000
0a
1+
#1240000
0+
#1250000
0<
1+
#1260000
0+
#1270000
1=
0`
1+
#1280000
0+
#1290000
b1101100 #
b1101100 5
b1101100 :
b1101100 >
b1101100 e
b111 d
b110 c
0=
1+
#1300000
0+
1-
#1310000
b1 2
1,
1+
#1320000
0+
#1330000
b10 2
b111 3
1.
1a
1+
#1340000
0+
#1350000
1b
1<
1+
#1360000
0+
#1370000
1`
1;
1+
#1380000
0+
#1390000
1+
#1400000
0+
0-
#1410000
b11 2
0,
1+
#1420000
0+
#1430000
0a
1+
#1440000
0+
#1450000
0<
1+
#1460000
0+
#1470000
1=
0`
1+
#1480000
0+
#1490000
b10110110 #
b10110110 5
b10110110 :
b10110110 >
b10110110 e
b1000 d
b111 c
0=
1+
#1500000
0+
1-
#1510000
b1 2
1,
1+
#1520000
0+
#1530000
b10 2
b1000 3
0.
1a
1+
#1540000
0+
#1550000
0b
1<
1+
#1560000
0+
#1570000
1`
0;
1+
#1580000
0+
#1590000
1+
#1600000
0+
0-
#1610000
b11 2
0,
1+
#1620000
0+
#1630000
0a
1+
#1640000
0+
#1650000
0<
1+
#1660000
0+
#1670000
1=
0`
1+
#1680000
0+
#1690000
b1011011 #
b1011011 5
b1011011 :
b1011011 >
b1011011 e
b1001 d
b1000 c
0=
1+
#1700000
0+
1-
#1710000
b1 2
1,
1+
#1720000
0+
#1730000
b10 2
b1001 3
1a
1+
#1740000
0+
#1750000
1<
1+
#1760000
0+
#1770000
1`
1+
#1780000
0+
#1790000
1+
#1800000
0+
0-
#1810000
b11 2
0,
1+
#1820000
0+
#1830000
0a
1+
#1840000
0+
#1850000
0<
1+
#1860000
0+
#1870000
1=
0`
1+
#1880000
0+
#1890000
b101101 #
b101101 5
b101101 :
b101101 >
b101101 e
b1010 d
b1001 c
0=
1+
#1900000
0+
1-
#1910000
b1 2
1,
1+
#1920000
0+
#1930000
b10 2
b1010 3
1a
1+
#1940000
0+
#1950000
1<
1+
#1960000
0+
#1970000
1`
1+
#1980000
0+
#1990000
1+
#2000000
0+
0-
#2010000
b11 2
0,
1+
#2020000
0+
#2030000
0a
1+
#2040000
0+
#2050000
0<
1+
#2060000
0+
#2070000
1=
0`
1+
#2080000
0+
#2090000
b10110 #
b10110 5
b10110 :
b10110 >
b10110 e
b0 d
16
b1010 c
0=
1+
#2100000
0+
1-
#2110000
b1 2
1,
1+
#2120000
0+
#2130000
b10 2
b1011 3
1a
1+
#2140000
0+
#2150000
1<
1+
#2160000
0+
#2170000
1`
1+
#2180000
0+
#2190000
1+
#2200000
0+
0-
#2210000
b11 2
0,
1+
#2220000
0+
#2230000
0a
1+
#2240000
0+
#2250000
0<
1+
#2260000
0+
#2270000
1=
0`
1+
#2280000
0+
#2290000
b1011 #
b1011 5
b1011 :
b1011 >
b1011 e
06
b1 d
b0 c
0=
1+
#2300000
0+
1-
#2310000
b1 2
1,
1+
#2320000
0+
#2330000
b10 2
b1100 3
1.
1a
1+
#2340000
0+
#2350000
1b
1<
1+
#2360000
0+
#2370000
1`
1;
1+
#2380000
0+
#2390000
1+
#2400000
0+
0-
#2410000
b11 2
0,
1+
#2420000
0+
#2430000
0a
1+
#2440000
0+
#2450000
0<
1+
#2460000
0+
#2470000
1=
0`
1+
#2480000
0+
#2490000
b10000101 #
b10000101 5
b10000101 :
b10000101 >
b10000101 e
b10 d
b1 c
0=
1+
#2500000
0+
1-
#2510000
b1 2
1,
1+
#2520000
0+
#2530000
b10 2
b1101 3
1a
1+
#2540000
0+
#2550000
1<
1+
#2560000
0+
#2570000
1`
1+
#2580000
0+
#2590000
1+
#2600000
0+
0-
#2610000
b11 2
0,
1+
#2620000
0+
#2630000
0a
1+
#2640000
0+
#2650000
0<
1+
#2660000
0+
#2670000
1=
0`
1+
#2680000
0+
#2690000
b11000010 #
b11000010 5
b11000010 :
b11000010 >
b11000010 e
b11 d
b10 c
0=
1+
#2700000
0+
1-
#2710000
b1 2
1,
1+
#2720000
0+
#2730000
b10 2
b1110 3
0.
1a
1+
#2740000
0+
#2750000
0b
1<
1+
#2760000
0+
#2770000
1`
0;
1+
#2780000
0+
#2790000
1+
#2800000
0+
0-
#2810000
b11 2
0,
1+
#2820000
0+
#2830000
0a
1+
#2840000
0+
#2850000
0<
1+
#2860000
0+
#2870000
1=
0`
1+
#2880000
0+
#2890000
b1100001 #
b1100001 5
b1100001 :
b1100001 >
b1100001 e
b100 d
b11 c
0=
1+
#2900000
0+
1-
#2910000
b1 2
1,
1+
#2920000
0+
#2930000
b10 2
b1111 3
1a
1+
#2940000
0+
#2950000
1<
1+
#2960000
0+
#2970000
1`
1+
#2980000
0+
#2990000
1+
#3000000
0+
0-
#3010000
b11 2
0,
1+
#3020000
0+
#3030000
0a
1+
#3040000
0+
#3050000
0<
1+
#3060000
0+
#3070000
1=
0`
1+
#3080000
0+
#3090000
b110000 #
b110000 5
b110000 :
b110000 >
b110000 e
b101 d
b100 c
0=
1+
#3100000
0+
1-
#3110000
b1 2
1,
1+
#3120000
0+
#3130000
b10 2
b10000 3
1a
1+
#3140000
0+
#3150000
1<
1+
#3160000
0+
#3170000
1`
1+
#3180000
0+
#3190000
1+
#3200000
0+
0-
#3210000
b11 2
0,
1+
#3220000
0+
#3230000
0a
1+
#3240000
0+
#3250000
0<
1+
#3260000
0+
#3270000
1=
0`
1+
#3280000
0+
#3290000
b11000 #
b11000 5
b11000 :
b11000 >
b11000 e
b110 d
b101 c
0=
1+
#3300000
0+
1-
#3310000
b1 2
1,
1+
#3320000
0+
#3330000
b10 2
b10001 3
1a
1+
#3340000
0+
#3350000
1<
1+
#3360000
0+
#3370000
1`
1+
#3380000
0+
#3390000
1+
#3400000
0+
0-
#3410000
b11 2
0,
1+
#3420000
0+
#3430000
0a
1+
#3440000
0+
#3450000
0<
1+
#3460000
0+
#3470000
1=
0`
1+
#3480000
0+
#3490000
b1100 #
b1100 5
b1100 :
b1100 >
b1100 e
b111 d
b110 c
0=
1+
#3500000
0+
1-
#3510000
b1 2
1,
1+
#3520000
0+
#3530000
b10 2
b10010 3
1.
1a
1+
#3540000
0+
#3550000
1b
1<
1+
#3560000
0+
#3570000
1`
1;
1+
#3580000
0+
#3590000
1+
#3600000
0+
0-
#3610000
b11 2
0,
1+
#3620000
0+
#3630000
0a
1+
#3640000
0+
#3650000
0<
1+
#3660000
0+
#3670000
1=
0`
1+
#3680000
0+
#3690000
b10000110 #
b10000110 5
b10000110 :
b10000110 >
b10000110 e
b1000 d
b111 c
0=
1+
#3700000
0+
1-
#3710000
b1 2
1,
1+
#3720000
0+
#3730000
b10 2
b10011 3
1a
1+
#3740000
0+
#3750000
1<
1+
#3760000
0+
#3770000
1`
1+
#3780000
0+
#3790000
1+
#3800000
0+
0-
#3810000
b11 2
0,
1+
#3820000
0+
#3830000
0a
1+
#3840000
0+
#3850000
0<
1+
#3860000
0+
#3870000
1=
0`
1+
#3880000
0+
#3890000
b11000011 #
b11000011 5
b11000011 :
b11000011 >
b11000011 e
b1001 d
b1000 c
0=
1+
#3900000
0+
1-
#3910000
b1 2
1,
1+
#3920000
0+
#3930000
b10 2
b10100 3
1a
1+
#3940000
0+
#3950000
1<
1+
#3960000
0+
#3970000
1`
1+
#3980000
0+
#3990000
1+
#4000000
0+
0-
#4010000
b11 2
0,
1+
#4020000
0+
#4030000
0a
1+
#4040000
0+
#4050000
0<
1+
#4060000
0+
#4070000
1=
0`
1+
#4080000
0+
#4090000
b11100001 #
b11100001 5
b11100001 :
b11100001 >
b11100001 e
b1010 d
b1001 c
0=
1+
#4100000
0+
1-
#4110000
b1 2
1,
1+
#4120000
0+
#4130000
b10 2
b10101 3
1a
1+
#4140000
0+
#4150000
1<
1+
#4160000
0+
#4170000
1`
1+
#4180000
0+
#4190000
1+
#4200000
0+
0-
#4210000
b11 2
0,
1+
#4220000
0+
#4230000
0a
1+
#4240000
0+
#4250000
0<
1+
#4260000
0+
#4270000
1=
0`
1+
#4280000
0+
#4290000
b11110000 #
b11110000 5
b11110000 :
b11110000 >
b11110000 e
16
b0 d
b1010 c
0=
1+
#4300000
0+
1-
#4310000
b1 2
1,
1+
#4320000
0+
#4330000
b10 2
b10110 3
0.
1a
1+
#4340000
0+
#4350000
0b
1<
1+
#4360000
0+
#4370000
1`
0;
1+
#4380000
0+
#4390000
1+
#4400000
0+
0-
#4410000
b11 2
0,
1+
#4420000
0+
#4430000
0a
1+
#4440000
0+
#4450000
0<
1+
#4460000
0+
#4470000
1=
0`
1+
#4480000
0+
#4490000
b1111000 #
b1111000 5
b1111000 :
b1111000 >
b1111000 e
b1 d
06
b0 c
0=
1+
#4500000
0+
1-
#4510000
b1 2
1,
1+
#4520000
0+
#4530000
b10 2
b10111 3
1.
1a
1+
#4540000
0+
#4550000
1b
1<
1+
#4560000
0+
#4570000
1`
1;
1+
#4580000
0+
#4590000
1+
#4600000
0+
0-
#4610000
b11 2
0,
1+
#4620000
0+
#4630000
0a
1+
#4640000
0+
#4650000
0<
1+
#4660000
0+
#4670000
1=
0`
1+
#4680000
0+
#4690000
b10111100 #
b10111100 5
b10111100 :
b10111100 >
b10111100 e
b10 d
b1 c
0=
1+
#4700000
0+
1-
#4710000
b1 2
1,
1+
#4720000
0+
#4730000
b10 2
b11000 3
1a
1+
#4740000
0+
#4750000
1<
1+
#4760000
0+
#4770000
1`
1+
#4780000
0+
#4790000
1+
#4800000
0+
0-
#4810000
b11 2
0,
1+
#4820000
0+
#4830000
0a
1+
#4840000
0+
#4850000
0<
1+
#4860000
0+
#4870000
1=
0`
1+
#4880000
0+
#4890000
b11011110 #
b11011110 5
b11011110 :
b11011110 >
b11011110 e
b11 d
b10 c
0=
1+
#4900000
0+
1-
#4910000
b1 2
1,
1+
#4920000
0+
#4930000
b10 2
b11001 3
0.
1a
1+
#4940000
0+
#4950000
0b
1<
1+
#4960000
0+
#4970000
1`
0;
1+
#4980000
0+
#4990000
1+
#5000000
0+
0-
#5010000
b11 2
0,
1+
#5020000
0+
#5030000
0a
1+
#5040000
0+
#5050000
0<
1+
#5060000
0+
#5070000
1=
0`
1+
#5080000
0+
#5090000
b1101111 #
b1101111 5
b1101111 :
b1101111 >
b1101111 e
b100 d
b11 c
0=
1+
#5100000
0+
1-
#5110000
b1 2
1,
1+
#5120000
0+
#5130000
b10 2
b11010 3
1.
1a
1+
#5140000
0+
#5150000
1b
1<
1+
#5160000
0+
#5170000
1`
1;
1+
#5180000
0+
#5190000
1+
#5200000
0+
0-
#5210000
b11 2
0,
1+
#5220000
0+
#5230000
0a
1+
#5240000
0+
#5250000
0<
1+
#5260000
0+
#5270000
1=
0`
1+
#5280000
0+
#5290000
b10110111 #
b10110111 5
b10110111 :
b10110111 >
b10110111 e
b101 d
b100 c
0=
1+
#5300000
0+
1-
#5310000
b1 2
1,
1+
#5320000
0+
#5330000
b10 2
b11011 3
1a
1+
#5340000
0+
#5350000
1<
1+
#5360000
0+
#5370000
1`
1+
#5380000
0+
#5390000
1+
#5400000
0+
0-
#5410000
b11 2
0,
1+
#5420000
0+
#5430000
0a
1+
#5440000
0+
#5450000
0<
1+
#5460000
0+
#5470000
1=
0`
1+
#5480000
0+
#5490000
b11011011 #
b11011011 5
b11011011 :
b11011011 >
b11011011 e
b110 d
b101 c
0=
1+
#5500000
0+
1-
#5510000
b1 2
1,
1+
#5520000
0+
#5530000
b10 2
b11100 3
0.
1a
1+
#5540000
0+
#5550000
0b
1<
1+
#5560000
0+
#5570000
1`
0;
1+
#5580000
0+
#5590000
1+
#5600000
0+
0-
#5610000
b11 2
0,
1+
#5620000
0+
#5630000
0a
1+
#5640000
0+
#5650000
0<
1+
#5660000
0+
#5670000
1=
0`
1+
#5680000
0+
#5690000
b1101101 #
b1101101 5
b1101101 :
b1101101 >
b1101101 e
b111 d
b110 c
0=
1+
#5700000
0+
1-
#5710000
b1 2
1,
1+
#5720000
0+
#5730000
b10 2
b11101 3
1.
1a
1+
#5740000
0+
#5750000
1b
1<
1+
#5760000
0+
#5770000
1`
1;
1+
#5780000
0+
#5790000
1+
#5800000
0+
0-
#5810000
b11 2
0,
1+
#5820000
0+
#5830000
0a
1+
#5840000
0+
#5850000
0<
1+
#5860000
0+
#5870000
1=
0`
1+
#5880000
0+
#5890000
b10110110 #
b10110110 5
b10110110 :
b10110110 >
b10110110 e
b1000 d
b111 c
0=
1+
#5900000
0+
1-
#5910000
b1 2
1,
1+
#5920000
0+
#5930000
b10 2
b11110 3
0.
1a
1+
#5940000
0+
#5950000
0b
1<
1+
#5960000
0+
#5970000
1`
0;
1+
#5980000
0+
#5990000
1+
#6000000
0+
0-
#6010000
b11 2
0,
1+
#6020000
0+
#6030000
0a
1+
#6040000
0+
#6050000
0<
1+
#6060000
0+
#6070000
1=
0`
1+
#6080000
0+
#6090000
b1011011 #
b1011011 5
b1011011 :
b1011011 >
b1011011 e
b1001 d
b1000 c
0=
1+
#6100000
0+
1-
#6110000
b1 2
1,
1+
#6120000
0+
#6130000
b10 2
b11111 3
1a
1+
#6140000
0+
#6150000
1<
1+
#6160000
0+
