Lab2/refactor/seven_segment_controller.v

module seven_segment_controller(
    input clk,
    input reset_n,
    input [31:0] scan_codes,
    output reg [7:0] seven_segment_number,
    output reg [7:0] seven_segment_enable
);


localparam SCAN_CODE_0 = 8'h45;
localparam SCAN_CODE_1 = 8'h16;
localparam SCAN_CODE_2 = 8'h1e;
localparam SCAN_CODE_3 = 8'h26;
localparam SCAN_CODE_4 = 8'h25;
localparam SCAN_CODE_5 = 8'h2e;
localparam SCAN_CODE_6 = 8'h36;
localparam SCAN_CODE_7 = 8'h3d;
localparam SCAN_CODE_8 = 8'h3e;
localparam SCAN_CODE_9 = 8'h46;
localparam SCAN_CODE_RESET = 8'h0;

localparam SEVEN_SEGMENT_0 = 8'b1100_0000;
localparam SEVEN_SEGMENT_1 = 8'b1111_1001;
localparam SEVEN_SEGMENT_2 = 8'b1010_0100;
localparam SEVEN_SEGMENT_3 = 8'b1011_0000;
localparam SEVEN_SEGMENT_4 = 8'b1001_1001;
localparam SEVEN_SEGMENT_5 = 8'b1001_0010;
localparam SEVEN_SEGMENT_6 = 8'b1000_0010;
localparam SEVEN_SEGMENT_7 = 8'b1111_1000;
localparam SEVEN_SEGMENT_8 = 8'b1000_0000;
localparam SEVEN_SEGMENT_9 = 8'b1001_0000;
localparam SEVEN_SEGMENT_F = 8'b1000_1110;
localparam SEVEN_SEGMENT_EMPTY = 8'b1111_1111;


endmodule

Lab2/refactor/keyboard_controller.v
module keyboard_controller(
    input clk,
    input reset_n,
    input valid_scan_code,
    input [7:0] scan_code,
    output [31:0] scan_codes
);



endmodule

Lab2/refactor/serial_to_scancode.v
module serial_to_scancode(
    input clk,
    input reset_n,
    input sample_ready,
    input serial_data,
    output valid_scan_code,
    output [7:0] scan_code
);



endmodule

Lab2/refactor/falling_edge_detector.v
module falling_edge_detector(
    input clk,
    input reset_n,
    input in,
    output edge_found
);



endmodule

Lab2/refactor/synchronizer.v
module synchronizer(
    input clk,
    input reset_n,
    input unsynched,
    output synched
);



endmodule

Lab2/refactor/keyboard_top.v
module keyboard_top(
    input clk,
    input reset_n,
    input keyboard_clk,
    input keyboard_data,
    output [7:0] led_scancode_debug,
    output [7:0] seven_segment_number,
    output [7:0] seven_segment_enable
);

    wire keyboard_clk_synched;
    wire keyboard_data_synched;

    wire keyboard_clk_edge_found;

    wire valid_scan_code;
    wire [7:0] scan_code;
    wire [31:0] scan_codes;
    

    synchronizer kb_clk_synchronizer(
        .clk(clk),
        .reset_n(reset_n),
        .unsynched(keyboard_clk),
        .synched(keyboard_clk_synched)
    );

    synchronizer kb_data_synchronizer(
        .clk(clk),
        .reset_n(reset_n),
        .unsynched(keyboard_data),
        .synched(keyboard_data_synched)
    );   

    falling_edge_detector kb_clk_edge_detector(
        .clk(clk),
        .reset_n(reset_n),
        .in(keyboard_clk_synched),
        .edge_found(keyboard_clk_edge_found)
    );
    
    serial_to_scancode serial_to_scancode_converter(
        .clk(clk),
        .reset_n(reset_n),
        .sample_ready(keyboard_clk_edge_found),
        .serial_data(keyboard_data_synched),
        .valid_scan_code(valid_scan_code),
        .scan_code(scan_code)
    );    

    keyboard_controller inst_keyboard_controller(
        .clk(clk),
        .reset_n(reset_n),
        .valid_scan_code(valid_scan_code),
        .scan_code(scan_code),
        .scan_codes(scan_codes)
    );
    
    seven_segment_controller inst_seven_segment_controller(
        .clk(clk),
        .reset_n(reset_n),
        .scan_codes(scan_codes),  
        .seven_segment_number(seven_segment_number),
        .seven_segment_enable(seven_segment_enable)          
    );

    assign led_scancode_debug = scan_code;

endmodule

Lab2/refactor/testbench_top.v
`timescale 1ns / 1ps


module testbench_top();
    localparam INPUT_FILE = "input.txt";

    localparam INIT = 3'b000;
    localparam SHIFT = 3'b001;
    localparam WAIT = 3'b010;
    localparam WAIT2 = 3'b011;
    localparam FINISH = 3'b100;

    localparam NUM_KEYS = 12;

    reg [2:0] state;

    reg [7:0] memory [0:NUM_KEYS-1]; // 8 bit memory with 16 entries
    integer memory_index = 0;

    reg clk = 1'b0;
    reg reset_n = 1'b0;

    reg clk_slow = 1'b0;
    reg clk_keyboard = 1'b1;
    reg data_keyboard = 1'b0;

    wire [7:0] scan_code_debug;
    wire [7:0] seven_segment_number;
    wire [7:0] seven_segment_enable;

    reg [32:0] key_all;
    reg start_shifting = 1'b0;
    integer bit_index = 0;


    keyboard_top inst_keyboard_top(
        .clk(clk),
        .reset_n(reset_n),
        .keyboard_clk(clk_keyboard),
        .keyboard_data(data_keyboard),
        .led_scancode_debug(scan_code_debug),
        .seven_segment_number(seven_segment_number),
        .seven_segment_enable(seven_segment_enable)
    );


    always #10 clk = ~clk;
    always #100 clk_slow = ~clk_slow;


    initial begin
        $readmemh(INPUT_FILE, memory);
           $dumpfile("test.vcd");
           $dumpvars(0,testbench_top);


        reset_n = 1'b0;
        @(negedge clk);
        @(negedge clk);
        @(negedge clk);
        reset_n = 1'b1;
    end


    always @(posedge clk or negedge reset_n)
    begin
        if (!reset_n) begin
            data_keyboard <= 1'b0;
            key_all <= 0;
            memory_index <= 0;
            start_shifting <= 1'b0;
            bit_index <= 0;
            clk_keyboard <= 1'b1;
            state <= INIT;
        end else begin
            case (state)
                INIT:
                begin
                    key_all <= {1'b11, memory[memory_index], 2'b0, 1'b11, 8'hf0, 2'b0, 1'b11, memory[memory_index], 2'b0};
                    memory_index <= memory_index + 1;
                    state <= SHIFT;
                    bit_index <= 0;
                end

                SHIFT:
                begin
                    data_keyboard <= key_all[bit_index];
                    bit_index <= bit_index + 1;
                    state <= WAIT;
                end

                WAIT:
                begin
                    if (!clk_slow) begin
                        clk_keyboard <= 1'b0;
                        state <= WAIT2;
                    end
                end

                WAIT2:
                begin
                    if (clk_slow) begin
                        clk_keyboard <= 1'b1;
                        state <= SHIFT;
                        if (bit_index == 32) begin
                            state <= INIT;
                            if (memory_index == NUM_KEYS) begin
                                state <= FINISH;
                            end
                        end
                    end
                end

                FINISH:
                begin
                    $display("Finished!");
                   $finish;

                    $stop;
                end
            endcase
        end
    end


    always @(posedge clk_keyboard)
    begin
        if (bit_index == 12 & scan_code_debug != memory[memory_index-1]) begin
            $display("Failure!");
            $display("DUT Scan code = %x is not equal to expected = %x!", scan_code_debug, memory[memory_index-1]);
            $stop;
        end
    end

endmodule

Lab2/refactor/test.vcd
$date
	Sat Sep 16 17:40:35 2023
$end
$version
	Icarus Verilog
$end
$timescale
	1ps
$end
$scope module testbench_top $end
$var wire 8 ! seven_segment_number [7:0] $end
$var wire 8 " seven_segment_enable [7:0] $end
$var wire 8 # scan_code_debug [7:0] $end
$var parameter 3 $ FINISH $end
$var parameter 3 % INIT $end
$var parameter 72 & INPUT_FILE $end
$var parameter 32 ' NUM_KEYS $end
$var parameter 3 ( SHIFT $end
$var parameter 3 ) WAIT $end
$var parameter 3 * WAIT2 $end
$var reg 1 + clk $end
$var reg 1 , clk_keyboard $end
$var reg 1 - clk_slow $end
$var reg 1 . data_keyboard $end
$var reg 33 / key_all [32:0] $end
$var reg 1 0 reset_n $end
$var reg 1 1 start_shifting $end
$var reg 3 2 state [2:0] $end
$var integer 32 3 bit_index [31:0] $end
$var integer 32 4 memory_index [31:0] $end
$scope module inst_keyboard_top $end
$var wire 1 + clk $end
$var wire 1 , keyboard_clk $end
$var wire 1 5 keyboard_clk_edge_found $end
$var wire 1 6 keyboard_clk_synched $end
$var wire 1 . keyboard_data $end
$var wire 1 7 keyboard_data_synched $end
$var wire 8 8 led_scancode_debug [7:0] $end
$var wire 1 0 reset_n $end
$var wire 8 9 scan_code [7:0] $end
$var wire 32 : scan_codes [31:0] $end
$var wire 1 ; valid_scan_code $end
$var wire 8 < seven_segment_number [7:0] $end
$var wire 8 = seven_segment_enable [7:0] $end
$scope module inst_keyboard_controller $end
$var wire 1 + clk $end
$var wire 1 0 reset_n $end
$var wire 8 > scan_code [7:0] $end
$var wire 32 ? scan_codes [31:0] $end
$var wire 1 ; valid_scan_code $end
$upscope $end
$scope module inst_seven_segment_controller $end
$var wire 1 + clk $end
$var wire 1 0 reset_n $end
$var wire 32 @ scan_codes [31:0] $end
$var parameter 8 A SCAN_CODE_0 $end
$var parameter 8 B SCAN_CODE_1 $end
$var parameter 8 C SCAN_CODE_2 $end
$var parameter 8 D SCAN_CODE_3 $end
$var parameter 8 E SCAN_CODE_4 $end
$var parameter 8 F SCAN_CODE_5 $end
$var parameter 8 G SCAN_CODE_6 $end
$var parameter 8 H SCAN_CODE_7 $end
$var parameter 8 I SCAN_CODE_8 $end
$var parameter 8 J SCAN_CODE_9 $end
$var parameter 8 K SCAN_CODE_RESET $end
$var parameter 8 L SEVEN_SEGMENT_0 $end
$var parameter 8 M SEVEN_SEGMENT_1 $end
$var parameter 8 N SEVEN_SEGMENT_2 $end
$var parameter 8 O SEVEN_SEGMENT_3 $end
$var parameter 8 P SEVEN_SEGMENT_4 $end
$var parameter 8 Q SEVEN_SEGMENT_5 $end
$var parameter 8 R SEVEN_SEGMENT_6 $end
$var parameter 8 S SEVEN_SEGMENT_7 $end
$var parameter 8 T SEVEN_SEGMENT_8 $end
$var parameter 8 U SEVEN_SEGMENT_9 $end
$var parameter 8 V SEVEN_SEGMENT_EMPTY $end
$var parameter 8 W SEVEN_SEGMENT_F $end
$var reg 8 X seven_segment_enable [7:0] $end
$var reg 8 Y seven_segment_number [7:0] $end
$upscope $end
$scope module kb_clk_edge_detector $end
$var wire 1 + clk $end
$var wire 1 5 edge_found $end
$var wire 1 6 in $end
$var wire 1 0 reset_n $end
$upscope $end
$scope module kb_clk_synchronizer $end
$var wire 1 + clk $end
$var wire 1 0 reset_n $end
$var wire 1 6 synched $end
$var wire 1 , unsynched $end
$upscope $end
$scope module kb_data_synchronizer $end
$var wire 1 + clk $end
$var wire 1 0 reset_n $end
$var wire 1 7 synched $end
$var wire 1 . unsynched $end
$upscope $end
$scope module serial_to_scancode_converter $end
$var wire 1 + clk $end
$var wire 1 0 reset_n $end
$var wire 1 5 sample_ready $end
$var wire 8 Z scan_code [7:0] $end
$var wire 1 7 serial_data $end
$var wire 1 ; valid_scan_code $end
$upscope $end
$upscope $end
$upscope $end
$enddefinitions $end
$comment Show the parameter values. $end
$dumpall
b10001110 W
b11111111 V
b10010000 U
b10000000 T
b11111000 S
b10000010 R
b10010010 Q
b10011001 P
b10110000 O
b10100100 N
b11111001 M
b11000000 L
b0 K
b1000110 J
b111110 I
b111101 H
b110110 G
b101110 F
b100101 E
b100110 D
b11110 C
b10110 B
b1000101 A
b11 *
b10 )
b1 (
b1100 '
b11010010110111001110000011101010111010000101110011101000111100001110100 &
b0 %
b100 $
$end
#0
$dumpvars
bz Z
bx Y
bx X
bz @
bz ?
bz >
bx =
bx <
z;
bz :
bz 9
bz 8
z7
z6
z5
b0 4
b0 3
bx 2
01
00
bx /
0.
0-
1,
0+
bz #
bx "
bx !
$end
#10000
b0 2
b0 /
1+
#20000
0+
#30000
1+
#40000
0+
#50000
1+
#60000
10
0+
#70000
b1 2
b1 4
b100010110001111100000010001011000 /
1+
#80000
0+
#90000
b10 2
b1 3
1+
#100000
0+
1-
#110000
1+
#120000
0+
#130000
1+
#140000
0+
#150000
1+
#160000
0+
#170000
1+
#180000
0+
#190000
1+
#200000
0+
0-
#210000
b11 2
0,
1+
#220000
0+
#230000
1+
#240000
0+
#250000
1+
#260000
0+
#270000
1+
#280000
0+
#290000
1+
#300000
0+
1-
#310000
b1 2
1,
1+
#320000
0+
#330000
b10 2
b10 3
1+
#340000
0+
#350000
1+
#360000
0+
#370000
1+
#380000
0+
#390000
1+
#400000
0+
0-
#410000
b11 2
0,
1+
#420000
0+
#430000
1+
#440000
0+
#450000
1+
#460000
0+
#470000
1+
#480000
0+
#490000
1+
#500000
0+
1-
#510000
b1 2
1,
1+
#520000
0+
#530000
b10 2
b11 3
1+
#540000
0+
#550000
1+
#560000
0+
#570000
1+
#580000
0+
#590000
1+
#600000
0+
0-
#610000
b11 2
0,
1+
#620000
0+
#630000
1+
#640000
0+
#650000
1+
#660000
0+
#670000
1+
#680000
0+
#690000
1+
#700000
0+
1-
#710000
b1 2
1,
1+
#720000
0+
#730000
b10 2
b100 3
1.
1+
#740000
0+
#750000
1+
#760000
0+
#770000
1+
#780000
0+
#790000
1+
#800000
0+
0-
#810000
b11 2
0,
1+
#820000
0+
#830000
1+
#840000
0+
#850000
1+
#860000
0+
#870000
1+
#880000
0+
#890000
1+
#900000
0+
1-
#910000
b1 2
1,
1+
#920000
0+
#930000
b10 2
b101 3
1+
#940000
0+
#950000
1+
#960000
0+
#970000
1+
#980000
0+
#990000
1+
#1000000
0+
0-
#1010000
b11 2
0,
1+
#1020000
0+
#1030000
1+
#1040000
0+
#1050000
1+
#1060000
0+
#1070000
1+
#1080000
0+
#1090000
1+
#1100000
0+
1-
#1110000
b1 2
1,
1+
#1120000
0+
#1130000
b10 2
b110 3
0.
1+
#1140000
0+
#1150000
1+
#1160000
0+
#1170000
1+
#1180000
0+
#1190000
1+
#1200000
0+
0-
#1210000
b11 2
0,
1+
#1220000
0+
#1230000
1+
#1240000
0+
#1250000
1+
#1260000
0+
#1270000
1+
#1280000
0+
#1290000
1+
#1300000
0+
1-
#1310000
b1 2
1,
1+
#1320000
0+
#1330000
b10 2
b111 3
1.
1+
#1340000
0+
#1350000
1+
#1360000
0+
#1370000
1+
#1380000
0+
#1390000
1+
#1400000
0+
0-
#1410000
b11 2
0,
1+
#1420000
0+
#1430000
1+
#1440000
0+
#1450000
1+
#1460000
0+
#1470000
1+
#1480000
0+
#1490000
1+
#1500000
0+
1-
#1510000
b1 2
1,
1+
#1520000
0+
#1530000
b10 2
b1000 3
0.
1+
#1540000
0+
#1550000
1+
#1560000
0+
#1570000
1+
#1580000
0+
#1590000
1+
#1600000
0+
0-
#1610000
b11 2
0,
1+
#1620000
0+
#1630000
1+
#1640000
0+
#1650000
1+
#1660000
0+
#1670000
1+
#1680000
0+
#1690000
1+
#1700000
0+
1-
#1710000
b1 2
1,
1+
#1720000
0+
#1730000
b10 2
b1001 3
1+
#1740000
0+
#1750000
1+
#1760000
0+
#1770000
1+
#1780000
0+
#1790000
1+
#1800000
0+
0-
#1810000
b11 2
0,
1+
#1820000
0+
#1830000
1+
#1840000
0+
#1850000
1+
#1860000
0+
#1870000
1+
#1880000
0+
#1890000
1+
#1900000
0+
1-
#1910000
b1 2
1,
1+
#1920000
0+
#1930000
b10 2
b1010 3
1+
#1940000
0+
#1950000
1+
#1960000
0+
#1970000
1+
#1980000
0+
#1990000
1+
#2000000
0+
0-
#2010000
b11 2
0,
1+
#2020000
0+
#2030000
1+
#2040000
0+
#2050000
1+
#2060000
0+
#2070000
1+
#2080000
0+
#2090000
1+
#2100000
0+
1-
#2110000
b1 2
1,
1+
#2120000
0+
#2130000
b10 2
b1011 3
1.
1+
#2140000
0+
#2150000
1+
#2160000
0+
#2170000
1+
#2180000
0+
#2190000
1+
#2200000
0+
0-
#2210000
b11 2
0,
1+
#2220000
0+
#2230000
1+
#2240000
0+
#2250000
1+
#2260000
0+
#2270000
1+
#2280000
0+
#2290000
1+
#2300000
0+
1-
#2310000
b1 2
1,
1+
#2320000
0+
#2330000
b10 2
b1100 3
0.
1+
#2340000
0+
#2350000
1+
#2360000
0+
#2370000
1+
#2380000
0+
#2390000
1+
#2400000
0+
0-
#2410000
b11 2
0,
1+
#2420000
0+
#2430000
1+
#2440000
0+
#2450000
1+
#2460000
0+
#2470000
1+
#2480000
0+
#2490000
1+
#2500000
0+
1-
#2510000
b1 2
1,
1+
#2520000
0+
#2530000
b10 2
b1101 3
1+
#2540000
0+
#2550000
1+
#2560000
0+
#2570000
1+
#2580000
0+
#2590000
1+
#2600000
0+
0-
#2610000
b11 2
0,
1+
#2620000
0+
#2630000
1+
#2640000
0+
#2650000
1+
#2660000
0+
#2670000
1+
#2680000
0+
#2690000
1+
#2700000
0+
1-
#2710000
b1 2
1,
1+
#2720000
0+
#2730000
b10 2
b1110 3
1+
#2740000
0+
#2750000
1+
#2760000
0+
#2770000
1+
#2780000
0+
#2790000
1+
#2800000
0+
0-
#2810000
b11 2
0,
1+
#2820000
0+
#2830000
1+
#2840000
0+
#2850000
1+
#2860000
0+
#2870000
1+
#2880000
0+
#2890000
1+
#2900000
0+
1-
#2910000
b1 2
1,
1+
#2920000
0+
#2930000
b10 2
b1111 3
1+
#2940000
0+
#2950000
1+
#2960000
0+
#2970000
1+
#2980000
0+
#2990000
1+
#3000000
0+
0-
#3010000
b11 2
0,
1+
#3020000
0+
#3030000
1+
#3040000
0+
#3050000
1+
#3060000
0+
#3070000
1+
#3080000
0+
#3090000
1+
#3100000
0+
1-
#3110000
b1 2
1,
1+
#3120000
0+
#3130000
b10 2
b10000 3
1+
#3140000
0+
#3150000
1+
#3160000
0+
#3170000
1+
#3180000
0+
#3190000
1+
#3200000
0+
0-
#3210000
b11 2
0,
1+
#3220000
0+
#3230000
1+
#3240000
0+
#3250000
1+
#3260000
0+
#3270000
1+
#3280000
0+
#3290000
1+
#3300000
0+
1-
#3310000
b1 2
1,
1+
#3320000
0+
#3330000
b10 2
b10001 3
1+
#3340000
0+
#3350000
1+
#3360000
0+
#3370000
1+
#3380000
0+
#3390000
1+
#3400000
0+
0-
#3410000
b11 2
0,
1+
#3420000
0+
#3430000
1+
#3440000
0+
#3450000
1+
#3460000
0+
#3470000
1+
#3480000
0+
#3490000
1+
#3500000
0+
1-
#3510000
b1 2
1,
1+
#3520000
0+
#3530000
b10 2
b10010 3
1.
1+
#3540000
0+
#3550000
1+
#3560000
0+
#3570000
1+
#3580000
0+
#3590000
1+
#3600000
0+
0-
#3610000
b11 2
0,
1+
#3620000
0+
#3630000
1+
#3640000
0+
#3650000
1+
#3660000
0+
#3670000
1+
#3680000
0+
#3690000
1+
#3700000
0+
1-
#3710000
b1 2
1,
1+
#3720000
0+
#3730000
b10 2
b10011 3
1+
#3740000
0+
#3750000
1+
#3760000
0+
#3770000
1+
#3780000
0+
#3790000
1+
#3800000
0+
0-
#3810000
b11 2
0,
1+
#3820000
0+
#3830000
1+
#3840000
0+
#3850000
1+
#3860000
0+
#3870000
1+
#3880000
0+
#3890000
1+
#3900000
0+
1-
#3910000
b1 2
1,
1+
#3920000
0+
#3930000
b10 2
b10100 3
1+
#3940000
0+
#3950000
1+
#3960000
0+
#3970000
1+
#3980000
0+
#3990000
1+
#4000000
0+
0-
#4010000
b11 2
0,
1+
#4020000
0+
#4030000
1+
#4040000
0+
#4050000
1+
#4060000
0+
#4070000
1+
#4080000
0+
#4090000
1+
#4100000
0+
1-
#4110000
b1 2
1,
1+
#4120000
0+
#4130000
b10 2
b10101 3
1+
#4140000
0+
#4150000
1+
#4160000
0+
#4170000
1+
#4180000
0+
#4190000
1+
#4200000
0+
0-
#4210000
b11 2
0,
1+
#4220000
0+
#4230000
1+
#4240000
0+
#4250000
1+
#4260000
0+
#4270000
1+
#4280000
0+
#4290000
1+
#4300000
0+
1-
#4310000
b1 2
1,
1+
#4320000
0+
#4330000
b10 2
b10110 3
1+
#4340000
0+
#4350000
1+
#4360000
0+
#4370000
1+
#4380000
0+
#4390000
1+
#4400000
0+
0-
#4410000
b11 2
0,
1+
#4420000
0+
#4430000
1+
#4440000
0+
#4450000
1+
#4460000
0+
#4470000
1+
#4480000
0+
#4490000
1+
#4500000
0+
1-
#4510000
b1 2
1,
1+
#4520000
0+
#4530000
b10 2
b10111 3
0.
1+
#4540000
0+
#4550000
1+
#4560000
0+
#4570000
1+
#4580000
0+
#4590000
1+
#4600000
0+
0-
#4610000
b11 2
0,
1+
#4620000
0+
#4630000
1+
#4640000
0+
#4650000
1+
#4660000
0+
#4670000
1+
#4680000
0+
#4690000
1+
#4700000
0+
1-
#4710000
b1 2
1,
1+
#4720000
0+
#4730000
b10 2
b11000 3
1+
#4740000
0+
#4750000
1+
#4760000
0+
#4770000
1+
#4780000
0+
#4790000
1+
#4800000
0+
0-
#4810000
b11 2
0,
1+
#4820000
0+
#4830000
1+
#4840000
0+
#4850000
1+
#4860000
0+
#4870000
1+
#4880000
0+
#4890000
1+
#4900000
0+
1-
#4910000
b1 2
1,
1+
#4920000
0+
#4930000
b10 2
b11001 3
1+
#4940000
0+
#4950000
1+
#4960000
0+
#4970000
1+
#4980000
0+
#4990000
1+
#5000000
0+
0-
#5010000
b11 2
0,
1+
#5020000
0+
#5030000
1+
#5040000
0+
#5050000
1+
#5060000
0+
#5070000
1+
#5080000
0+
#5090000
1+
#5100000
0+
1-
#5110000
b1 2
1,
1+
#5120000
0+
#5130000
b10 2
b11010 3
1.
1+
#5140000
0+
#5150000
1+
#5160000
0+
#5170000
1+
#5180000
0+
#5190000
1+
#5200000
0+
0-
#5210000
b11 2
0,
1+
#5220000
0+
#5230000
1+
#5240000
0+
#5250000
1+
#5260000
0+
#5270000
1+
#5280000
0+
#5290000
1+
#5300000
0+
1-
#5310000
b1 2
1,
1+
#5320000
0+
#5330000
b10 2
b11011 3
1+
#5340000
0+
#5350000
1+
#5360000
0+
#5370000
1+
#5380000
0+
#5390000
1+
#5400000
0+
0-
#5410000
b11 2
0,
1+
#5420000
0+
#5430000
1+
#5440000
0+
#5450000
1+
#5460000
0+
#5470000
1+
#5480000
0+
#5490000
1+
#5500000
0+
1-
#5510000
b1 2
1,
1+
#5520000
0+
#5530000
b10 2
b11100 3
0.
1+
#5540000
0+
#5550000
1+
#5560000
0+
#5570000
1+
#5580000
0+
#5590000
1+
#5600000
0+
0-
#5610000
b11 2
0,
1+
#5620000
0+
#5630000
1+
#5640000
0+
#5650000
1+
#5660000
0+
#5670000
1+
#5680000
0+
#5690000
1+
#5700000
0+
1-
#5710000
b1 2
1,
1+
#5720000
0+
#5730000
b10 2
b11101 3
1.
1+
#5740000
0+
#5750000
1+
#5760000
0+
#5770000
1+
#5780000
0+
#5790000
1+
#5800000
0+
0-
#5810000
b11 2
0,
1+
#5820000
0+
#5830000
1+
#5840000
0+
#5850000
1+
#5860000
0+
#5870000
1+
#5880000
0+
#5890000
1+
#5900000
0+
1-
#5910000
b1 2
1,
1+
#5920000
0+
#5930000
b10 2
b11110 3
0.
1+
#5940000
0+
#5950000
1+
#5960000
0+
#5970000
1+
#5980000
0+
#5990000
1+
#6000000
0+
0-
#6010000
b11 2
0,
1+
#6020000
0+
#6030000
1+
#6040000
0+
#6050000
1+
#6060000
0+
#6070000
1+
#6080000
0+
#6090000
1+
#6100000
0+
1-
#6110000
b1 2
1,
1+
#6120000
0+
#6130000
b10 2
b11111 3
1+
#6140000
0+
#6150000
1+
#6160000
0+
#6170000
1+
#6180000
0+
#6190000
1+
#6200000
0+
0-
#6210000
b11 2
0,
1+
#6220000
0+
#6230000
1+
#6240000
0+
#6250000
1+
#6260000
0+
#6270000
1+
#6280000
0+
#6290000
1+
#6300000
0+
1-
#6310000
b1 2
1,
1+
#6320000
0+
#6330000
b10 2
b100000 3
1+
#6340000
0+
#6350000
1+
#6360000
0+
#6370000
1+
#6380000
0+
#6390000
1+
#6400000
0+
0-
#6410000
b11 2
0,
1+
#6420000
0+
#6430000
1+
#6440000
0+
#6450000
1+
#6460000
0+
#6470000
1+
#6480000
0+
#6490000
1+
#6500000
0+
1-
#6510000
b0 2
1,
1+
#6520000
0+
#6530000
b0 3
b1 2
b10 4
b100011110001111100000010001111000 /
1+
#6540000
0+
#6550000
b10 2
b1 3
1+
#6560000
0+
#6570000
1+
#6580000
0+
#6590000
1+
#6600000
0+
0-
#6610000
b11 2
0,
1+
#6620000
0+
#6630000
1+
#6640000
0+
#6650000
1+
#6660000
0+
#6670000
1+
#6680000
0+
#6690000
1+
#6700000
0+
1-
#6710000
b1 2
1,
1+
#6720000
0+
#6730000
b10 2
b10 3
1+
#6740000
0+
#6750000
1+
#6760000
0+
#6770000
1+
#6780000
0+
#6790000
1+
#6800000
0+
0-
#6810000
b11 2
0,
1+
#6820000
0+
#6830000
1+
#6840000
0+
#6850000
1+
#6860000
0+
#6870000
1+
#6880000
0+
#6890000
1+
#6900000
0+
1-
#6910000
b1 2
1,
1+
#6920000
0+
#6930000
b10 2
b11 3
1+
#6940000
0+
#6950000
1+
#6960000
0+
#6970000
1+
#6980000
0+
#6990000
1+
#7000000
0+
0-
#7010000
b11 2
0,
1+
#7020000
0+
#7030000
1+
#7040000
0+
#7050000
1+
#7060000
0+
#7070000
1+
#7080000
0+
#7090000
1+
#7100000
0+
1-
#7110000
b1 2
1,
1+
#7120000
0+
#7130000
b10 2
b100 3
1.
1+
#7140000
0+
#7150000
1+
#7160000
0+
#7170000
1+
#7180000
0+
#7190000
1+
#7200000
0+
0-
#7210000
b11 2
0,
1+
#7220000
0+
#7230000
1+
#7240000
0+
#7250000
1+
#7260000
0+
#7270000
1+
#7280000
0+
#7290000
1+
#7300000
0+
1-
#7310000
b1 2
1,
1+
#7320000
0+
#7330000
b10 2
b101 3
1+
#7340000
0+
#7350000
1+
#7360000
0+
#7370000
1+
#7380000
0+
#7390000
1+
#7400000
0+
0-
#7410000
b11 2
0,
1+
#7420000
0+
#7430000
1+
#7440000
0+
#7450000
1+
#7460000
0+
#7470000
1+
#7480000
0+
#7490000
1+
#7500000
0+
1-
#7510000
b1 2
1,
1+
#7520000
0+
#7530000
b10 2
b110 3
1+
#7540000
0+
#7550000
1+
#7560000
0+
#7570000
1+
#7580000
0+
#7590000
1+
#7600000
0+
0-
#7610000
b11 2
0,
1+
#7620000
0+
#7630000
1+
#7640000
0+
#7650000
1+
#7660000
0+
#7670000
1+
#7680000
0+
#7690000
1+
#7700000
0+
1-
#7710000
b1 2
1,
1+
#7720000
0+
#7730000
b10 2
b111 3
1+
#7740000
0+
#7750000
1+
#7760000
0+
#7770000
1+
#7780000
0+
#7790000
1+
#7800000
0+
0-
#7810000
b11 2
0,
1+
#7820000
0+
#7830000
1+
#7840000
0+
#7850000
1+
#7860000
0+
#7870000
1+
#7880000
0+
#7890000
1+
#7900000
0+
1-
#7910000
b1 2
1,
1+
#7920000
0+
#7930000
b10 2
b1000 3
0.
1+
#7940000
0+
#7950000
1+
#7960000
0+
#7970000
1+
#7980000
0+
#7990000
1+
#8000000
0+
0-
#8010000
b11 2
0,
1+
#8020000
0+
#8030000
1+
#8040000
0+
#8050000
1+
#8060000
0+
#8070000
1+
#8080000
0+
#8090000
1+
#8100000
0+
1-
#8110000
b1 2
1,
1+
#8120000
0+
#8130000
b10 2
b1001 3
1+
#8140000
0+
#8150000
1+
#8160000
0+
#8170000
1+
#8180000
0+
#8190000
1+
#8200000
0+
0-
#8210000
b11 2
0,
1+
#8220000
0+
#8230000
1+
#8240000
0+
#8250000
1+
#8260000
0+
#8270000
1+
#8280000
0+
#8290000
1+
#8300000
0+
1-
#8310000
b1 2
1,
1+
#8320000
0+
#8330000
b10 2
b1010 3
1+
#8340000
0+
#8350000
1+
#8360000
0+
#8370000
1+
#8380000
0+
#8390000
1+
#8400000
0+
0-
#8410000
b11 2
0,
1+
#8420000
0+
#8430000
1+
#8440000
0+
#8450000
1+
#8460000
0+
#8470000
1+
#8480000
0+
#8490000
1+
#8500000
0+
1-
#8510000
b1 2
1,
1+
#8520000
0+
#8530000
b10 2
b1011 3
1.
1+
#8540000
0+
#8550000
1+
#8560000
0+
#8570000
1+
#8580000
0+
#8590000
1+
#8600000
0+
0-
#8610000
b11 2
0,
1+
#8620000
0+
#8630000
1+
#8640000
0+
#8650000
1+
#8660000
0+
#8670000
1+
#8680000
0+
#8690000
1+
#8700000
0+
1-
#8710000
b1 2
1,
1+
#8720000
0+
#8730000
b10 2
b1100 3
0.
1+
#8740000
0+
#8750000
1+
#8760000
0+
#8770000
1+
#8780000
0+
#8790000
1+
#8800000
0+
0-
#8810000
b11 2
0,
1+
#8820000
0+
#8830000
1+
#8840000
0+
#8850000
1+
#8860000
0+
#8870000
1+
#8880000
0+
#8890000
1+
#8900000
0+
1-
#8910000
b1 2
1,
1+
#8920000
0+
#8930000
b10 2
b1101 3
1+
#8940000
0+
#8950000
1+
#8960000
0+
#8970000
1+
#8980000
0+
#8990000
1+
#9000000
0+
0-
#9010000
b11 2
0,
1+
#9020000
0+
#9030000
1+
#9040000
0+
#9050000
1+
#9060000
0+
#9070000
1+
#9080000
0+
#9090000
1+
#9100000
0+
1-
#9110000
b1 2
1,
1+
#9120000
0+
#9130000
b10 2
b1110 3
1+
#9140000
0+
#9150000
1+
#9160000
0+
#9170000
1+
#9180000
0+
#9190000
1+
#9200000
0+
0-
#9210000
b11 2
0,
1+
#9220000
0+
#9230000
1+
#9240000
0+
#9250000
1+
#9260000
0+
#9270000
1+
#9280000
0+
#9290000
1+
#9300000
0+
1-
#9310000
b1 2
1,
1+
#9320000
0+
#9330000
b10 2
b1111 3
1+
#9340000
0+
#9350000
1+
#9360000
0+
#9370000
1+
#9380000
0+
#9390000
1+
#9400000
0+
0-
#9410000
b11 2
0,
1+
#9420000
0+
#9430000
1+
#9440000
0+
#9450000
1+
#9460000
0+
#9470000
1+
#9480000
0+
#9490000
1+
#9500000
0+
1-
#9510000
b1 2
1,
1+
#9520000
0+
#9530000
b10 2
b10000 3
1+
#9540000
0+
#9550000
1+
#9560000
0+
#9570000
1+
#9580000
0+
#9590000
1+
#9600000
0+
0-
#9610000
b11 2
0,
1+
#9620000
0+
#9630000
1+
#9640000
0+
#9650000
1+
#9660000
0+
#9670000
1+
#9680000
0+
#9690000
1+
#9700000
0+
1-
#9710000
b1 2
1,
1+
#9720000
0+
#9730000
b10 2
b10001 3
1+
#9740000
0+
#9750000
1+
#9760000
0+
#9770000
1+
#9780000
0+
#9790000
1+
#9800000
0+
0-
#9810000
b11 2
0,
1+
#9820000
0+
#9830000
1+
#9840000
0+
#9850000
1+
#9860000
0+
#9870000
1+
#9880000
0+
#9890000
1+
