Lab2/verilog/binary_to_sg.v
module binary_to_sg
  (input  [3:0] binary_in,
   output reg [7:0] sev_seg);

   always @ (binary_in) begin
      case(binary_in)
        4'b0000 : sev_seg = 8'b11000000; //0

        4'b0001 :  sev_seg = 8'b11111001; //1

        4'b0010:  sev_seg = 8'b10100100; //2

        4'b0011:  sev_seg = 8'b10110000; //...

        4'b0100:  sev_seg = 8'b10011001;

        4'b0101:  sev_seg = 8'b10010010;

        4'b0110: sev_seg = 8'b10000010;

        4'b0111: sev_seg = 8'b11111000;

        4'b1000: sev_seg = 8'b10000000;

        4'b1001: sev_seg = 8'b10010000; //9

        4'b1111 : sev_seg = 8'b11111111; //off

        default : sev_seg = 8'b10000110; //error

      endcase // case (sel)
   end // always @ (binary_in)


endmodule

Lab2/verilog/convert_to_binary.v
module convert_to_binary
  (input [7:0] scan_code_in,
   output reg [3:0] binary_out);



  /* convert_to_binary.vhd:16:17  */
  always @ (scan_code_in) begin
    case (scan_code_in)
      8'h00: binary_out = 4'b1111;
      8'h46: binary_out = 4'b1001;
      8'h3E: binary_out = 4'b1000;
      8'h3D: binary_out = 4'b0111;
      8'h36: binary_out = 4'b0110;
      8'h2E: binary_out = 4'b0101;
      8'h25: binary_out = 4'b0100;
      8'h26: binary_out = 4'b0011;
      8'h1E: binary_out = 4'b0010;
      8'h16: binary_out = 4'b0001;
      8'h45: binary_out = 4'b0000;
      default: binary_out = 4'b1010;
    endcase // case (scan_code_in)
  end // always @ (scan_code_in)

endmodule

Lab2/verilog/keyboard_ctrl.v
module keyboard_ctrl
(input            clk,
 input            rst,
 input            valid_code,
 input [7:0]      scan_code_in,
 output reg [7:0] code_to_display,
 output reg [3:0] seg_en);

   reg [2:0] state, next_state;
   reg [31:0] scanCodes;
   reg [1:0]  seg_counter;
   reg [17:0] counter;
   reg [3:0]  seg_curr;


   always @ (posedge clk, negedge rst)
     if (~rst) begin
        state <= 0;
        next_state <= 0;
        scanCodes <= 0;
        counter <= 0;
        seg_counter <= 0;
        seg_curr <= 0;
     end else if (counter == "11111111111111110")begin
        counter <= 0;
        seg_counter <= seg_counter + 1;
     end else begin
        counter <= counter + 1;
        state <= next_state;
     end

   always @(state)
     if (valid_code)begin
        case(state)
          0:
            if(scan_code_in == "11110000")begin
               next_state <= 1;
               seg_curr <= "1110";
               //do nothin
            end else begin
               //do nothin
            end
          1:
            if(scan_code_in == "11110000") begin
               next_state <= 2;
               scanCodes = scanCodes << 8;
               seg_curr <= "1100";
            end else if(scanCodes[31:24] == "00000000")begin
               scanCodes[31:24] <= scan_code_in;
            end
          2: if(scan_code_in == "11110000") begin
             next_state <= 3;
             scanCodes = scanCodes << 8;
             seg_curr <= "1000";
          end else if(scanCodes[31:24] == "00000000")begin
             scanCodes[31:24] <= scan_code_in;
          end
          3: if(scan_code_in == "11110000") begin
             next_state <= 4;
             scanCodes = scanCodes << 8;
             seg_curr <= "0000";
          end else if(scanCodes[31:24] == "00000000")begin
             scanCodes[31:24] <= scan_code_in;
          end
          4: if(scan_code_in == "11110000") begin
             scanCodes = scanCodes << 8;
          end else if(scanCodes[31:24] == "00000000")begin
             scanCodes[31:24] <= scan_code_in;
          end
          default:begin
             //do nothing
          end
        endcase
     end

   always @ (seg_counter)
     begin
        case(seg_counter)
          0: begin
             seg_en <= "1110";
             code_to_display <= scanCodes[31:24];
          end
          1: begin
             seg_en <= "1101";
             code_to_display <= scanCodes[23:16];
          end
          2: begin
             seg_en <= "1011";
             code_to_display <= scanCodes[15:8];
          end
          3: begin
             seg_en <= "0111";
             code_to_display <= scanCodes[7:0];
          end
        endcase
     end

endmodule

Lab2/verilog/convert_scancode.v
module convert_scancode
  (input  clk,
   input  rst,
   input  edge_found,
   input  serial_data,
   output reg valid_scan_code,
   output reg [7:0] scan_code_out);

   reg [9:0] scan_code;

   reg [3:0] current_counter, next_counter;

   always @ (posedge clk, negedge rst)
   if (~rst) begin
    scan_code_out <= 0;
    valid_scan_code <= 0;
    current_counter <= 0;
    next_counter <= 0;
   end else if(edge_found & (current_counter == "1010")) begin
    scan_code[8:0] <= scan_code[9:1];
    scan_code[9] <= serial_data;
    scan_code_out[7:0] <= scan_code[7:0];
    next_counter <= "0000";
    valid_scan_code <= 1;

   end else if (edge_found) begin
    scan_code[8:0] <= scan_code[9:1];
    scan_code[9] <= serial_data;
    scan_code_out[7:0] <= scan_code[7:0];
    next_counter <= current_counter + 1;
    current_counter <= next_counter;
    valid_scan_code <= 0;
   end else begin
    //do nothing
   end

endmodule

Lab2/verilog/edge_detector.v
module edge_detector
  (input  clk,
   input  rst,
   input  kb_clk_sync,
   output edge_found);

  reg kb_clk_in;
  reg edge_found;

  always @(posedge clk)
  if(~rst) begin
    kb_clk_in <= 0;
  end else begin
    kb_clk_in <= kb_clk_sync;
    edge_found <= (!kb_clk_sync & kb_clk_in);
  end

endmodule

Lab2/verilog/sync_keyboard.v
module sync_keyboard
  (input  clk,
   input  kb_clk,
   input  kb_data,
   output reg kb_clk_sync,
   output reg kb_data_sync);
  reg data_1, clk_1;
//maybe add kb_clk, chatgpt suggested
  always @ (posedge clk)
  begin
    data_1 <= kb_data;
    kb_data_sync <= data_1;
    clk_1 <= kb_clk;
    kb_clk_sync <= clk_1;
  end
endmodule

Lab2/verilog/keyboard_top.v
module keyboard_top
  (input        clk,
   input        rst,
   input        kb_data,
   input        kb_clk,
   output [7:0] sc,
   output [7:0] num,
   output [3:0] seg_en);

   // set up all ports here

   wire [7:0] scan_code_out;
   wire       edge_found;
   wire       kb_data_sync;
   wire       kb_clk_sync;
   wire       valid_scan_code;
   wire [7:0] code_to_display;
   wire [7:0] sev_seg;
   wire [3:0] binary_out;
   wire [3:0] binary_num;


   // connect all ports here
   // module followed by DUT name
   sync_keyboard sync_keyboard_inst (
                                     .clk(clk),
                                     .kb_clk(kb_clk),
                                     .kb_data(kb_data),
                                     .kb_clk_sync(kb_clk_sync),
                                     .kb_data_sync(kb_data_sync));
   /* keyboard_top.vhd:113:5  */
   edge_detector edge_detector_inst (
                                     .clk(clk),
                                     .rst(rst),
                                     .kb_clk_sync(kb_clk_sync),
                                     .edge_found(edge_found));


   /* keyboard_top.vhd:124:5  */
   convert_scancode convert_scancode_inst (
                                           .clk(clk),
                                           .rst(rst),
                                           .edge_found(edge_found),
                                           .serial_data(kb_data_sync),
                                           .valid_scan_code(valid_scan_code),
                                           .scan_code_out(scan_code_out));



   /* keyboard_top.vhd:138:5  */
   keyboard_ctrl keyboard_ctrl_inst (
                                     .clk(clk),
                                     .rst(rst),
                                     .valid_code(valid_scan_code),
                                     .scan_code_in(scan_code_out),
                                     .code_to_display(code_to_display),
                                     .seg_en(seg_en));



   /* keyboard_top.vhd:148:5  */
   convert_to_binary convert_to_binary_inst (
                                             .scan_code_in(code_to_display),
                                             .binary_out(binary_out));



   /* keyboard_top.vhd:155:5  */
   binary_to_sg binary_to_sg_inst (
                                   .binary_in(binary_num),
                                   .sev_seg(sev_seg));
endmodule

Lab2/verilog/tb_pkg.v
module tb_pkg;

   reg clk = 0;
   reg rst = 0;
   reg kb_data = 1;
   reg kb_clk = 0;
   wire [7:0] sc = 0;
   wire [7:0] num = 0;
   wire [3:0] seg_en = 0;

   keyboard_top DUT (
                     .clk(clk),
                     .rst(rst),
                     .kb_data(kb_data),
                     .sc(sc),
                     .num(num),
                     .seg_en(seg_en),
                     .kb_clk(kb_clk)
                     );


   // duration for each bit = 20 * timescale = 20 * 1 ns  = 20ns
   localparam period = 40;

   always #5 clk <= !clk;

   always #20 kb_clk <= !kb_clk;

   initial // initial block executes only once
     begin

        $dumpfile("test.vcd");
        $dumpvars(0,tb_pkg);
        // start sending data
        // values for a and b
        kb_data = 0;
        rst <= 1;

        #period; // wait for period
        rst <= 0;

        #period
        kb_data = 1;

        #period;

        kb_data = 0;

        #period;

        kb_data = 0;

        #period;
        kb_data = 1;

        #period;

        kb_data = 0;

        #period;

        kb_data = 0;


        $finish();
     end // initial begin
endmodule

Lab2/verilog/test.vcd
$date
	Thu Sep 14 18:18:56 2023
$end
$version
	Icarus Verilog
$end
$timescale
	1s
$end
$scope module tb_pkg $end
$var wire 8 ! num [7:0] $end
$var wire 8 " sc [7:0] $end
$var wire 4 # seg_en [3:0] $end
$var parameter 32 $ period $end
$var reg 1 % clk $end
$var reg 1 & kb_clk $end
$var reg 1 ' kb_data $end
$var reg 1 ( rst $end
$scope module DUT $end
$var wire 4 ) binary_num [3:0] $end
$var wire 1 % clk $end
$var wire 1 & kb_clk $end
$var wire 1 ' kb_data $end
$var wire 8 * num [7:0] $end
$var wire 1 ( rst $end
$var wire 8 + sc [7:0] $end
$var wire 4 , seg_en [3:0] $end
$var wire 1 - valid_scan_code $end
$var wire 8 . sev_seg [7:0] $end
$var wire 8 / scan_code_out [7:0] $end
$var wire 1 0 kb_data_sync $end
$var wire 1 1 kb_clk_sync $end
$var wire 1 2 edge_found $end
$var wire 8 3 code_to_display [7:0] $end
$var wire 4 4 binary_out [3:0] $end
$scope module binary_to_sg_inst $end
$var wire 4 5 binary_in [3:0] $end
$var reg 8 6 sev_seg [7:0] $end
$upscope $end
$scope module convert_scancode_inst $end
$var wire 1 % clk $end
$var wire 1 ( rst $end
$var wire 1 0 serial_data $end
$var wire 1 2 edge_found $end
$var reg 4 7 current_counter [3:0] $end
$var reg 4 8 next_counter [3:0] $end
$var reg 10 9 scan_code [9:0] $end
$var reg 8 : scan_code_out [7:0] $end
$var reg 1 - valid_scan_code $end
$upscope $end
$scope module convert_to_binary_inst $end
$var wire 8 ; scan_code_in [7:0] $end
$var reg 4 < binary_out [3:0] $end
$upscope $end
$scope module edge_detector_inst $end
$var wire 1 % clk $end
$var wire 1 ( rst $end
$var wire 1 1 kb_clk_sync $end
$var reg 1 2 edge_found $end
$var reg 1 = kb_clk_in $end
$upscope $end
$scope module keyboard_ctrl_inst $end
$var wire 1 % clk $end
$var wire 1 ( rst $end
$var wire 8 > scan_code_in [7:0] $end
$var wire 1 - valid_code $end
$var reg 8 ? code_to_display [7:0] $end
$var reg 18 @ counter [17:0] $end
$var reg 3 A next_state [2:0] $end
$var reg 32 B scanCodes [31:0] $end
$var reg 2 C seg_counter [1:0] $end
$var reg 4 D seg_curr [3:0] $end
$var reg 4 E seg_en [3:0] $end
$var reg 3 F state [2:0] $end
$upscope $end
$scope module sync_keyboard_inst $end
$var wire 1 % clk $end
$var wire 1 & kb_clk $end
$var wire 1 ' kb_data $end
$var reg 1 G clk_1 $end
$var reg 1 H data_1 $end
$var reg 1 1 kb_clk_sync $end
$var reg 1 0 kb_data_sync $end
$upscope $end
$upscope $end
$upscope $end
$enddefinitions $end
$comment Show the parameter values. $end
$dumpall
b101000 $
$end
#0
$dumpvars
xH
xG
b0 F
b0 E
b0 D
b0 C
b0 B
b0 A
b0 @
b0 ?
b0 >
x=
b1111 <
b0 ;
b0 :
bx 9
b0 8
b0 7
b10000110 6
bz 5
b1111 4
b0 3
x2
x1
x0
b0 /
b10000110 .
0-
b0 ,
b0 +
b0 *
bz )
1(
0'
0&
0%
b0 #
b0 "
b0 !
$end
#5
b1 @
0G
0H
1%
#10
0%
#15
b10 @
01
00
1%
#20
1G
0%
1&
#25
b11 @
0=
11
1%
#30
0%
#35
b100 @
02
1=
1%
#40
b0 @
0%
0&
0(
#45
0=
0G
1%
#50
0%
#55
01
1%
#60
1G
0%
1&
#65
11
1%
#70
0%
#75
1%
#80
0%
0&
1'
#85
0G
1H
1%
#90
0%
#95
01
10
1%
#100
1G
0%
1&
#105
11
1%
#110
0%
#115
1%
#120
0%
0&
0'
#125
0G
0H
1%
#130
0%
#135
01
00
1%
#140
1G
0%
1&
#145
11
1%
#150
0%
#155
1%
#160
0%
0&
#165
0G
1%
#170
0%
#175
01
1%
#180
1G
0%
1&
#185
11
1%
#190
0%
#195
1%
#200
0%
0&
1'
#205
0G
1H
1%
#210
0%
#215
01
10
1%
#220
1G
0%
1&
#225
11
1%
#230
0%
#235
1%
#240
0%
0&
0'
#245
0G
0H
1%
#250
0%
#255
01
00
1%
