Lab2/verilog/binary_to_sg.v
module binary_to_sg
  (input  [3:0] binary_in,
   output reg [7:0] sev_seg);

   always @ (binary_in) begin
      case(binary_in)
        4'b0000 : sev_seg = 8'b11000000; //0

        4'b0001 :  sev_seg = 8'b11111001; //1

        4'b0010:  sev_seg = 8'b10100100; //2

        4'b0011:  sev_seg = 8'b10110000; //...

        4'b0100:  sev_seg = 8'b10011001;

        4'b0101:  sev_seg = 8'b10010010;

        4'b0110: sev_seg = 8'b10000010;

        4'b0111: sev_seg = 8'b11111000;

        4'b1000: sev_seg = 8'b10000000;

        4'b1001: sev_seg = 8'b10010000; //9

        4'b1111 : sev_seg = 8'b11111111; //off

        default : sev_seg = 8'b10000110; //error

      endcase // case (sel)
   end // always @ (binary_in)


endmodule

Lab2/verilog/convert_to_binary.v
module convert_to_binary
  (input [7:0] scan_code_in,
   output reg [3:0] binary_out);



  /* convert_to_binary.vhd:16:17  */
  always @ (scan_code_in) begin
    case (scan_code_in)
      8'h00: binary_out = 4'b1111;
      8'h46: binary_out = 4'b1001;
      8'h3E: binary_out = 4'b1000;
      8'h3D: binary_out = 4'b0111;
      8'h36: binary_out = 4'b0110;
      8'h2E: binary_out = 4'b0101;
      8'h25: binary_out = 4'b0100;
      8'h26: binary_out = 4'b0011;
      8'h1E: binary_out = 4'b0010;
      8'h16: binary_out = 4'b0001;
      8'h45: binary_out = 4'b0000;
      default: binary_out = 4'b1010;
    endcase // case (scan_code_in)
  end // always @ (scan_code_in)

endmodule

Lab2/verilog/keyboard_ctrl.v
module keyboard_ctrl
(input            clk,
 input            rst,
 input            valid_code,
 input [7:0]      scan_code_in,
 output reg[7:0] code_to_display,
 output reg [3:0] seg_en);

reg state, next_state;
reg [31:0] scanCodes;
reg [1:0] seg_counter;
reg [17:0] counter;
//reg [3:0] seg_en;
//reg [7:0] code_to_display;

   always @ (posedge clk, negedge rst)
     if (~rst) begin
        state <= 0;
        next_state <= 0;
        scanCodes <= 0;
        counter <= 0;
        seg_counter <= 0;
        code_to_display <= scanCodes[31:24];
        seg_en <= "1111";
     end else if (counter == 4)begin
        counter <= 0;
        seg_counter <= seg_counter + 1;
     end else begin
        counter <= counter + 1;
        state <= next_state;
     end

always @(state)
if (valid_code)begin
case(state)
  0: 
    if(scan_code_in == "11110000")begin
      next_state <= 1;
      
    end else begin
      //do nothin
    end
  1: 
    if(scan_code_in == "11110000") begin
      scanCodes = scanCodes << 8; 
    end else if(scanCodes[31:24] == "00000000")begin 
      scanCodes[31:24] <= scan_code_in;
    end
  default:begin
    //do nothing
  end
endcase
end 

   always @ (seg_counter)
     begin
        case(seg_counter)
          0: begin
             seg_en <= "1110";
             code_to_display <= scanCodes[31:24];
          end
          1: begin
             seg_en <= "1101";
             code_to_display <= scanCodes[23:16];
          end
          2: begin
             seg_en <= "1011";
             code_to_display <= scanCodes[15:8];
          end
          3: begin
             seg_en <= "0111";
             code_to_display <= scanCodes[7:0];
          end
        endcase
     end

endmodule

Lab2/verilog/convert_scancode.v
module convert_scancode
  (input  clk,
   input  rst,
   input  edge_found,
   input  serial_data,
   output reg valid_scan_code,
   output reg [7:0] scan_code_out);

   reg [9:0] scan_code = 0;

   reg [3:0] counter;

   always @ (posedge clk, negedge rst)
   if (~rst) begin
    scan_code_out <= 0;
    valid_scan_code <= 0;
    counter <= 0;
   end else if(edge_found & (counter == 10)) begin
    scan_code[8:0] <= scan_code[9:1];
    scan_code[9] <= serial_data;
    scan_code_out[7:0] <= scan_code[7:0];
    counter <= 0;
    valid_scan_code <= 1;

   end else if (edge_found) begin
    scan_code[8:0] <= scan_code[9:1];
    scan_code[9] <= serial_data;
    scan_code_out[7:0] <= scan_code[7:0];
    counter <= counter + 1;
    valid_scan_code <= 0;
   end else begin
    //do nothing
   end

endmodule

Lab2/verilog/edge_detector.v
module edge_detector
  (input  clk,
   input  rst,
   input  kb_clk_sync,
   output edge_found);

  reg kb_clk_in;
  reg edge_found;

  always @(posedge clk)
  if(~rst) begin
    kb_clk_in <= 0;
  end else begin
    kb_clk_in <= kb_clk_sync;
    edge_found <= (!kb_clk_sync & kb_clk_in);
  end

endmodule

Lab2/verilog/sync_keyboard.v
module sync_keyboard
  (input  clk,
   input  kb_clk,
   input  kb_data,
   output reg kb_clk_sync,
   output reg kb_data_sync);
  reg data_1, clk_1;
//maybe add kb_clk, chatgpt suggested
  always @ (posedge clk)
  begin
    data_1 <= kb_data;
    kb_data_sync <= data_1;
    clk_1 <= kb_clk;
    kb_clk_sync <= clk_1;
  end
endmodule

Lab2/verilog/keyboard_top.v
module keyboard_top
  (input        clk,
   input        rst,
   input        kb_data,
   input        kb_clk,
   output [7:0] sc,
   output [7:0] num,
   output [3:0] seg_en);

   // set up all ports here

   wire [7:0] scan_code_out;
   wire       edge_found;
   wire       kb_data_sync;
   wire       kb_clk_sync;
   wire       valid_scan_code;
   wire [7:0] code_to_display;
   wire [7:0] sev_seg;
   wire [3:0] binary_out;
   wire [3:0] binary_num;


   // connect all ports here
   // module followed by DUT name
   sync_keyboard sync_keyboard_inst (
                                     .clk(clk),
                                     .kb_clk(kb_clk),
                                     .kb_data(kb_data),
                                     .kb_clk_sync(kb_clk_sync),
                                     .kb_data_sync(kb_data_sync));
   /* keyboard_top.vhd:113:5  */
   edge_detector edge_detector_inst (
                                     .clk(clk),
                                     .rst(rst),
                                     .kb_clk_sync(kb_clk_sync),
                                     .edge_found(edge_found));


   /* keyboard_top.vhd:124:5  */
   convert_scancode convert_scancode_inst (
                                           .clk(clk),
                                           .rst(rst),
                                           .edge_found(edge_found),
                                           .serial_data(kb_data_sync),
                                           .valid_scan_code(valid_scan_code),
                                           .scan_code_out(scan_code_out));



   /* keyboard_top.vhd:138:5  */
   keyboard_ctrl keyboard_ctrl_inst (
                                     .clk(clk),
                                     .rst(rst),
                                     .valid_code(valid_scan_code),
                                     .scan_code_in(scan_code_out),
                                     .code_to_display(code_to_display),
                                     .seg_en(seg_en));



   /* keyboard_top.vhd:148:5  */
   convert_to_binary convert_to_binary_inst (
                                             .scan_code_in(code_to_display),
                                             .binary_out(binary_out));



   /* keyboard_top.vhd:155:5  */
   binary_to_sg binary_to_sg_inst (
                                   .binary_in(binary_num),
                                   .sev_seg(sev_seg));
endmodule

Lab2/verilog/tb_pkg.v
module tb_pkg;

   reg clk = 0;
   reg rst = 0;
   reg kb_data = 1;
   reg kb_clk = 0;
   wire [7:0] sc = 0;
   wire [7:0] num = 0;
   wire [3:0] seg_en = 0;

   keyboard_top DUT (
                     .clk(clk),
                     .rst(rst),
                     .kb_data(kb_data),
                     .sc(sc),
                     .num(num),
                     .seg_en(seg_en),
                     .kb_clk(kb_clk)
                     );


   // duration for each bit = 20 * timescale = 20 * 1 ns  = 20ns
   localparam period = 40;

   always #5 clk <= !clk;

   always #20 kb_clk <= !kb_clk;

   initial // initial block executes only once
     begin


        // these need to be commented out for schematics
        $dumpfile("test.vcd");
        $dumpvars(0,tb_pkg);

        // start sending data
        // values for a and b

        #period; // wait for period
        rst <= 1;

        // 0x16, 11 bit long
        #period;

        kb_data = 0;
        #period;

        kb_data = 0;
        #period;

        kb_data = 0;
        #period;

        kb_data = 0;
        #period;

        kb_data = 0;
        #period;

        kb_data = 0;

        //payload

        #period
          kb_data = 1;

        #period;

        kb_data = 0;

        #period;

        kb_data = 1;

        #period;
        kb_data = 1;

        #period;

        kb_data = 0;

        //0x1E
        #period;

        kb_data = 0;
        #period;

        kb_data = 0;
        #period;

        kb_data = 0;
        #period;

        kb_data = 0;
        #period;

        kb_data = 0;
        #period;

        kb_data = 0;

        #period
          //payload

          kb_data = 1;

        #period

          kb_data = 1;

        #period;

        kb_data = 1;

        #period;

        kb_data = 1;

        #period;
        kb_data = 0;

        #period;

        kb_data = 0;


        $finish();
     end // initial begin
endmodule

Lab2/verilog/test.vcd
$date
	Fri Sep 15 10:53:31 2023
$end
$version
	Icarus Verilog
$end
$timescale
	1s
$end
$scope module tb_pkg $end
$var wire 8 ! num [7:0] $end
$var wire 8 " sc [7:0] $end
$var wire 4 # seg_en [3:0] $end
$var parameter 32 $ period $end
$var reg 1 % clk $end
$var reg 1 & kb_clk $end
$var reg 1 ' kb_data $end
$var reg 1 ( rst $end
$scope module DUT $end
$var wire 4 ) binary_num [3:0] $end
$var wire 1 % clk $end
$var wire 1 & kb_clk $end
$var wire 1 ' kb_data $end
$var wire 8 * num [7:0] $end
$var wire 1 ( rst $end
$var wire 8 + sc [7:0] $end
$var wire 4 , seg_en [3:0] $end
$var wire 1 - valid_scan_code $end
$var wire 8 . sev_seg [7:0] $end
$var wire 8 / scan_code_out [7:0] $end
$var wire 1 0 kb_data_sync $end
$var wire 1 1 kb_clk_sync $end
$var wire 1 2 edge_found $end
$var wire 8 3 code_to_display [7:0] $end
$var wire 4 4 binary_out [3:0] $end
$scope module binary_to_sg_inst $end
$var wire 4 5 binary_in [3:0] $end
$var reg 8 6 sev_seg [7:0] $end
$upscope $end
$scope module convert_scancode_inst $end
$var wire 1 % clk $end
$var wire 1 ( rst $end
$var wire 1 0 serial_data $end
$var wire 1 2 edge_found $end
$var reg 4 7 counter [3:0] $end
$var reg 10 8 scan_code [9:0] $end
$var reg 8 9 scan_code_out [7:0] $end
$var reg 1 - valid_scan_code $end
$upscope $end
$scope module convert_to_binary_inst $end
$var wire 8 : scan_code_in [7:0] $end
$var reg 4 ; binary_out [3:0] $end
$upscope $end
$scope module edge_detector_inst $end
$var wire 1 % clk $end
$var wire 1 ( rst $end
$var wire 1 1 kb_clk_sync $end
$var reg 1 2 edge_found $end
$var reg 1 < kb_clk_in $end
$upscope $end
$scope module keyboard_ctrl_inst $end
$var wire 1 % clk $end
$var wire 1 ( rst $end
$var wire 8 = scan_code_in [7:0] $end
$var wire 1 - valid_code $end
$var reg 8 > code_to_display [7:0] $end
$var reg 18 ? counter [17:0] $end
$var reg 1 @ next_state $end
$var reg 32 A scanCodes [31:0] $end
$var reg 2 B seg_counter [1:0] $end
$var reg 4 C seg_en [3:0] $end
$var reg 1 D state $end
$upscope $end
$scope module sync_keyboard_inst $end
$var wire 1 % clk $end
$var wire 1 & kb_clk $end
$var wire 1 ' kb_data $end
$var reg 1 E clk_1 $end
$var reg 1 F data_1 $end
$var reg 1 1 kb_clk_sync $end
$var reg 1 0 kb_data_sync $end
$upscope $end
$upscope $end
$upscope $end
$enddefinitions $end
$comment Show the parameter values. $end
$dumpall
b101000 $
$end
#0
$dumpvars
xF
xE
0D
b0 C
b0 B
b0 A
0@
b0 ?
b0 >
b0 =
x<
b1111 ;
b0 :
b0 9
bx 8
b0 7
b10000110 6
bz 5
b1111 4
b0 3
x2
x1
x0
b0 /
b10000110 .
0-
b0 ,
b0 +
b0 *
bz )
0(
1'
0&
0%
b0 #
b0 "
b0 !
$end
#5
0E
1F
0<
1%
#10
0%
#15
01
10
1%
#20
0%
1&
#25
1E
1%
#30
0%
#35
11
1%
#40
0%
0&
1(
#45
b1 ?
0E
02
1<
1%
#50
0%
#55
b10 ?
01
1%
#60
0%
1&
#65
b11 ?
1E
12
0<
1%
#70
0%
#75
b1 7
bx /
bx 9
bx =
b1xxxxxxxxx 8
b100 ?
02
11
1%
#80
0%
0&
0'
#85
b0x #
b0x ,
b1 C
b1 B
b0 ?
0E
0F
1<
1%
#90
0%
#95
b1 ?
01
00
1%
#100
0%
1&
#105
b10 ?
1E
12
0<
1%
#110
0%
#115
b10 7
b1xxxxxxxx 8
b11 ?
02
11
1%
#120
0%
0&
#125
b100 ?
0E
1<
1%
#130
0%
#135
b10 B
b0 ?
01
1%
#140
0%
1&
#145
b1 ?
1E
12
0<
1%
#150
0%
#155
b11 7
b1xxxxxxx 8
b10 ?
02
11
1%
#160
0%
0&
#165
b11 ?
0E
1<
1%
#170
0%
#175
b100 ?
01
1%
#180
0%
1&
#185
b11 B
b0 ?
1E
12
0<
1%
#190
0%
#195
b100 7
b1xxxxxxx /
b1xxxxxxx 9
b1xxxxxxx =
b1xxxxxx 8
b1 ?
02
11
1%
#200
0%
0&
#205
b10 ?
0E
1<
1%
#210
0%
#215
b11 ?
01
1%
#220
0%
1&
#225
b100 ?
1E
12
0<
1%
#230
0%
#235
b0 #
b0 ,
b0 C
b101 7
b1xxxxxx /
b1xxxxxx 9
b1xxxxxx =
b1xxxxx 8
b0 B
b0 ?
02
11
1%
#240
0%
0&
#245
b1 ?
0E
1<
1%
#250
0%
#255
b10 ?
01
1%
#260
0%
1&
#265
b11 ?
1E
12
0<
1%
#270
0%
#275
b110 7
b1xxxxx /
b1xxxxx 9
b1xxxxx =
b1xxxx 8
b100 ?
02
11
1%
#280
0%
0&
#285
b0x #
b0x ,
b1 C
b1 B
b0 ?
0E
1<
1%
#290
0%
#295
b1 ?
01
1%
#300
0%
1&
#305
b10 ?
1E
12
0<
1%
#310
0%
#315
b111 7
b1xxxx /
b1xxxx 9
b1xxxx =
b1xxx 8
b11 ?
02
11
1%
#320
0%
0&
1'
#325
b100 ?
0E
1F
1<
1%
#330
0%
#335
b10 B
b0 ?
01
10
1%
#340
0%
1&
#345
b1 ?
1E
12
0<
1%
#350
0%
#355
b1000 7
b1xxx /
b1xxx 9
b1xxx =
b10000001xx 8
b10 ?
02
11
1%
#360
0%
0&
0'
#365
b11 ?
0E
0F
1<
1%
#370
0%
#375
b100 ?
01
00
1%
#380
0%
1&
#385
b11 B
b0 ?
1E
12
0<
1%
#390
0%
#395
b1001 7
b1xx /
b1xx 9
b1xx =
b10000001x 8
b1 ?
02
11
1%
#400
0%
0&
1'
#405
b10 ?
0E
1F
1<
1%
#410
0%
#415
b11 ?
01
10
1%
#420
0%
1&
#425
b100 ?
1E
12
0<
1%
#430
0%
#435
b0 #
b0 ,
b0 C
b1010 7
b1x /
b1x 9
b1x =
b1010000001 8
b0 B
b0 ?
02
11
1%
#440
0%
0&
#445
b1 ?
0E
1<
1%
#450
0%
#455
b10 ?
01
1%
#460
0%
1&
#465
b11 ?
1E
12
0<
1%
#470
0%
#475
1-
b0 7
b10000001 /
b10000001 9
b10000001 =
b1101000000 8
b100 ?
02
11
1%
#480
0%
0&
0'
#485
b0x #
b0x ,
b1 C
b1 B
b0 ?
0E
0F
1<
1%
#490
0%
#495
b1 ?
01
00
1%
#500
0%
1&
#505
b10 ?
1E
12
0<
1%
#510
0%
#515
0-
b1 7
b1000000 /
b1000000 9
b1000000 =
b110100000 8
b11 ?
02
11
1%
#520
0%
0&
#525
b100 ?
0E
1<
1%
#530
0%
#535
b10 B
b0 ?
01
1%
#540
0%
1&
#545
b1 ?
1E
12
0<
1%
#550
0%
#555
b10 7
b10100000 /
b10100000 9
b10100000 =
b11010000 8
b10 ?
02
11
1%
#560
0%
0&
#565
b11 ?
0E
1<
1%
#570
0%
#575
b100 ?
01
1%
#580
0%
1&
#585
b11 B
b0 ?
1E
12
0<
1%
#590
0%
#595
b11 7
b11010000 /
b11010000 9
b11010000 =
b1101000 8
b1 ?
02
11
1%
#600
0%
0&
#605
b10 ?
0E
1<
1%
#610
0%
#615
b11 ?
01
1%
#620
0%
1&
#625
b100 ?
1E
12
0<
1%
#630
0%
#635
b0 #
b0 ,
b0 C
b100 7
b1101000 /
b1101000 9
b1101000 =
b110100 8
b0 B
b0 ?
02
11
1%
#640
0%
0&
#645
b1 ?
0E
1<
1%
#650
0%
#655
b10 ?
01
1%
#660
0%
1&
#665
b11 ?
1E
12
0<
1%
#670
0%
#675
b101 7
b110100 /
b110100 9
b110100 =
b11010 8
b100 ?
02
11
1%
#680
0%
0&
#685
b0x #
b0x ,
b1 C
b1 B
b0 ?
0E
1<
1%
#690
0%
#695
b1 ?
01
1%
#700
0%
1&
#705
b10 ?
1E
12
0<
1%
#710
0%
#715
b110 7
b11010 /
b11010 9
b11010 =
b1101 8
b11 ?
02
11
1%
#720
0%
0&
#725
b100 ?
0E
1<
1%
#730
0%
#735
b10 B
b0 ?
01
1%
#740
0%
1&
#745
b1 ?
1E
12
0<
1%
#750
0%
#755
b111 7
b1101 /
b1101 9
b1101 =
b110 8
b10 ?
02
11
1%
#760
0%
0&
1'
#765
b11 ?
0E
1F
1<
1%
#770
0%
#775
b100 ?
01
10
1%
#780
0%
1&
#785
b11 B
b0 ?
1E
12
0<
1%
#790
0%
#795
b1000 7
b110 /
b110 9
b110 =
b1000000011 8
b1 ?
02
11
1%
#800
0%
0&
#805
b10 ?
0E
1<
1%
#810
0%
#815
b11 ?
01
1%
#820
0%
1&
#825
b100 ?
1E
12
0<
1%
#830
0%
#835
b0 #
b0 ,
b0 C
b1001 7
b11 /
b11 9
b11 =
b1100000001 8
b0 B
b0 ?
02
11
1%
#840
0%
0&
#845
b1 ?
0E
1<
1%
#850
0%
#855
b10 ?
01
1%
#860
0%
1&
#865
b11 ?
1E
12
0<
1%
#870
0%
#875
b1010 7
b1 /
b1 9
b1 =
b1110000000 8
b100 ?
02
11
1%
#880
0%
0&
#885
b0x #
b0x ,
b1 C
b1 B
b0 ?
0E
1<
1%
#890
0%
#895
b1 ?
01
1%
#900
0%
1&
#905
b10 ?
1E
12
0<
1%
#910
0%
#915
1-
b0 7
b10000000 /
b10000000 9
b10000000 =
b1111000000 8
b11 ?
02
11
1%
#920
0%
0&
0'
#925
b100 ?
0E
0F
1<
1%
#930
0%
#935
b10 B
b0 ?
01
00
1%
#940
0%
1&
#945
b1 ?
1E
12
0<
1%
#950
0%
#955
0-
b1 7
b11000000 /
b11000000 9
b11000000 =
b111100000 8
b10 ?
02
11
1%
