Lab3/verilog/ALU_ctrl.v
module ALU_ctrl (
                 input        clk,
                 input        rst_n,
                 input        enter,
                 input        sign,
                 output [3:0] func,
                 output [1:0] reg_ctrl
                 );



endmodule

Lab3/verilog/testbench_ALU_ctrl.v
// Simulation parameters
`timescale 1ns / 1ps

module tb_ALU_ctrl () ;


   localparam  CLKT  = 10; // 100 MHz, 10ns

   // DUT instance parameters

   // Non-auto signals
   reg         clk   = 1'b0;
   reg         rst_n = 1'b1;

   // TODO: Init during declaration (before simulation time 0) to avoid race conditions
   /* DUT Inputs */
   reg         enter = 0; // To I_ALU_CTRL of ALU_ctrl.v
   reg         sign  = 0; // To I_ALU_CTRL of ALU_ctrl.v

   /* DUT Outputs */
   wire [3:0]   func;       // From I_ALU_CTRL of ALU_ctrl.v
   wire [1:0]   reg_ctrl;   // From I_ALU_CTRL of ALU_ctrl.v


   // System Clock
   always begin
      #(CLKT/2) clk = ~clk;
   end

   // DUT Instantiation
   ALU_ctrl I_ALU_CTRL (
                        // Inputs
                        .clk      (clk),
                        .rst_n    (rst_n),
                        .enter    (enter),
                        .sign     (sign),
                        // Outputs
                        .func     (func),
                        .reg_ctrl (reg_ctrl)
                        );


   initial begin
      $dumpfile("test.vcd");
      $dumpvars(0,tb_ALU_ctrl);

      // *************************
      // User test data pattern
      // *************************

      rst_n <= 0;
      #CLKT;
      rst_n <= 1;
      #1;
      enter <= 1;
      #CLKT;
      enter <= 0;
      #CLKT;
      enter <= 1;
      #CLKT;
      enter <= 0;
      #CLKT;
      enter <= 1;
      #CLKT;
      enter <= 0;
      #CLKT;
      sign <= 1;
      #CLKT;
      sign <= 0;
      #CLKT;
      enter <= 1;
      #CLKT;
      enter <= 0;
      #CLKT;
      enter <= 1;
      #CLKT;
      enter <= 0;
      #CLKT;
      enter <= 1;
      #CLKT;
      enter <= 0;
      #CLKT;




      $display("@%0d: TEST PASSED", $time);
      $finish;
   end

endmodule

Lab3/verilog/ALU.v
module ALU (
            input [7:0]  A,
            input [7:0]  B,
            input [3:0]  FN,
            output [7:0] result,
            output       overflow,
            output       sign
            );



endmodule

Lab3/verilog/testbench_ALU.v
// Simulation parameters
`timescale 1ns / 1ps


module tb_ALU () ;


   localparam  CLKT  = 10; // 100 MHz, 10ns

   // DUT instance parameters

   // Non-auto signals
   reg         clk   = 1'b0;

   // TODO: Init during declaration (before simulation time 0) to avoid race conditions
   /* DUT Inputs */
   reg [7:0]   A     = 0; // To I_ALU of ALU.v
   reg [7:0]   B     = 0; // To I_ALU of ALU.v
   reg [3:0]   FN    = 0; // To I_ALU of ALU.v

   /* DUT Outputs */
   wire         overflow;   // From I_ALU of ALU.v
   wire [7:0]   result;     // From I_ALU of ALU.v
   wire         sign;       // From I_ALU of ALU.v



   reg [7:0]   A_reg;
   reg [7:0]   B_reg;
   reg [3:0]   FN_reg;
   reg [2:0]   counter;


   // System Clock
   always begin
      #(CLKT/2) clk = ~clk;
   end

   // DUT Instantiation
   ALU I_ALU (
              // Inputs
              .A        (A),
              .B        (B),
              .FN       (FN),
              // Outputs
              .result   (result),
              .overflow (overflow),
              .sign     (sign)
              );


   initial begin
      $dumpfile("test.vcd");
      $dumpvars(0,tb_ALU);

      // *************************
      // User test data pattern
      // *************************
      A_reg <= 8'b00000101; //5
      B_reg <= 8'b00000011; //3
      FN_reg <= 4'b0000;
      #CLKT;
      A_reg <= 8'b00001001; //9
      B_reg <= 8'b00000011; //3
      FN_reg <= 4'b0001;
      #CLKT;
      A_reg <= 8'b00010001; //17
      B_reg <= 8'b10010001; //145
      FN_reg <= 4'b0000;
      #CLKT;
      A_reg <= 8'b10010001; //145
      B_reg <= 8'b01111100; //124
      FN_reg <= 4'b0001;
      #CLKT;
      A_reg <= 8'b10010100; //148
      B_reg <= 8'b11111001; //249
      FN_reg <= 4'b0100;
      #CLKT;
      A_reg <= 8'b11010101; //213
      B_reg <= 8'b01101001; //105
      FN_reg <= 4'b0100;
      #CLKT;
      A_reg <= 8'b00100011; //35
      B_reg <= 8'b01100011; //35
      FN_reg <= 4'b0100;
      #CLKT;
      A_reg <= 8'b11110010; //242
      B_reg <= 8'b01101000; //104
      FN_reg <= 4'b0100;
      #CLKT;
      A_reg <= 8'b00110001; //49
      B_reg <= 8'b00101101; //45
      FN_reg <= 4'b0100;
      #CLKT;
      A_reg <= 8'b01010101; //85
      B_reg <= 8'b00100100; //36
      FN_reg <= 4'b0100;
      #CLKT;
      A_reg <= 8'b00000000; // Invalid input command
      B_reg <= 8'b00000000; // Invalid input command
      FN_reg <= 4'b1111;    // Invalid input command
      #CLKT;

      // The following operations are performed
      // Pass A
      // Pass B
      // Pass A
      // Pass B
      // Pass unsigned A + B
      // Pass unsigned A - B
      // Pass unsigned A - B
      // Pass unsigned A + B
      // Pass unsigned A - B
      // Pass unsigned max(A,
      // Pass signed A + B
      // Pass signed A - B
      // Pass signed max(A, B)
      // Invalid input command
      assign A = A_reg;
      assign B = B_reg;
      assign FN = FN_reg;

      $display("@%0d: TEST PASSED", $time);
      $finish;
   end // initial begin

endmodule

Lab3/verilog/test.vcd
$date
	Mon Oct  2 18:47:19 2023
$end
$version
	Icarus Verilog
$end
$timescale
	1ps
$end
$scope module tb_ALU $end
$var wire 1 ! overflow $end
$var wire 8 " result [7:0] $end
$var wire 1 # sign $end
$var parameter 32 $ CLKT $end
$var reg 8 % A [7:0] $end
$var reg 8 & A_reg [7:0] $end
$var reg 8 ' B [7:0] $end
$var reg 8 ( B_reg [7:0] $end
$var reg 4 ) FN [3:0] $end
$var reg 4 * FN_reg [3:0] $end
$var reg 1 + clk $end
$scope module I_ALU $end
$var wire 8 , A [7:0] $end
$var wire 8 - B [7:0] $end
$var wire 4 . FN [3:0] $end
$var wire 1 ! overflow $end
$var wire 8 / result [7:0] $end
$var wire 1 # sign $end
$upscope $end
$upscope $end
$scope module tb_ALU_ctrl $end
$var wire 4 0 func [3:0] $end
$var wire 2 1 reg_ctrl [1:0] $end
$var parameter 32 2 CLKT $end
$var reg 1 3 clk $end
$var reg 1 4 enter $end
$var reg 1 5 rst_n $end
$var reg 1 6 sign $end
$scope module I_ALU_CTRL $end
$var wire 1 3 clk $end
$var wire 1 4 enter $end
$var wire 4 7 func [3:0] $end
$var wire 2 8 reg_ctrl [1:0] $end
$var wire 1 5 rst_n $end
$var wire 1 6 sign $end
$upscope $end
$upscope $end
$enddefinitions $end
$comment Show the parameter values. $end
$dumpall
b1010 2
b1010 $
$end
#0
$dumpvars
bz 8
bz 7
06
05
04
03
bz 1
bz 0
bz /
b0 .
b0 -
b0 ,
0+
b0 *
b0 )
b11 (
b0 '
b101 &
b0 %
z#
bz "
z!
$end
#5000
13
1+
#10000
15
b1 *
b1001 &
03
0+
#11000
14
#15000
13
1+
#20000
b0 *
b10010001 (
b10001 &
03
0+
#21000
04
#25000
13
1+
#30000
b1 *
b1111100 (
b10010001 &
03
0+
#31000
14
#35000
13
1+
#40000
b100 *
b11111001 (
b10010100 &
03
0+
#41000
04
#45000
13
1+
#50000
b1101001 (
b11010101 &
03
0+
#51000
14
#55000
13
1+
#60000
b1100011 (
b100011 &
03
0+
#61000
04
#65000
13
1+
#70000
b1101000 (
b11110010 &
03
0+
#71000
16
#75000
13
1+
#80000
b101101 (
b110001 &
03
0+
#81000
06
#85000
13
1+
#90000
b100100 (
b1010101 &
03
0+
#91000
14
#95000
13
1+
#100000
b1111 *
b0 (
b0 &
03
0+
#101000
04
#105000
13
1+
#110000
03
0+
b1111 )
b1111 .
