Lab3/verilog/reg_updater.v
module reg_updater (
                   input        clk,
                   input        rst_n,
                   input [1:0]  reg_ctrl, //2'b01 for A 2'b10 for B
                   input [7:0]  sw_input,
                   output [7:0] A,
                   output [7:0] B
                    );

   reg [7:0] r_A,r_B;


   // If changed to clk we can change the value of B during computations, cool?
   // Unsure about this
   always @(reg_ctrl or rst_n /* or sw_input */) begin
      if (!rst_n) begin
         r_A <= 8'b0;
         r_B <= 8'b0;
      end else begin
         case (reg_ctrl)
           2'b01: r_A <= sw_input;
           2'b10: r_B <= sw_input;
           default: // Handle any other values of reg_ctrl, maybe add in alu_ctrl to use this
             begin
                r_A <= 8'b0;
                r_B <= 8'b0;
             end
         endcase

      end
   end

   assign A = r_A;
   assign B = r_B;



endmodule

Lab3/verilog/testbench_reg.v
// Simulation parameters
`timescale 1ns / 1ps

module tb_reg_updater () ;

   localparam  CLKT  = 10; // 100 MHz, 10ns
   localparam  period  = 40; // 20 MHz, 40ns

    // DUT instance parameters

    // Non-auto signals
   reg       clk      = 1'b0;
   reg       rst_n    = 1'b1;

    /* DUT Inputs */
   reg [1:0] reg_ctrl = 2'b00; // To I_REG_UPDATER of reg_updater.v
   reg [7:0] sw_input = 0; // To I_REG_UPDATER of reg_updater.v

    /* DUT Outputs */
   wire [7:0] A;             // From I_REG_UPDATER of reg_updater.v
   wire [7:0] B;             // From I_REG_UPDATER of reg_updater.v


    // System Clock
    always begin
        #(CLKT/2) clk = ~clk;
    end

    // DUT Instantiation
   reg_updater I_REG_UPDATER (
                              // Outputs
                              .A        (A),
                              .B        (B),
                              // Inputs
                              .clk      (clk),
                              .rst_n    (rst_n),
                              .reg_ctrl (reg_ctrl),
                              .sw_input (sw_input)
                              );
   initial begin

      $dumpfile("test.vcd");
      $dumpvars(0,tb_reg_updater);

      sw_input <= 8'b0000_0011;
      #period;

      reg_ctrl <= 2'b00;
      #period;

      //sw_input <= 8'b0000_1100;

      #period;

      reg_ctrl <= 2'b01;

      #period;

            sw_input <= 8'b0000_1100;

            #period;

            reg_ctrl <= 2'b11;

      #period;

            sw_input <= 8'b0001_1110;

      #period;

            sw_input <= 8'b0101_1110;

      #period;


      $display("@%0d: reg_updater TEST PASSED", $time);
      //$finish;
   end

endmodule

Lab3/verilog/binary_to_bcd.v
module binary_to_bcd (
                      input [7:0]  binary_in,
                      output wire [9:0] bcd_out
                      );

   //Internal variables
   reg [11:0] reg_bcd_out;
   reg [3:0]  i;

   //Implement the Double Dabble algorithm
   always @(binary_in)
     begin
        reg_bcd_out = 0; //initialize reg_bcd_out to zero.
        for (i = 0; i < 8; i = i+1) //run for 8 iterations
          begin
             reg_bcd_out = {reg_bcd_out[10:0],binary_in[7-i]}; //concatenation

             //if a hex digit of 'reg_bcd_out' is more than 4, add 3 to it.
             if(i < 7 && reg_bcd_out[3:0] > 4)
               reg_bcd_out[3:0] = reg_bcd_out[3:0] + 3;
             if(i < 7 && reg_bcd_out[7:4] > 4)
               reg_bcd_out[7:4] = reg_bcd_out[7:4] + 3;
             if(i < 7 && reg_bcd_out[11:8] > 4)
               reg_bcd_out[11:8] = reg_bcd_out[11:8] + 3;
          end
     end


   //to obtain max 255 we can remove 2 bits :)
   assign bcd_out = reg_bcd_out[9:0];


endmodule

Lab3/verilog/testbench_bcd.v
// Simulation parameters
`timescale 1ns / 1ps



module tb_binary_to_bcd () ;

   localparam  CLKT  = 10; // 100 MHz, 10ns
   localparam  period  = 40; // 20 MHz, 40ns


    // TODO: INIT after (verilog-auto)!!
    // DUT instance parameters

    // Non-auto signals
   reg       Clk       = 1'b0;
   reg       Rst_n     = 1'b1;

    // TODO: Init during declaration (before simulation time 0) to avoid race conditions
    /* DUT Inputs */
   reg [7:0] binary_in = 0; // To I_BINARY_TO_BCD of binary_to_bcd.v

    /* DUT Outputs */
   wire [9:0] bcd_out;        // From I_BINARY_TO_BCD of binary_to_bcd.v


    // System Clock
    always begin
        #(CLKT/2) Clk = ~Clk;
    end

    // TODO: Declare/Connect interfaces
    // axi4_lite_if axil_if_binary_to_bcd (.Clk(Clk), .Rst_n(Rst_n));
    // ...

    // TODO: Ensure SV interfaces connections
    // DUT Instantiation
   binary_to_bcd I_BINARY_TO_BCD (
                                  // Outputs
                                  .bcd_out   (bcd_out),
                                  // Inputs
                                  .binary_in (binary_in)
                                  );


    // TODO: Tasks/functions
    // ...

    // TODO: TB Objects
    // axi4_lite_bfm bfm;

    // TODO: Stimuli
   initial begin
      $dumpfile("test.vcd");
      $dumpvars(0,tb_binary_to_bcd);

      #period;

      binary_in <= 8'b1111_1001;

      #period;



      $display("@%0d: BCD TEST PASSED", $time);
      //$finish;
   end

endmodule

Lab3/verilog/seven_segment_driver.v
`timescale 1ns / 1ps
module seven_segment_driver (
                             input        clk,
                             input        rst_n,
                             input [9:0]  BCD_digit, //this is basically 3 digits
                             input        sign,
                             input        overflow,
                             output [7:0] digit_anode, //segment enable
                             output [7:0] segment //number to show
                             );

   reg [7:0]      segment_state;
   reg [31:0]     segment_counter;
   reg [3:0]      routed_vals;
   wire [7:0]     led_out;

   sc_to_seven_seg my_converter ( .BCD_digit(routed_vals), .led_out(led_out));
   assign segment = led_out; //siffran som ska lysa
   assign digit_anode = ~segment_state; //segment to enable

   //Also add sign for sign and overflow led
   always @* begin
      case(segment_state)
        8'b0000_0001:   routed_vals = BCD_digit[3:0]; //ental
        8'b0000_0010:   routed_vals = BCD_digit[7:4]; //tiotal
        8'b0000_0100:   routed_vals = {2'b00 , BCD_digit[9:8]}; //hundratal
        default:        routed_vals = BCD_digit[7:0];
      endcase
   end

   always @(posedge clk or negedge rst_n)begin
      if (~rst_n)begin
         segment_state <= 8'b0000_0001;
         segment_counter <= 32'b0;
      end else begin
         if (segment_counter == 32'd100_000)begin
            segment_counter <= 32'd0;
            segment_state <= {segment_state[7:4],segment_state[2:0],segment_state[3]};
         end else begin
            segment_counter <= segment_counter +1;
         end
      end
   end

endmodule //seven_seg_controller


module sc_to_seven_seg ( input [3:0] BCD_digit, output wire [7:0] led_out);

    reg [7:0] int_seven_segment_number;

    //shift this in every clk
   always @* begin
      case(BCD_digit)
        //create mapping here for BCD_digits to numbers
        4'b0000 : int_seven_segment_number = 8'b11000000; //0

        4'b0001 :  int_seven_segment_number = 8'b11111001; //1

        4'b0010:  int_seven_segment_number = 8'b10100100; //2

        4'b0011:  int_seven_segment_number = 8'b10110000; //...

        4'b0100:  int_seven_segment_number = 8'b10011001;

        4'b0101:  int_seven_segment_number = 8'b10010010;

        4'b0110: int_seven_segment_number = 8'b10000010;

        4'b0111: int_seven_segment_number = 8'b11111000;

        4'b1000: int_seven_segment_number = 8'b10000000;

        4'b1001: int_seven_segment_number = 8'b10010000; //9

        4'b1111 : int_seven_segment_number = 8'b11111111; //off

        default : int_seven_segment_number = 8'b10000110; //error


      endcase
   end

    assign led_out = int_seven_segment_number;

endmodule // sc_to_seven_seg

Lab3/verilog/ALU.v
module ALU (
            input [7:0]  A,
            input [7:0]  B,
            input [3:0]  FN,
            output [7:0] result,
            output       overflow,
            output       sign
            );


   reg [7:0] ALU_Result;
   wire [8:0] tmp;
   reg        pn;

// mod 3 missing
   always @(*)
     begin
        case(FN)
          4'b0000: // A
            ALU_Result = A;
          4'b0001: // B
            ALU_Result = B;
          4'b0010: // Unsigned A + B
            ALU_Result = A + B;
          4'b0011: // Unsigned A - B
            ALU_Result = A - B;
          4'b0100: // Unsigned A mod 3
            ALU_Result = A % 3;
          // maybe the sign output is just to say if positive or negative for the signed case
          4'b1010: // Signed A + B
            ALU_Result = $signed(A) + $signed(B);
          4'b1011: // Signed A - B
            ALU_Result = $signed(A) - $signed(B);
          4'b1100: // Signed A mod 3
            ALU_Result = $signed(A) % 3;
          default: ALU_Result = A + B ;
        endcase // case (FN)

        // $signed might not be needed
        if ((FN == 4'b1010 || FN == 4'b1011 || FN == 4'b1100) && $signed(ALU_Result) < 0) begin
           pn <= 1;
        end else begin
           pn <= 0;
        end
     end

   assign result = ALU_Result;
   assign tmp = {1'b0,A} + {1'b0,B};
   assign overflow = tmp[8]; // Carryout flag
   assign sign = pn;




endmodule

Lab3/verilog/ALU_ctrl.v
module ALU_ctrl (
                 input        clk,
                 input        rst_n,
                 input        enter,
                 input        sign,
                 output wire [3:0] func,
                 output wire [1:0] reg_ctrl
                 );

    reg [3:0] state, next_state;
    reg [1:0] i_reg, next_i_reg;

   always @(posedge clk) begin
      if(~rst_n) begin
         state <= 0;
         i_reg <= 0;
      end else begin
         state <= next_state;
         i_reg <= next_i_reg;
      end
   end

   always @(posedge enter or posedge sign) begin
      next_state = state;
      next_i_reg = i_reg;

      if (enter) begin

         case (state)
           4'b0000: begin
              next_state = 4'b0001;
              next_i_reg = 2'b01;
           end
           4'b0001: begin
              next_state = 4'b0010;
              next_i_reg = 2'b10;
           end
           4'b0010: next_state = 4'b0011;
           4'b0011: next_state = 4'b0100;
           4'b0100: next_state = 4'b0010;
           4'b1010: next_state = 4'b1011;
           4'b1011: next_state = 4'b1100;
           4'b1100: next_state = 4'b1010;
           default: next_state = 4'b0000;
         endcase

      end else if (sign) begin

         case (state)
           4'b0000: next_state = 4'b0000;
           4'b0001: next_state = 4'b0001;
           4'b0010: next_state = 4'b1010;
           4'b0011: next_state = 4'b1011;
           4'b0100: next_state = 4'b1100;
           4'b1010: next_state = 4'b0010;
           4'b1011: next_state = 4'b0011;
           4'b1100: next_state = 4'b0100;
           default: next_state = 4'b0000;
         endcase

      end
   end

    assign func = state;
    assign reg_ctrl = i_reg;

endmodule

Lab3/verilog/debouncer.v
module debouncer (
                  input  clk,
                  input  rst_n,
                  input  button_in,
                  output wire button_out
                  );

   reg [19:0] count; //Range to count 20ms with 50 MHz clock
   //reg [1:0] count; //For simulation! actually just ignore debouncer for simulation retard!
   reg        button_tmp;
   reg        reg_button_out;


   always @(posedge clk or negedge rst_n) begin
      if (!rst_n) begin
         /*AUTORESET*/
         button_tmp <= 0;
         reg_button_out <= 0;
         count <= 0;
      end
      else begin
         count <= count + 1;
         button_tmp <= button_in;

         if (count == 0) begin
            reg_button_out <= button_tmp;
         end else
           begin
           // do nothing
           end
      end // else: !if(!rst_n)
   end // always @ (posedge clk)

   assign button_out = reg_button_out;


endmodule

Lab3/verilog/ALU_top.v
module ALU_top(
               input        clk,
               input        rst_n,
               input        b_enter,
               input        b_sign,
               input [7:0]  sw_in,
               output [7:0] sev_seg,
               output [7:0] anode
               );


   wire d_enter;
   wire d_sign;
   wire w_sign;
   wire w_overflow;
   wire [9:0] w_bcd_digit;
   wire [1:0] w_reg_ctrl;
   wire [3:0] w_func;
   wire [7:0] w_result;
   wire [7:0] A,B;



   // .modport(topport)
   debouncer enter_debouncer(
                             // Inputs
                             .clk        (clk),
                             .rst_n      (rst_n),
                             .button_in  (b_enter),
                             // Outputs
                             .button_out (d_enter)
                             );

   debouncer sign_debouncer(
                            // Inputs
                            .clk        (clk),
                            .rst_n      (rst_n),
                            .button_in  (b_sign),
                            // Outputs
                            .button_out (d_sign)
                            );

   ALU_ctrl I_ALU_CTRL(
                       // Inputs
                       .clk      (clk),
                       .rst_n    (rst_n),
                       .enter    (d_enter), //d_enter for IRL
                       .sign     (d_sign), //b_enter for SIM
                       // Outputs
                       .func     (w_func),
                       .reg_ctrl (w_reg_ctrl)
                       );

   reg_updater I_REG_UPDATER(
                             // Inputs
                             .clk      (clk),
                             .rst_n    (rst_n),
                             .reg_ctrl (w_reg_ctrl),
                             .sw_input (sw_in),
                             // Outputs
                             .A        (A),
                             .B        (B)
                             );

   ALU I_ALU (
              // Inputs
              .A        (A),
              .B        (B),
              .FN       (w_func),
              // Outputs
              .result   (w_result),
              .overflow (w_overflow),
              .sign     (w_sign)
              );


   binary_to_bcd I_BINARY_TO_BCD (
                                  // Inputs
                                  .binary_in (w_result),
                                  // Outputs
                                  .bcd_out   (w_bcd_digit)
                                  );


   seven_segment_driver I_SEVEN_SEGMENT_DRIVER (
                                                // Inputs
                                                .clk         (clk),
                                                .rst_n       (rst_n),
                                                .BCD_digit   (w_bcd_digit),
                                                .sign        (w_sign),
                                                .overflow    (w_overflow),
                                                // Outputs
                                                .digit_anode (anode),
                                                .segment     (sev_seg)
                                                );





endmodule

Lab3/verilog/testbench_top.v
// Simulation parameters
`timescale 1ns / 1ps

module tb_ALU_top () ;

   localparam  CLKT  = 10; // 100 MHz, 10ns
   //localparam  CLKT  = 2; // 100 MHz, 10ns
   localparam  period  = 40; // 20 MHz, 40ns

    // DUT instance parameters

    // Non-auto signals
   reg       clk     = 1'b0;
   reg       rst_n   = 1'b1;

    /* DUT Inputs */
   reg       b_enter = 0; // To I_ALU_TOP of ALU_top.v
   reg       b_sign  = 0; // To I_ALU_TOP of ALU_top.v
   reg [7:0] sw_in   = 0; // To I_ALU_TOP of ALU_top.v

    /* DUT Outputs */
   wire [7:0] anode;        // From I_ALU_TOP of ALU_top.v
   wire [7:0] sev_seg;      // From I_ALU_TOP of ALU_top.v


    // System Clock
    always begin
        #(CLKT/2) clk = ~clk;
    end

    // DUT Instantiation
   ALU_top I_ALU_TOP (
                      // Inputs
                      .clk     (clk),
                      .rst_n   (rst_n),
                      .b_enter (b_enter),
                      .b_sign  (b_sign),
                      .sw_in   (sw_in),
                      // Outputs
                      .sev_seg (sev_seg),
                      .anode   (anode)
                      );

   initial begin
      $dumpfile("test.vcd");
      $dumpvars(0,tb_ALU_top);

      rst_n <= 0;
      #1;
      rst_n <= 1;
      #period;

      sw_in <= 8'b0000_0011;
      #period;
      b_enter <= 1;
      #period;
      b_enter <= 0;
      #period;
      sw_in <= 8'b0000_0100;
      #period;
      b_enter <= 1;
      #period;
      b_enter <= 0;
      #period;
      b_enter <= 1;
      #period;
      b_enter <= 0;
      #period;
      b_enter <= 1;
      #period;
      b_enter <= 0;
      #period;
      b_enter <= 1;
      #period;
      b_enter <= 0;
      #period;


      $display("@%0d: TOP TEST PASSED", $time);
      $finish;
   end

endmodule

Lab3/verilog/testbench_ALU_ctrl.v
// Simulation parameters
`timescale 1ns / 1ps

module tb_ALU_ctrl () ;


   localparam  CLKT  = 10; // 100 MHz, 10ns
   localparam  period  = 40; // 20 MHz, 40ns

   // DUT instance parameters

   // Non-auto signals
   reg         clk   = 1'b0;
   reg         rst_n = 1'b1;

   // TODO: Init during declaration (before simulation time 0) to avoid race conditions
   /* DUT Inputs */
   reg         enter = 0; // To I_ALU_CTRL of ALU_ctrl.v
   reg         sign  = 0; // To I_ALU_CTRL of ALU_ctrl.v

   /* DUT Outputs */
   wire [3:0]   func;       // From I_ALU_CTRL of ALU_ctrl.v
   wire [1:0]   reg_ctrl;   // From I_ALU_CTRL of ALU_ctrl.v


   // System Clock
   always begin
      #(CLKT/2) clk = ~clk;
   end

   // DUT Instantiation
   ALU_ctrl I_ALU_CTRL (
                        // Inputs
                        .clk      (clk),
                        .rst_n    (rst_n),
                        .enter    (enter),
                        .sign     (sign),
                        // Outputs
                        .func     (func),
                        .reg_ctrl (reg_ctrl)
                        );


   initial begin
      $dumpfile("test.vcd");
      $dumpvars(0,tb_ALU_ctrl);

      // *************************
      // User test data pattern
      // *************************

      rst_n <= 0;
      #period;
      rst_n <= 1;
      #1;
      enter <= 1;
      #period;
      enter <= 0;
      #period;
      enter <= 1;
      #period;
      enter <= 0;
      #period;
      enter <= 1;
      #period;
      enter <= 0;
      #period;
      sign <= 1;
      #period;
      sign <= 0;
      #period;
      enter <= 1;
      #period;
      enter <= 0;
      #period;
      enter <= 1;
      #period;
      enter <= 0;
      #period;
      enter <= 1;
      #period;
      enter <= 0;
      #period;




      $display("@%0d: TEST PASSED", $time);
      $finish;
   end

endmodule

Lab3/verilog/testbench_ALU.v
// Simulation parameters
`timescale 1ns / 1ps


module tb_ALU () ;


   localparam  CLKT  = 10; // 100 MHz, 10ns
   localparam  period  = 40; // 20 MHz, 40ns

   // DUT instance parameters

   // Non-auto signals
   reg         clk   = 1'b0;

   // TODO: Init during declaration (before simulation time 0) to avoid race conditions
   /* DUT Inputs */
   reg [7:0]   A     = 0; // To I_ALU of ALU.v
   reg [7:0]   B     = 0; // To I_ALU of ALU.v
   reg [3:0]   FN    = 0; // To I_ALU of ALU.v

   /* DUT Outputs */
   wire         overflow;   // From I_ALU of ALU.v
   wire [7:0]   result;     // From I_ALU of ALU.v
   wire         sign;       // From I_ALU of ALU.v

   // System Clock
   always begin
      #(CLKT/2) clk = ~clk;
   end

   // DUT Instantiation
   ALU I_ALU (
              // Inputs
              .A        (A),
              .B        (B),
              .FN       (FN),
              // Outputs
              .result   (result),
              .overflow (overflow),
              .sign     (sign)
              );


   initial begin
      $dumpfile("test.vcd");
      $dumpvars(0,tb_ALU);

      //0100 unsigned mod 3
      //1100 signed mod 3


      // *************************
      // User test data pattern
      // *************************
      A <= 8'b00000101; //5
      B <= 8'b00000011; //3
      FN <= 4'b0000;
      #period;
      A <= 8'b00001001; //9
      B <= 8'b00000011; //3
      FN <= 4'b0001;
      #period;
      A <= 8'b00010001; //17
      B <= 8'b10010001; //145
      FN <= 4'b0010;
      #period;
      A <= 8'b10010001; //145
      B <= 8'b01111100; //124
      FN <= 4'b0011;
      #period;
      A <= 8'b10010100; //148
      B <= 8'b11111001; //249
      FN <= 4'b1010;
      #period;
      A <= 8'b1111_1110; //213
      B <= 8'b0000_0111; //105
      FN <= 4'b1011;
      #period;
      A <= 8'b00100011; //35
      B <= 8'b01100011; //35
      FN <= 4'b0010;
      #period;
      A <= 8'b0000_0010; //2
      B <= 8'b01101000; //104
      FN <= 4'b0100;
      #period;
      A <= 8'b0000_0011; //3
      B <= 8'b00101101; //45
      FN <= 4'b0100;
      #period;
      A <= 8'b01010101; //85
      B <= 8'b00100100; //36
      FN <= 4'b1100;
      #period;
      A <= 8'b00000000; // Invalid input command
      B <= 8'b00000000; // Invalid input command
      FN <= 4'b1111;    // Invalid input command
      #period;

      // The following operations are performed
      // Pass A
      // Pass B
      // Pass A
      // Pass B
      // Pass unsigned A + B
      // Pass unsigned A - B
      // Pass unsigned A - B
      // Pass unsigned A + B
      // Pass unsigned A - B
      // Pass unsigned max(A,
      // Pass signed A + B
      // Pass signed A - B
      // Pass signed max(A, B)
      // Invalid input command

      $display("@%0d: ALU TEST PASSED", $time);
      $finish;
   end // initial begin

endmodule

Lab3/verilog/test.vcd
$date
	Wed Oct  4 09:18:10 2023
$end
$version
	Icarus Verilog
$end
$timescale
	1ps
$end
$scope module tb_ALU $end
$var wire 1 ! sign $end
$var wire 8 " result [7:0] $end
$var wire 1 # overflow $end
$var parameter 32 $ CLKT $end
$var parameter 32 % period $end
$var reg 8 & A [7:0] $end
$var reg 8 ' B [7:0] $end
$var reg 4 ( FN [3:0] $end
$var reg 1 ) clk $end
$scope module I_ALU $end
$var wire 8 * A [7:0] $end
$var wire 8 + B [7:0] $end
$var wire 4 , FN [3:0] $end
$var wire 8 - result [7:0] $end
$var wire 1 ! sign $end
$var wire 9 . tmp [8:0] $end
$var wire 1 # overflow $end
$var reg 8 / ALU_Result [7:0] $end
$var reg 1 0 pn $end
$upscope $end
$upscope $end
$scope module tb_ALU_ctrl $end
$var wire 2 1 reg_ctrl [1:0] $end
$var wire 4 2 func [3:0] $end
$var parameter 32 3 CLKT $end
$var parameter 32 4 period $end
$var reg 1 5 clk $end
$var reg 1 6 enter $end
$var reg 1 7 rst_n $end
$var reg 1 8 sign $end
$scope module I_ALU_CTRL $end
$var wire 1 5 clk $end
$var wire 1 6 enter $end
$var wire 4 9 func [3:0] $end
$var wire 2 : reg_ctrl [1:0] $end
$var wire 1 7 rst_n $end
$var wire 1 8 sign $end
$var reg 2 ; i_reg [1:0] $end
$var reg 2 < next_i_reg [1:0] $end
$var reg 4 = next_state [3:0] $end
$var reg 4 > state [3:0] $end
$upscope $end
$upscope $end
$scope module tb_ALU_top $end
$var wire 8 ? sev_seg [7:0] $end
$var wire 8 @ anode [7:0] $end
$var parameter 32 A CLKT $end
$var parameter 32 B period $end
$var reg 1 C b_enter $end
$var reg 1 D b_sign $end
$var reg 1 E clk $end
$var reg 1 F rst_n $end
$var reg 8 G sw_in [7:0] $end
$scope module I_ALU_TOP $end
$var wire 1 C b_enter $end
$var wire 1 D b_sign $end
$var wire 1 E clk $end
$var wire 1 F rst_n $end
$var wire 8 H sw_in [7:0] $end
$var wire 1 I w_sign $end
$var wire 8 J w_result [7:0] $end
$var wire 2 K w_reg_ctrl [1:0] $end
$var wire 1 L w_overflow $end
$var wire 4 M w_func [3:0] $end
$var wire 10 N w_bcd_digit [9:0] $end
$var wire 8 O sev_seg [7:0] $end
$var wire 1 P d_sign $end
$var wire 1 Q d_enter $end
$var wire 8 R anode [7:0] $end
$var wire 8 S B [7:0] $end
$var wire 8 T A [7:0] $end
$scope module I_ALU $end
$var wire 8 U result [7:0] $end
$var wire 1 I sign $end
$var wire 9 V tmp [8:0] $end
$var wire 1 L overflow $end
$var wire 4 W FN [3:0] $end
$var wire 8 X B [7:0] $end
$var wire 8 Y A [7:0] $end
$var reg 8 Z ALU_Result [7:0] $end
$var reg 1 [ pn $end
$upscope $end
$scope module I_ALU_CTRL $end
$var wire 1 E clk $end
$var wire 1 C enter $end
$var wire 4 \ func [3:0] $end
$var wire 2 ] reg_ctrl [1:0] $end
$var wire 1 F rst_n $end
$var wire 1 D sign $end
$var reg 2 ^ i_reg [1:0] $end
$var reg 2 _ next_i_reg [1:0] $end
$var reg 4 ` next_state [3:0] $end
$var reg 4 a state [3:0] $end
$upscope $end
$scope module I_BINARY_TO_BCD $end
$var wire 8 b binary_in [7:0] $end
$var wire 10 c bcd_out [9:0] $end
$var reg 4 d i [3:0] $end
$var reg 12 e reg_bcd_out [11:0] $end
$upscope $end
$scope module I_REG_UPDATER $end
$var wire 1 E clk $end
$var wire 2 f reg_ctrl [1:0] $end
$var wire 1 F rst_n $end
$var wire 8 g sw_input [7:0] $end
$var wire 8 h B [7:0] $end
$var wire 8 i A [7:0] $end
$var reg 8 j r_A [7:0] $end
$var reg 8 k r_B [7:0] $end
$upscope $end
$scope module I_SEVEN_SEGMENT_DRIVER $end
$var wire 10 l BCD_digit [9:0] $end
$var wire 1 E clk $end
$var wire 8 m digit_anode [7:0] $end
$var wire 1 L overflow $end
$var wire 1 F rst_n $end
$var wire 8 n segment [7:0] $end
$var wire 1 I sign $end
$var wire 8 o led_out [7:0] $end
$var reg 4 p routed_vals [3:0] $end
$var reg 32 q segment_counter [31:0] $end
$var reg 8 r segment_state [7:0] $end
$scope module my_converter $end
$var wire 4 s BCD_digit [3:0] $end
$var wire 8 t led_out [7:0] $end
$var reg 8 u int_seven_segment_number [7:0] $end
$upscope $end
$upscope $end
$scope module enter_debouncer $end
$var wire 1 C button_in $end
$var wire 1 Q button_out $end
$var wire 1 E clk $end
$var wire 1 F rst_n $end
$var reg 1 v button_tmp $end
$var reg 20 w count [19:0] $end
$var reg 1 x reg_button_out $end
$upscope $end
$scope module sign_debouncer $end
$var wire 1 D button_in $end
$var wire 1 P button_out $end
$var wire 1 E clk $end
$var wire 1 F rst_n $end
$var reg 1 y button_tmp $end
$var reg 20 z count [19:0] $end
$var reg 1 { reg_button_out $end
$upscope $end
$upscope $end
$upscope $end
$scope module tb_binary_to_bcd $end
$var wire 10 | bcd_out [9:0] $end
$var parameter 32 } CLKT $end
$var parameter 32 ~ period $end
$var reg 1 !" Clk $end
$var reg 1 "" Rst_n $end
$var reg 8 #" binary_in [7:0] $end
$scope module I_BINARY_TO_BCD $end
$var wire 8 $" binary_in [7:0] $end
$var wire 10 %" bcd_out [9:0] $end
$var reg 4 &" i [3:0] $end
$var reg 12 '" reg_bcd_out [11:0] $end
$upscope $end
$upscope $end
$scope module tb_reg_updater $end
$var wire 8 (" B [7:0] $end
$var wire 8 )" A [7:0] $end
$var parameter 32 *" CLKT $end
$var parameter 32 +" period $end
$var reg 1 ," clk $end
$var reg 2 -" reg_ctrl [1:0] $end
$var reg 1 ." rst_n $end
$var reg 8 /" sw_input [7:0] $end
$scope module I_REG_UPDATER $end
$var wire 8 0" A [7:0] $end
$var wire 8 1" B [7:0] $end
$var wire 1 ," clk $end
$var wire 2 2" reg_ctrl [1:0] $end
$var wire 1 ." rst_n $end
$var wire 8 3" sw_input [7:0] $end
$var reg 8 4" r_A [7:0] $end
$var reg 8 5" r_B [7:0] $end
$upscope $end
$upscope $end
$enddefinitions $end
$comment Show the parameter values. $end
$dumpall
b101000 +"
b1010 *"
b101000 ~
b1010 }
b101000 B
b10 A
b101000 4
b1010 3
b101000 %
b1010 $
$end
#0
$dumpvars
b0 5"
b0 4"
b11 3"
b0 2"
b0 1"
b0 0"
b11 /"
1."
b0 -"
0,"
b0 )"
b0 ("
b0 '"
b1000 &"
b0 %"
b0 $"
b0 #"
1""
0!"
b0 |
0{
b0 z
0y
0x
b0 w
0v
b11000000 u
b11000000 t
b0 s
b1 r
b0 q
b0 p
b11000000 o
b11000000 n
b11111110 m
b0 l
b0 k
b0 j
b0 i
b0 h
b0 g
b0 f
b0 e
b1000 d
b0 c
b0 b
b0 a
bx `
bx _
b0 ^
b0 ]
b0 \
0[
b0 Z
b0 Y
b0 X
b0 W
b0 V
b0 U
b0 T
b0 S
b11111110 R
0Q
0P
b11000000 O
b0 N
b0 M
0L
b0 K
b0 J
0I
b0 H
b0 G
0F
0E
0D
0C
b11111110 @
b11000000 ?
b0 >
bx =
bx <
b0 ;
b0 :
b0 9
08
07
06
05
b0 2
b0 1
00
b101 /
b1000 .
b101 -
b0 ,
b11 +
b101 *
0)
b0 (
b11 '
b101 &
0#
b101 "
0!
$end
#1000
1F
1E
#2000
0E
#3000
b1 w
b1 z
bx K
bx ]
bx f
bx ^
bx M
bx W
bx \
bx a
b1 q
1E
#4000
0E
#5000
b10 q
b10 z
b10 w
1E
1,"
1!"
15
1)
#6000
0E
#7000
b11 w
b11 z
b11 q
1E
#8000
0E
#9000
b100 q
b100 z
b100 w
1E
#10000
0E
0,"
0!"
05
0)
#11000
b101 w
b101 z
b101 q
1E
#12000
0E
#13000
b110 q
b110 z
b110 w
1E
#14000
0E
#15000
b111 w
b111 z
b111 q
1E
1,"
1!"
15
1)
#16000
0E
#17000
b1000 q
b1000 z
b1000 w
1E
#18000
0E
#19000
b1001 w
b1001 z
b1001 q
1E
#20000
0E
0,"
0!"
05
0)
#21000
b1010 q
b1010 z
b1010 w
1E
#22000
0E
#23000
b1011 w
b1011 z
b1011 q
1E
#24000
0E
#25000
b1100 q
b1100 z
b1100 w
1E
1,"
1!"
15
1)
#26000
0E
#27000
b1101 w
b1101 z
b1101 q
1E
#28000
0E
#29000
b1110 q
b1110 z
b1110 w
1E
#30000
0E
0,"
0!"
05
0)
#31000
b1111 w
b1111 z
b1111 q
1E
#32000
0E
#33000
b10000 q
b10000 z
b10000 w
1E
#34000
0E
#35000
b10001 w
b10001 z
b10001 q
1E
1,"
1!"
15
1)
#36000
0E
#37000
b10010 q
b10010 z
b10010 w
1E
#38000
0E
#39000
b10011 w
b10011 z
b10011 q
1E
#40000
b11 )"
b11 0"
b11 4"
b1001001001 |
b1001001001 %"
b1001001001 '"
b1000 &"
b11 "
b11 -
b11 /
b1 -"
b1 2"
b11111001 #"
b11111001 $"
17
b1 (
b1 ,
b1100 .
b1001 &
b1001 *
0E
0,"
0!"
05
0)
#41000
b1 <
b1 =
b10100 q
b10100 z
b10100 w
16
b11 G
b11 H
b11 g
1E
#42000
0E
#43000
b10101 w
b10101 z
b10101 q
1E
#44000
0E
#45000
b10110 q
b10110 z
b10110 w
b1 1
b1 :
b1 ;
b1 2
b1 9
b1 >
1E
1,"
1!"
15
1)
#46000
0E
#47000
b10111 w
b10111 z
b10111 q
1E
#48000
0E
#49000
b11000 q
b11000 z
b11000 w
1E
#50000
0E
0,"
0!"
05
0)
#51000
b11001 w
b11001 z
b11001 q
1E
#52000
0E
#53000
b11010 q
b11010 z
b11010 w
1E
#54000
0E
#55000
b11011 w
b11011 z
b11011 q
1E
1,"
1!"
15
1)
#56000
0E
#57000
b11100 q
b11100 z
b11100 w
1E
#58000
0E
#59000
b11101 w
b11101 z
b11101 q
1E
#60000
0E
0,"
0!"
05
0)
#61000
b11110 q
b11110 z
b11110 w
1E
#62000
0E
#63000
b11111 w
b11111 z
b11111 q
1E
#64000
0E
#65000
b100000 q
b100000 z
b100000 w
1E
1,"
1!"
15
1)
#66000
0E
#67000
b100001 w
b100001 z
b100001 q
1E
#68000
0E
#69000
b100010 q
b100010 z
b100010 w
1E
#70000
0E
0,"
0!"
05
0)
#71000
b100011 w
b100011 z
b100011 q
1E
#72000
0E
#73000
b100100 q
b100100 z
b100100 w
1E
#74000
0E
#75000
b100101 w
b100101 z
b100101 q
1E
1,"
1!"
15
1)
#76000
0E
#77000
b100110 q
b100110 z
b100110 w
1E
#78000
0E
#79000
b100111 w
b100111 z
b100111 q
1E
#80000
b10100010 "
b10100010 -
b10100010 /
b1100 /"
b1100 3"
b10 (
b10 ,
b10010001 '
b10010001 +
b10100010 .
b10001 &
b10001 *
0E
0,"
0!"
05
0)
#81000
b0 `
b101000 q
b101000 z
b101000 w
06
1C
1E
#82000
0E
#83000
1v
b101001 w
b101001 z
b0 M
b0 W
b0 \
b0 a
b101001 q
1E
#84000
0E
#85000
b101010 q
b101010 z
b101010 w
1E
1,"
1!"
15
1)
#86000
0E
#87000
b101011 w
b101011 z
b101011 q
1E
#88000
0E
#89000
b101100 q
b101100 z
b101100 w
1E
#90000
0E
0,"
0!"
05
0)
#91000
b101101 w
b101101 z
b101101 q
1E
#92000
0E
#93000
b101110 q
b101110 z
b101110 w
1E
#94000
0E
#95000
b101111 w
b101111 z
b101111 q
1E
1,"
1!"
15
1)
#96000
0E
