Lab3/verilog/binary_to_bcd.v
module binary_to_bcd (
                      input [7:0]  binary_in,
                      output wire [9:0] bcd_out
                      );

   //Internal variables
   reg [11:0] reg_bcd_out;
   reg [3:0]  i;

   //Implement the Double Dabble algorithm
   always @(binary_in)
     begin
        reg_bcd_out = 0; //initialize reg_bcd_out to zero.
        for (i = 0; i < 8; i = i+1) //run for 8 iterations
          begin
             reg_bcd_out = {reg_bcd_out[10:0],binary_in[7-i]}; //concatenation

             //if a hex digit of 'reg_bcd_out' is more than 4, add 3 to it.
             if(i < 7 && reg_bcd_out[3:0] > 4)
               reg_bcd_out[3:0] = reg_bcd_out[3:0] + 3;
             if(i < 7 && reg_bcd_out[7:4] > 4)
               reg_bcd_out[7:4] = reg_bcd_out[7:4] + 3;
             if(i < 7 && reg_bcd_out[11:8] > 4)
               reg_bcd_out[11:8] = reg_bcd_out[11:8] + 3;
          end
     end


   //to obtain max 255 we can remove 2 bits :)
   assign bcd_out = reg_bcd_out[9:0];


endmodule

Lab3/verilog/testbench_bcd.v
// Simulation parameters
`timescale 1ns / 1ps



module tb_binary_to_bcd () ;

   localparam  CLKT  = 10; // 100 MHz, 10ns
   localparam  period  = 40; // 20 MHz, 40ns


    // TODO: INIT after (verilog-auto)!!
    // DUT instance parameters

    // Non-auto signals
   reg       Clk       = 1'b0;
   reg       Rst_n     = 1'b1;

    // TODO: Init during declaration (before simulation time 0) to avoid race conditions
    /* DUT Inputs */
   reg [7:0] binary_in = 0; // To I_BINARY_TO_BCD of binary_to_bcd.v

    /* DUT Outputs */
   wire [9:0] bcd_out;        // From I_BINARY_TO_BCD of binary_to_bcd.v


    // System Clock
    always begin
        #(CLKT/2) Clk = ~Clk;
    end

    // TODO: Declare/Connect interfaces
    // axi4_lite_if axil_if_binary_to_bcd (.Clk(Clk), .Rst_n(Rst_n));
    // ...

    // TODO: Ensure SV interfaces connections
    // DUT Instantiation
   binary_to_bcd I_BINARY_TO_BCD (
                                  // Outputs
                                  .bcd_out   (bcd_out),
                                  // Inputs
                                  .binary_in (binary_in)
                                  );


    // TODO: Tasks/functions
    // ...

    // TODO: TB Objects
    // axi4_lite_bfm bfm;

    // TODO: Stimuli
   initial begin
      $dumpfile("test.vcd");
      $dumpvars(0,tb_binary_to_bcd);

      #period;

      binary_in <= 8'b1111_1001;

      #period;



      $display("@%0d: BCD TEST PASSED", $time);
      //$finish;
   end

endmodule

Lab3/verilog/ALU_ctrl.v
module ALU_ctrl (
                 input        clk,
                 input        rst_n,
                 input        enter,
                 input        sign,
                 output wire [3:0] func,
                 output wire [1:0] reg_ctrl
                 );

    reg [3:0] state, next_state;
    reg [1:0] i_reg, next_i_reg;

   always @(posedge clk) begin
      if(~rst_n) begin
         state <= 0;
         i_reg <= 0;
      end else begin
         state <= next_state;
         i_reg <= next_i_reg;
      end
   end

   always @(posedge enter or posedge sign) begin
      next_state = state;
      next_i_reg = i_reg;

      if (enter) begin

         case (state)
           4'b0000: begin
              next_state = 4'b0001;
              next_i_reg = 2'b01;
           end
           4'b0001: begin
              next_state = 4'b0010;
              next_i_reg = 2'b10;
           end
           4'b0010: next_state = 4'b0011;
           4'b0011: next_state = 4'b0100;
           4'b0100: next_state = 4'b0010;
           4'b1010: next_state = 4'b1011;
           4'b1011: next_state = 4'b1100;
           4'b1100: next_state = 4'b1010;
           default: next_state = 4'b0000;
         endcase

      end else if (sign) begin

         case (state)
           4'b0000: next_state = 4'b0000;
           4'b0001: next_state = 4'b0001;
           4'b0010: next_state = 4'b1010;
           4'b0011: next_state = 4'b1011;
           4'b0100: next_state = 4'b1100;
           4'b1010: next_state = 4'b0010;
           4'b1011: next_state = 4'b0011;
           4'b1100: next_state = 4'b0100;
           default: next_state = 4'b0000;
         endcase

      end
   end

    assign func = state;
    assign reg_ctrl = i_reg;

endmodule

Lab3/verilog/testbench_ALU_ctrl.v
// Simulation parameters
`timescale 1ns / 1ps

module tb_ALU_ctrl () ;


   localparam  CLKT  = 10; // 100 MHz, 10ns
   localparam  period  = 40; // 20 MHz, 40ns

   // DUT instance parameters

   // Non-auto signals
   reg         clk   = 1'b0;
   reg         rst_n = 1'b1;

   // TODO: Init during declaration (before simulation time 0) to avoid race conditions
   /* DUT Inputs */
   reg         enter = 0; // To I_ALU_CTRL of ALU_ctrl.v
   reg         sign  = 0; // To I_ALU_CTRL of ALU_ctrl.v

   /* DUT Outputs */
   wire [3:0]   func;       // From I_ALU_CTRL of ALU_ctrl.v
   wire [1:0]   reg_ctrl;   // From I_ALU_CTRL of ALU_ctrl.v


   // System Clock
   always begin
      #(CLKT/2) clk = ~clk;
   end

   // DUT Instantiation
   ALU_ctrl I_ALU_CTRL (
                        // Inputs
                        .clk      (clk),
                        .rst_n    (rst_n),
                        .enter    (enter),
                        .sign     (sign),
                        // Outputs
                        .func     (func),
                        .reg_ctrl (reg_ctrl)
                        );


   initial begin
      $dumpfile("test.vcd");
      $dumpvars(0,tb_ALU_ctrl);

      // *************************
      // User test data pattern
      // *************************

      rst_n <= 0;
      #period;
      rst_n <= 1;
      #1;
      enter <= 1;
      #period;
      enter <= 0;
      #period;
      enter <= 1;
      #period;
      enter <= 0;
      #period;
      enter <= 1;
      #period;
      enter <= 0;
      #period;
      sign <= 1;
      #period;
      sign <= 0;
      #period;
      enter <= 1;
      #period;
      enter <= 0;
      #period;
      enter <= 1;
      #period;
      enter <= 0;
      #period;
      enter <= 1;
      #period;
      enter <= 0;
      #period;




      $display("@%0d: TEST PASSED", $time);
      $finish;
   end

endmodule

Lab3/verilog/ALU.v
module ALU (
            input [7:0]  A,
            input [7:0]  B,
            input [3:0]  FN,
            output [7:0] result,
            output       overflow,
            output       sign
            );


   reg [7:0] ALU_Result;
   wire [8:0] tmp;
   reg        pn;

// mod 3 missing
   always @(*)
     begin
        case(FN)
          4'b0000: // A
            ALU_Result = A;
          4'b0001: // B
            ALU_Result = B;
          4'b0010: // Unsigned A + B
            ALU_Result = A + B;
          4'b0011: // Unsigned A - B
            ALU_Result = A - B;
          4'b0100: // Unsigned A mod 3
            ALU_Result = A % 3;
          // maybe the sign output is just to say if positive or negative for the signed case
          4'b1010: // Signed A + B
            ALU_Result = $signed(A) + $signed(B);
          4'b1011: // Signed A - B
            ALU_Result = $signed(A) - $signed(B);
          4'b1100: // Signed A mod 3
            ALU_Result = $signed(A) % 3;
          default: ALU_Result = A + B ;
        endcase // case (FN)

        // $signed might not be needed
        if ((FN == 4'b1010 || FN == 4'b1011 || FN == 4'b1100) && $signed(ALU_Result) < 0) begin
           pn <= 1;
        end else begin
           pn <= 0;
        end
     end

   assign result = ALU_Result;
   assign tmp = {1'b0,A} + {1'b0,B};
   assign overflow = tmp[8]; // Carryout flag
   assign sign = pn;




endmodule

Lab3/verilog/testbench_ALU.v
// Simulation parameters
`timescale 1ns / 1ps


module tb_ALU () ;


   localparam  CLKT  = 10; // 100 MHz, 10ns
   localparam  period  = 40; // 20 MHz, 40ns

   // DUT instance parameters

   // Non-auto signals
   reg         clk   = 1'b0;

   // TODO: Init during declaration (before simulation time 0) to avoid race conditions
   /* DUT Inputs */
   reg [7:0]   A     = 0; // To I_ALU of ALU.v
   reg [7:0]   B     = 0; // To I_ALU of ALU.v
   reg [3:0]   FN    = 0; // To I_ALU of ALU.v

   /* DUT Outputs */
   wire         overflow;   // From I_ALU of ALU.v
   wire [7:0]   result;     // From I_ALU of ALU.v
   wire         sign;       // From I_ALU of ALU.v

   // System Clock
   always begin
      #(CLKT/2) clk = ~clk;
   end

   // DUT Instantiation
   ALU I_ALU (
              // Inputs
              .A        (A),
              .B        (B),
              .FN       (FN),
              // Outputs
              .result   (result),
              .overflow (overflow),
              .sign     (sign)
              );


   initial begin
      $dumpfile("test.vcd");
      $dumpvars(0,tb_ALU);

      //0100 unsigned mod 3
      //1100 signed mod 3


      // *************************
      // User test data pattern
      // *************************
      A <= 8'b00000101; //5
      B <= 8'b00000011; //3
      FN <= 4'b0000;
      #period;
      A <= 8'b00001001; //9
      B <= 8'b00000011; //3
      FN <= 4'b0001;
      #period;
      A <= 8'b00010001; //17
      B <= 8'b10010001; //145
      FN <= 4'b0010;
      #period;
      A <= 8'b10010001; //145
      B <= 8'b01111100; //124
      FN <= 4'b0011;
      #period;
      A <= 8'b10010100; //148
      B <= 8'b11111001; //249
      FN <= 4'b1010;
      #period;
      A <= 8'b1111_1110; //213
      B <= 8'b0000_0111; //105
      FN <= 4'b1011;
      #period;
      A <= 8'b00100011; //35
      B <= 8'b01100011; //35
      FN <= 4'b0010;
      #period;
      A <= 8'b0000_0010; //2
      B <= 8'b01101000; //104
      FN <= 4'b0100;
      #period;
      A <= 8'b0000_0011; //3
      B <= 8'b00101101; //45
      FN <= 4'b0100;
      #period;
      A <= 8'b01010101; //85
      B <= 8'b00100100; //36
      FN <= 4'b1100;
      #period;
      A <= 8'b00000000; // Invalid input command
      B <= 8'b00000000; // Invalid input command
      FN <= 4'b1111;    // Invalid input command
      #period;

      // The following operations are performed
      // Pass A
      // Pass B
      // Pass A
      // Pass B
      // Pass unsigned A + B
      // Pass unsigned A - B
      // Pass unsigned A - B
      // Pass unsigned A + B
      // Pass unsigned A - B
      // Pass unsigned max(A,
      // Pass signed A + B
      // Pass signed A - B
      // Pass signed max(A, B)
      // Invalid input command

      $display("@%0d: ALU TEST PASSED", $time);
      $finish;
   end // initial begin

endmodule

Lab3/verilog/test.vcd
$date
	Tue Oct  3 12:14:29 2023
$end
$version
	Icarus Verilog
$end
$timescale
	1ps
$end
$scope module tb_ALU $end
$var wire 1 ! sign $end
$var wire 8 " result [7:0] $end
$var wire 1 # overflow $end
$var parameter 32 $ CLKT $end
$var parameter 32 % period $end
$var reg 8 & A [7:0] $end
$var reg 8 ' B [7:0] $end
$var reg 4 ( FN [3:0] $end
$var reg 1 ) clk $end
$scope module I_ALU $end
$var wire 8 * A [7:0] $end
$var wire 8 + B [7:0] $end
$var wire 4 , FN [3:0] $end
$var wire 8 - result [7:0] $end
$var wire 1 ! sign $end
$var wire 9 . tmp [8:0] $end
$var wire 1 # overflow $end
$var reg 8 / ALU_Result [7:0] $end
$var reg 1 0 pn $end
$upscope $end
$upscope $end
$scope module tb_ALU_ctrl $end
$var wire 2 1 reg_ctrl [1:0] $end
$var wire 4 2 func [3:0] $end
$var parameter 32 3 CLKT $end
$var parameter 32 4 period $end
$var reg 1 5 clk $end
$var reg 1 6 enter $end
$var reg 1 7 rst_n $end
$var reg 1 8 sign $end
$scope module I_ALU_CTRL $end
$var wire 1 5 clk $end
$var wire 1 6 enter $end
$var wire 4 9 func [3:0] $end
$var wire 2 : reg_ctrl [1:0] $end
$var wire 1 7 rst_n $end
$var wire 1 8 sign $end
$var reg 2 ; i_reg [1:0] $end
$var reg 2 < next_i_reg [1:0] $end
$var reg 4 = next_state [3:0] $end
$var reg 4 > state [3:0] $end
$upscope $end
$upscope $end
$scope module tb_binary_to_bcd $end
$var wire 10 ? bcd_out [9:0] $end
$var parameter 32 @ CLKT $end
$var parameter 32 A period $end
$var reg 1 B Clk $end
$var reg 1 C Rst_n $end
$var reg 8 D binary_in [7:0] $end
$scope module I_BINARY_TO_BCD $end
$var wire 8 E binary_in [7:0] $end
$var wire 10 F bcd_out [9:0] $end
$var reg 4 G i [3:0] $end
$var reg 12 H reg_bcd_out [11:0] $end
$upscope $end
$upscope $end
$enddefinitions $end
$comment Show the parameter values. $end
$dumpall
b101000 A
b1010 @
b101000 4
b1010 3
b101000 %
b1010 $
$end
#0
$dumpvars
b0 H
b1000 G
b0 F
b0 E
b0 D
1C
0B
b0 ?
bx >
bx =
bx <
bx ;
bx :
bx 9
08
07
06
05
bx 2
bx 1
00
b101 /
b1000 .
b101 -
b0 ,
b11 +
b101 *
0)
b0 (
b11 '
b101 &
0#
b101 "
0!
$end
#5000
b0 1
b0 :
b0 ;
b0 2
b0 9
b0 >
1B
15
1)
#10000
0B
05
0)
#15000
1B
15
1)
#20000
0B
05
0)
#25000
1B
15
1)
#30000
0B
05
0)
#35000
1B
15
1)
#40000
b1001001001 ?
b1001001001 F
b1001001001 H
b1000 G
b11 "
b11 -
b11 /
b11111001 D
b11111001 E
17
b1 (
b1 ,
b1100 .
b1001 &
b1001 *
0B
05
0)
#41000
b1 <
b1 =
16
#45000
b1 1
b1 :
b1 ;
b1 2
b1 9
b1 >
1B
15
1)
#50000
0B
05
0)
#55000
1B
15
1)
#60000
0B
05
0)
#65000
1B
15
1)
#70000
0B
05
0)
#75000
1B
15
1)
#80000
b10100010 "
b10100010 -
b10100010 /
b10 (
b10 ,
b10010001 '
b10010001 +
b10100010 .
b10001 &
b10001 *
0B
05
0)
#81000
06
#85000
1B
15
1)
#90000
0B
05
0)
#95000
1B
15
1)
#100000
0B
05
0)
#105000
1B
15
1)
#110000
0B
05
0)
#115000
1B
15
1)
#120000
b10101 "
b10101 -
b10101 /
1#
b11 (
b11 ,
b1111100 '
b1111100 +
b100001101 .
b10010001 &
b10010001 *
0B
05
0)
#121000
b10 <
b10 =
16
#125000
b10 1
b10 :
b10 ;
b10 2
b10 9
b10 >
1B
15
1)
#130000
0B
05
0)
#135000
1B
15
1)
#140000
0B
05
0)
#145000
1B
15
1)
#150000
0B
05
0)
#155000
1B
15
1)
#160000
1!
10
b10001101 "
b10001101 -
b10001101 /
b1010 (
b1010 ,
b11111001 '
b11111001 +
b110001101 .
b10010100 &
b10010100 *
0B
05
0)
#161000
06
#165000
1B
15
1)
#170000
0B
05
0)
#175000
1B
15
1)
#180000
0B
05
0)
#185000
1B
15
1)
#190000
0B
05
0)
#195000
1B
15
1)
#200000
0!
00
b1101100 "
b1101100 -
b1101100 /
b1011 (
b1011 ,
b1101001 '
b1101001 +
b100111110 .
b11010101 &
b11010101 *
0B
05
0)
#201000
b11 =
16
#205000
b11 2
b11 9
b11 >
1B
15
1)
#210000
0B
05
0)
#215000
1B
15
1)
#220000
0B
05
0)
#225000
1B
15
1)
#230000
0B
05
0)
#235000
1B
15
1)
#240000
b10000110 "
b10000110 -
b10000110 /
0#
b10 (
b10 ,
b1100011 '
b1100011 +
b10000110 .
b100011 &
b100011 *
0B
05
0)
#241000
06
#245000
1B
15
1)
#250000
0B
05
0)
#255000
1B
15
1)
#260000
0B
05
0)
#265000
1B
15
1)
#270000
0B
05
0)
#275000
1B
15
1)
#280000
b10 "
b10 -
b10 /
1#
b100 (
b100 ,
b1101000 '
b1101000 +
b101011010 .
b11110010 &
b11110010 *
0B
05
0)
#281000
b1011 =
18
#285000
b1011 2
b1011 9
b1011 >
1B
15
1)
#290000
0B
05
0)
#295000
1B
15
1)
#300000
0B
05
0)
#305000
1B
15
1)
#310000
0B
05
0)
#315000
1B
15
1)
#320000
b1 "
b1 -
b1 /
0#
b101101 '
b101101 +
b1011110 .
b110001 &
b110001 *
0B
05
0)
#321000
08
#325000
1B
15
1)
#330000
0B
05
0)
#335000
1B
15
1)
#340000
0B
05
0)
#345000
1B
15
1)
#350000
0B
05
0)
#355000
1B
15
1)
#360000
b100100 '
b100100 +
b1111001 .
b1010101 &
b1010101 *
0B
05
0)
#361000
b1100 =
16
#365000
b1100 2
b1100 9
b1100 >
1B
15
1)
#370000
0B
05
0)
#375000
1B
15
1)
#380000
0B
05
0)
#385000
1B
15
1)
#390000
0B
05
0)
#395000
1B
15
1)
#400000
b0 "
b0 -
b0 /
b1111 (
b1111 ,
b0 '
b0 +
b0 .
b0 &
b0 *
0B
05
0)
#401000
06
