vga_example/vga.v
`timescale 1ns / 1ps


module vga(
    input clock,
    input reset,
    output io_horizontal_sync,
    output io_vertical_sync,
    output reg [11:0] io_rgb_color
);

    localparam COLOR_BLUE = 12'hf00;
    localparam COLOR_GREEN = 12'h0f0;
    localparam COLOR_RED = 12'h00f;
    localparam COLOR_WHITE = 12'hfff;

    localparam NUM_HORIZONTAL_VISIBLE_PIXELS = 640;
    localparam NUM_HORIZONTAL_FRONT_PORCH_PIXELS = 16;
    localparam NUM_HORIZONTAL_SYNC_PIXELS = 96;
    localparam NUM_HORIZONTAL_BACK_PORCH_PIXELS = 48;
    localparam NUM_HORIZONTAL_ALL_PIXELS =
        NUM_HORIZONTAL_VISIBLE_PIXELS + NUM_HORIZONTAL_FRONT_PORCH_PIXELS +
        NUM_HORIZONTAL_SYNC_PIXELS + NUM_HORIZONTAL_BACK_PORCH_PIXELS;

    localparam NUM_VERTICAL_VISIBLE_PIXELS = 480;
    localparam NUM_VERTICAL_FRONT_PORCH_PIXELS = 10;
    localparam NUM_VERTICAL_SYNC_PIXELS = 2;
    localparam NUM_VERTICAL_BACK_PORCH_PIXELS = 29;
    localparam NUM_VERTICAL_ALL_PIXELS =
        NUM_VERTICAL_VISIBLE_PIXELS + NUM_VERTICAL_FRONT_PORCH_PIXELS +
        NUM_VERTICAL_SYNC_PIXELS + NUM_VERTICAL_BACK_PORCH_PIXELS;

    reg [10:0] horizontal_counter_reg, horizontal_counter_next;
    reg [10:0] vertical_counter_reg, vertical_counter_next;

    wire [1:0] counter_25mhz_next;
    reg [1:0] counter_25mhz_reg;
    wire clock_25mhz = counter_25mhz_reg == 3;

    reg h_sync_reg, h_sync_next;
    reg v_sync_reg, v_sync_next;

    reg is_displaying_pixels;


    always @ (posedge clock)
    begin
        if (reset == 1) begin
            horizontal_counter_reg <= 0;
            vertical_counter_reg <= 0;
            h_sync_reg <= 1;
            v_sync_reg <= 1;
            counter_25mhz_reg <= 0;
        end
        else begin
            horizontal_counter_reg <= horizontal_counter_next;
            vertical_counter_reg <= vertical_counter_next;
            h_sync_reg <= h_sync_next;
            v_sync_reg <= v_sync_next;
            counter_25mhz_reg <= counter_25mhz_next;
        end
    end


    assign counter_25mhz_next = counter_25mhz_reg + 1;


    always @ (*)
    begin
        horizontal_counter_next = horizontal_counter_reg;
        vertical_counter_next = vertical_counter_reg;

        if (clock_25mhz) begin
            if (horizontal_counter_reg == NUM_HORIZONTAL_ALL_PIXELS-1) begin
                horizontal_counter_next = 0;
            end
            else begin
                horizontal_counter_next = horizontal_counter_reg + 1;
            end

            if (horizontal_counter_reg == NUM_HORIZONTAL_ALL_PIXELS-1) begin
                vertical_counter_next = vertical_counter_reg + 1;
                if (vertical_counter_reg == NUM_VERTICAL_ALL_PIXELS-1) begin
                    vertical_counter_next = 0;
                end
            end
        end
    end


    always @ (*)
    begin
        h_sync_next = h_sync_reg;
        v_sync_next = v_sync_reg;

        if (clock_25mhz) begin
            if (
                horizontal_counter_reg >= NUM_HORIZONTAL_VISIBLE_PIXELS + NUM_HORIZONTAL_FRONT_PORCH_PIXELS &&
                horizontal_counter_reg < NUM_HORIZONTAL_VISIBLE_PIXELS + NUM_HORIZONTAL_FRONT_PORCH_PIXELS + NUM_HORIZONTAL_SYNC_PIXELS
            ) begin
                h_sync_next = 0;
            end
            else begin
                h_sync_next = 1;
            end

            if (
                vertical_counter_reg >= NUM_VERTICAL_VISIBLE_PIXELS + NUM_VERTICAL_FRONT_PORCH_PIXELS &&
                vertical_counter_reg < NUM_VERTICAL_VISIBLE_PIXELS + NUM_VERTICAL_FRONT_PORCH_PIXELS + NUM_VERTICAL_SYNC_PIXELS
            ) begin
                v_sync_next = 0;
            end
            else begin
                v_sync_next = 1;
            end
        end
    end


    always @ (*)
    begin
        is_displaying_pixels = 0;
        if (horizontal_counter_reg < NUM_HORIZONTAL_VISIBLE_PIXELS && vertical_counter_reg < NUM_VERTICAL_VISIBLE_PIXELS) begin
            is_displaying_pixels <= 1;
        end
    end


    // Draw pixels on the screen
    always @ (*)
    begin
        io_rgb_color = 0;
        if (is_displaying_pixels) begin
            // Paint the middle pixel in the 3rd row white
            if (vertical_counter_reg == 3-1 && horizontal_counter_reg == NUM_HORIZONTAL_VISIBLE_PIXELS/2) begin
                io_rgb_color = COLOR_WHITE;
            end

            // Draw red, green, and blue squares in the middle of the screen
            if (vertical_counter_reg >= NUM_VERTICAL_VISIBLE_PIXELS/3 && vertical_counter_reg < 2*NUM_VERTICAL_VISIBLE_PIXELS/3) begin
                if (horizontal_counter_reg < NUM_HORIZONTAL_VISIBLE_PIXELS/3) begin
                    io_rgb_color = COLOR_RED;
                end
                else if (horizontal_counter_reg < 2*NUM_HORIZONTAL_VISIBLE_PIXELS/3) begin
                    io_rgb_color = COLOR_BLUE;
                end
                else begin
                    io_rgb_color = COLOR_GREEN;
                end
            end
        end
    end

    assign io_horizontal_sync = h_sync_reg;
    assign io_vertical_sync = v_sync_reg;

endmodule

vga_example/vga_tb.v
// Simulation parameters
`timescale 1ns / 1ps

module tb_vga () ;

    // Simulation parameters

   localparam   CLKT  = 10; // 100 MHz

    // TODO: INIT after (verilog-auto)!!
    // DUT instance parameters

    // Non-auto signals
   reg        clk   = 1'b0;
   reg        rst_n = 1'b1;

    // TODO: Init during declaration (before simulation time 0) to avoid race conditions
    /* DUT Inputs */
  // reg        clk = 0;         // To I_VGA of vga.v
  // reg        rst_n = 0;         // To I_VGA of vga.v

    /* DUT Outputs */
   wire        io_horizontal_sync; // From I_VGA of vga.v
   wire [11:0] io_rgb_color;       // From I_VGA of vga.v
   wire        io_vertical_sync;   // From I_VGA of vga.v


    // System Clk
    always begin
        #(CLKT/2) clk = ~clk;
    end

    // TODO: Declare/Connect interfaces
    // axi4_lite_if axil_if_vga (.clk(clk), .rst_n(rst_n));
    // ...

    // TODO: Ensure SV interfaces connections
    // DUT Instantiation
   vga I_VGA (
              // Outputs
              .io_horizontal_sync (io_horizontal_sync),
              .io_vertical_sync   (io_vertical_sync),
              .io_rgb_color       (io_rgb_color),
              // Inputs
              .clock              (clk),
              .reset              (rst_n)
              );


    // TODO: Tasks/functions
    // ...

    // TODO: TB Objects
    // axi4_lite_bfm bfm;

    // TODO: Stimuli
    initial begin
      $dumpfile("test.vcd");
      $dumpvars(0,tb_vga);
        // bfm = new(axil_if_vga);
        //
        #10 rst_n = 0;


       #100;


       $display("@%0d: TEST PASSED", $time);
        $finish;
    end

endmodule

vga_example/test.vcd
$date
	Mon Oct  9 17:17:39 2023
$end
$version
	Icarus Verilog
$end
$timescale
	1ps
$end
$scope module tb_vga $end
$var wire 1 ! io_vertical_sync $end
$var wire 12 " io_rgb_color [11:0] $end
$var wire 1 # io_horizontal_sync $end
$var parameter 32 $ CLKT $end
$var reg 1 % clk $end
$var reg 1 & rst_n $end
$scope module I_VGA $end
$var wire 1 % clock $end
$var wire 1 # io_horizontal_sync $end
$var wire 1 ! io_vertical_sync $end
$var wire 1 & reset $end
$var wire 2 ' counter_25mhz_next [1:0] $end
$var wire 1 ( clock_25mhz $end
$var parameter 12 ) COLOR_BLUE $end
$var parameter 12 * COLOR_GREEN $end
$var parameter 12 + COLOR_RED $end
$var parameter 12 , COLOR_WHITE $end
$var parameter 35 - NUM_HORIZONTAL_ALL_PIXELS $end
$var parameter 32 . NUM_HORIZONTAL_BACK_PORCH_PIXELS $end
$var parameter 32 / NUM_HORIZONTAL_FRONT_PORCH_PIXELS $end
$var parameter 32 0 NUM_HORIZONTAL_SYNC_PIXELS $end
$var parameter 32 1 NUM_HORIZONTAL_VISIBLE_PIXELS $end
$var parameter 35 2 NUM_VERTICAL_ALL_PIXELS $end
$var parameter 32 3 NUM_VERTICAL_BACK_PORCH_PIXELS $end
$var parameter 32 4 NUM_VERTICAL_FRONT_PORCH_PIXELS $end
$var parameter 32 5 NUM_VERTICAL_SYNC_PIXELS $end
$var parameter 32 6 NUM_VERTICAL_VISIBLE_PIXELS $end
$var reg 2 7 counter_25mhz_reg [1:0] $end
$var reg 1 8 h_sync_next $end
$var reg 1 9 h_sync_reg $end
$var reg 11 : horizontal_counter_next [10:0] $end
$var reg 11 ; horizontal_counter_reg [10:0] $end
$var reg 12 < io_rgb_color [11:0] $end
$var reg 1 = is_displaying_pixels $end
$var reg 1 > v_sync_next $end
$var reg 1 ? v_sync_reg $end
$var reg 11 @ vertical_counter_next [10:0] $end
$var reg 11 A vertical_counter_reg [10:0] $end
$upscope $end
$upscope $end
$enddefinitions $end
$comment Show the parameter values. $end
$dumpall
b111100000 6
b10 5
b1010 4
b11101 3
b1000001001 2
b1010000000 1
b1100000 0
b10000 /
b110000 .
b1100100000 -
b111111111111 ,
b1111 +
b11110000 *
b111100000000 )
b1010 $
$end
#0
$dumpvars
bx A
bx @
x?
x>
x=
bx <
bx ;
bx :
x9
x8
bx 7
x(
bx '
1&
0%
x#
bx "
x!
$end
#5000
b0 "
b0 <
1=
1>
18
b0 @
b0 :
0(
b1 '
b0 7
1!
1?
1#
19
b0 A
b0 ;
1%
#10000
0%
0&
#15000
b10 '
b1 7
1%
#20000
0%
#25000
b11 '
b10 7
1%
#30000
0%
#35000
b1 :
1(
b0 '
b11 7
1%
#40000
0%
#45000
1=
0(
b1 '
b0 7
b1 ;
1%
#50000
0%
#55000
b10 '
b1 7
1%
#60000
0%
#65000
b11 '
b10 7
1%
#70000
0%
#75000
b10 :
1(
b0 '
b11 7
1%
#80000
0%
#85000
1=
0(
b1 '
b0 7
b10 ;
1%
#90000
0%
#95000
b10 '
b1 7
1%
#100000
0%
#105000
b11 '
b10 7
1%
#110000
0%
#115000
b11 :
1(
b0 '
b11 7
1%
#120000
0%
#125000
1=
0(
b1 '
b0 7
b11 ;
1%
#130000
0%
#135000
b10 '
b1 7
1%
#140000
0%
#145000
b11 '
b10 7
1%
#150000
0%
#155000
b100 :
1(
b0 '
b11 7
1%
#160000
0%
#165000
1=
0(
b1 '
b0 7
b100 ;
1%
#170000
0%
#175000
b10 '
b1 7
1%
#180000
0%
#185000
b11 '
b10 7
1%
#190000
0%
#195000
b101 :
1(
b0 '
b11 7
1%
#200000
0%
#205000
1=
0(
b1 '
b0 7
b101 ;
1%
#210000
0%
#215000
b10 '
b1 7
1%
#220000
0%
#225000
b11 '
b10 7
1%
#230000
0%
#235000
b110 :
1(
b0 '
b11 7
1%
#240000
0%
#245000
1=
0(
b1 '
b0 7
b110 ;
1%
#250000
0%
#255000
b10 '
b1 7
1%
#260000
0%
#265000
b11 '
b10 7
1%
#270000
0%
#275000
b111 :
1(
b0 '
b11 7
1%
#280000
0%
#285000
1=
0(
b1 '
b0 7
b111 ;
1%
#290000
0%
#295000
b10 '
b1 7
1%
#300000
0%
#305000
b11 '
b10 7
1%
#310000
0%
#315000
b1000 :
1(
b0 '
b11 7
1%
#320000
0%
#325000
1=
0(
b1 '
b0 7
b1000 ;
1%
#330000
0%
#335000
b10 '
b1 7
1%
#340000
0%
#345000
b11 '
b10 7
1%
#350000
0%
#355000
b1001 :
1(
b0 '
b11 7
1%
#360000
0%
#365000
1=
0(
b1 '
b0 7
b1001 ;
1%
#370000
0%
#375000
b10 '
b1 7
1%
#380000
0%
#385000
b11 '
b10 7
1%
#390000
0%
#395000
b1010 :
1(
b0 '
b11 7
1%
#400000
0%
#405000
1=
0(
b1 '
b0 7
b1010 ;
1%
#410000
0%
#415000
b10 '
b1 7
1%
#420000
0%
#425000
b11 '
b10 7
1%
#430000
0%
#435000
b1011 :
1(
b0 '
b11 7
1%
#440000
0%
#445000
1=
0(
b1 '
b0 7
b1011 ;
1%
#450000
0%
#455000
b10 '
b1 7
1%
#460000
0%
#465000
b11 '
b10 7
1%
#470000
0%
#475000
b1100 :
1(
b0 '
b11 7
1%
#480000
0%
#485000
1=
0(
b1 '
b0 7
b1100 ;
1%
#490000
0%
#495000
b10 '
b1 7
1%
#500000
0%
#505000
b11 '
b10 7
1%
#510000
0%
#515000
b1101 :
1(
b0 '
b11 7
1%
#520000
0%
#525000
1=
0(
b1 '
b0 7
b1101 ;
1%
#530000
0%
#535000
b10 '
b1 7
1%
#540000
0%
#545000
b11 '
b10 7
1%
#550000
0%
#555000
b1110 :
1(
b0 '
b11 7
1%
#560000
0%
#565000
1=
0(
b1 '
b0 7
b1110 ;
1%
#570000
0%
#575000
b10 '
b1 7
1%
#580000
0%
#585000
b11 '
b10 7
1%
#590000
0%
#595000
b1111 :
1(
b0 '
b11 7
1%
#600000
0%
#605000
1=
0(
b1 '
b0 7
b1111 ;
1%
#610000
0%
#615000
b10 '
b1 7
1%
#620000
0%
#625000
b11 '
b10 7
1%
#630000
0%
#635000
b10000 :
1(
b0 '
b11 7
1%
#640000
0%
#645000
1=
0(
b1 '
b0 7
b10000 ;
1%
#650000
0%
#655000
b10 '
b1 7
1%
#660000
0%
#665000
b11 '
b10 7
1%
#670000
0%
#675000
b10001 :
1(
b0 '
b11 7
1%
#680000
0%
#685000
1=
0(
b1 '
b0 7
b10001 ;
1%
#690000
0%
#695000
b10 '
b1 7
1%
#700000
0%
#705000
b11 '
b10 7
1%
#710000
0%
#715000
b10010 :
1(
b0 '
b11 7
1%
#720000
0%
#725000
1=
0(
b1 '
b0 7
b10010 ;
1%
#730000
0%
#735000
b10 '
b1 7
1%
#740000
0%
#745000
b11 '
b10 7
1%
#750000
0%
#755000
b10011 :
1(
b0 '
b11 7
1%
#760000
0%
#765000
1=
0(
b1 '
b0 7
b10011 ;
1%
#770000
0%
#775000
b10 '
b1 7
1%
#780000
0%
#785000
b11 '
b10 7
1%
#790000
0%
#795000
b10100 :
1(
b0 '
b11 7
1%
#800000
0%
#805000
1=
0(
b1 '
b0 7
b10100 ;
1%
#810000
0%
#815000
b10 '
b1 7
1%
#820000
0%
#825000
b11 '
b10 7
1%
#830000
0%
#835000
b10101 :
1(
b0 '
b11 7
1%
#840000
0%
#845000
1=
0(
b1 '
b0 7
b10101 ;
1%
#850000
0%
#855000
b10 '
b1 7
1%
#860000
0%
#865000
b11 '
b10 7
1%
#870000
0%
#875000
b10110 :
1(
b0 '
b11 7
1%
#880000
0%
#885000
1=
0(
b1 '
b0 7
b10110 ;
1%
#890000
0%
#895000
b10 '
b1 7
1%
#900000
0%
#905000
b11 '
b10 7
1%
#910000
0%
#915000
b10111 :
1(
b0 '
b11 7
1%
#920000
0%
#925000
1=
0(
b1 '
b0 7
b10111 ;
1%
#930000
0%
#935000
b10 '
b1 7
1%
#940000
0%
#945000
b11 '
b10 7
1%
#950000
0%
#955000
b11000 :
1(
b0 '
b11 7
1%
#960000
0%
#965000
1=
0(
b1 '
b0 7
b11000 ;
1%
#970000
0%
#975000
b10 '
b1 7
1%
#980000
0%
#985000
b11 '
b10 7
1%
#990000
0%
#995000
b11001 :
1(
b0 '
b11 7
1%
#1000000
0%
#1005000
1=
0(
b1 '
b0 7
b11001 ;
1%
#1010000
0%
#1015000
b10 '
b1 7
1%
#1020000
0%
#1025000
b11 '
b10 7
1%
#1030000
0%
#1035000
b11010 :
1(
b0 '
b11 7
1%
#1040000
0%
#1045000
1=
0(
b1 '
b0 7
b11010 ;
1%
#1050000
0%
#1055000
b10 '
b1 7
1%
#1060000
0%
#1065000
b11 '
b10 7
1%
#1070000
0%
#1075000
b11011 :
1(
b0 '
b11 7
1%
#1080000
0%
#1085000
1=
0(
b1 '
b0 7
b11011 ;
1%
#1090000
0%
#1095000
b10 '
b1 7
1%
#1100000
0%
#1105000
b11 '
b10 7
1%
#1110000
0%
#1115000
b11100 :
1(
b0 '
b11 7
1%
#1120000
0%
#1125000
1=
0(
b1 '
b0 7
b11100 ;
1%
#1130000
0%
#1135000
b10 '
b1 7
1%
#1140000
0%
#1145000
b11 '
b10 7
1%
#1150000
0%
#1155000
b11101 :
1(
b0 '
b11 7
1%
#1160000
0%
#1165000
1=
0(
b1 '
b0 7
b11101 ;
1%
#1170000
0%
#1175000
b10 '
b1 7
1%
#1180000
0%
#1185000
b11 '
b10 7
1%
#1190000
0%
#1195000
b11110 :
1(
b0 '
b11 7
1%
#1200000
0%
#1205000
1=
0(
b1 '
b0 7
b11110 ;
1%
#1210000
0%
#1215000
b10 '
b1 7
1%
#1220000
0%
#1225000
b11 '
b10 7
1%
#1230000
0%
#1235000
b11111 :
1(
b0 '
b11 7
1%
#1240000
0%
#1245000
1=
0(
b1 '
b0 7
b11111 ;
1%
#1250000
0%
#1255000
b10 '
b1 7
1%
#1260000
0%
#1265000
b11 '
b10 7
1%
#1270000
0%
#1275000
b100000 :
1(
b0 '
b11 7
1%
#1280000
0%
#1285000
1=
0(
b1 '
b0 7
b100000 ;
1%
#1290000
0%
#1295000
b10 '
b1 7
1%
#1300000
0%
#1305000
b11 '
b10 7
1%
#1310000
0%
#1315000
b100001 :
1(
b0 '
b11 7
1%
#1320000
0%
#1325000
1=
0(
b1 '
b0 7
b100001 ;
1%
#1330000
0%
#1335000
b10 '
b1 7
1%
#1340000
0%
#1345000
b11 '
b10 7
1%
#1350000
0%
#1355000
b100010 :
1(
b0 '
b11 7
1%
#1360000
0%
#1365000
1=
0(
b1 '
b0 7
b100010 ;
1%
#1370000
0%
#1375000
b10 '
b1 7
1%
#1380000
0%
#1385000
b11 '
b10 7
1%
#1390000
0%
#1395000
b100011 :
1(
b0 '
b11 7
1%
#1400000
0%
#1405000
1=
0(
b1 '
b0 7
b100011 ;
1%
#1410000
0%
#1415000
b10 '
b1 7
1%
#1420000
0%
#1425000
b11 '
b10 7
1%
#1430000
0%
#1435000
b100100 :
1(
b0 '
b11 7
1%
#1440000
0%
#1445000
1=
0(
b1 '
b0 7
b100100 ;
1%
#1450000
0%
#1455000
b10 '
b1 7
1%
#1460000
0%
#1465000
b11 '
b10 7
1%
#1470000
0%
#1475000
b100101 :
1(
b0 '
b11 7
1%
#1480000
0%
#1485000
1=
0(
b1 '
b0 7
b100101 ;
1%
#1490000
0%
#1495000
b10 '
b1 7
1%
#1500000
0%
#1505000
b11 '
b10 7
1%
#1510000
0%
#1515000
b100110 :
1(
b0 '
b11 7
1%
#1520000
0%
#1525000
1=
0(
b1 '
b0 7
b100110 ;
1%
#1530000
0%
#1535000
b10 '
b1 7
1%
#1540000
0%
#1545000
b11 '
b10 7
1%
#1550000
0%
#1555000
b100111 :
1(
b0 '
b11 7
1%
#1560000
0%
#1565000
1=
0(
b1 '
b0 7
b100111 ;
1%
#1570000
0%
#1575000
b10 '
b1 7
1%
#1580000
0%
#1585000
b11 '
b10 7
1%
#1590000
0%
#1595000
b101000 :
1(
b0 '
b11 7
1%
#1600000
0%
#1605000
1=
0(
b1 '
b0 7
b101000 ;
1%
#1610000
0%
#1615000
b10 '
b1 7
1%
#1620000
0%
#1625000
b11 '
b10 7
1%
#1630000
0%
#1635000
b101001 :
1(
b0 '
b11 7
1%
#1640000
0%
#1645000
1=
0(
b1 '
b0 7
b101001 ;
1%
#1650000
0%
#1655000
b10 '
b1 7
1%
#1660000
0%
#1665000
b11 '
b10 7
1%
#1670000
0%
#1675000
b101010 :
1(
b0 '
b11 7
1%
#1680000
0%
#1685000
1=
0(
b1 '
b0 7
b101010 ;
1%
#1690000
0%
#1695000
b10 '
b1 7
1%
#1700000
0%
#1705000
b11 '
b10 7
1%
#1710000
0%
#1715000
b101011 :
1(
b0 '
b11 7
1%
#1720000
0%
#1725000
1=
0(
b1 '
b0 7
b101011 ;
1%
#1730000
0%
#1735000
b10 '
b1 7
1%
#1740000
0%
#1745000
b11 '
b10 7
1%
#1750000
0%
#1755000
b101100 :
1(
b0 '
b11 7
1%
#1760000
0%
#1765000
1=
0(
b1 '
b0 7
b101100 ;
1%
#1770000
0%
#1775000
b10 '
b1 7
1%
#1780000
0%
#1785000
b11 '
b10 7
1%
#1790000
0%
#1795000
b101101 :
1(
b0 '
b11 7
1%
#1800000
0%
#1805000
1=
0(
b1 '
b0 7
b101101 ;
1%
#1810000
0%
#1815000
b10 '
b1 7
1%
#1820000
0%
#1825000
b11 '
b10 7
1%
#1830000
0%
#1835000
b101110 :
1(
b0 '
b11 7
1%
#1840000
0%
#1845000
1=
0(
b1 '
b0 7
b101110 ;
1%
#1850000
0%
#1855000
b10 '
b1 7
1%
#1860000
0%
#1865000
b11 '
b10 7
1%
#1870000
0%
#1875000
b101111 :
1(
b0 '
b11 7
1%
#1880000
0%
#1885000
1=
0(
b1 '
b0 7
b101111 ;
1%
#1890000
0%
#1895000
b10 '
b1 7
1%
#1900000
0%
#1905000
b11 '
b10 7
1%
#1910000
0%
#1915000
b110000 :
1(
b0 '
b11 7
1%
#1920000
0%
#1925000
1=
0(
b1 '
b0 7
b110000 ;
1%
#1930000
0%
#1935000
b10 '
b1 7
1%
#1940000
0%
#1945000
b11 '
b10 7
1%
#1950000
0%
#1955000
b110001 :
1(
b0 '
b11 7
1%
#1960000
0%
#1965000
1=
0(
b1 '
b0 7
b110001 ;
1%
#1970000
0%
#1975000
b10 '
b1 7
1%
#1980000
0%
#1985000
b11 '
b10 7
1%
#1990000
0%
#1995000
b110010 :
1(
b0 '
b11 7
1%
#2000000
0%
#2005000
1=
0(
b1 '
b0 7
b110010 ;
1%
#2010000
0%
#2015000
b10 '
b1 7
1%
#2020000
0%
#2025000
b11 '
b10 7
1%
#2030000
0%
#2035000
b110011 :
1(
b0 '
b11 7
1%
#2040000
0%
#2045000
1=
0(
b1 '
b0 7
b110011 ;
1%
#2050000
0%
#2055000
b10 '
b1 7
1%
#2060000
0%
#2065000
b11 '
b10 7
1%
#2070000
0%
#2075000
b110100 :
1(
b0 '
b11 7
1%
#2080000
0%
#2085000
1=
0(
b1 '
b0 7
b110100 ;
1%
#2090000
0%
#2095000
b10 '
b1 7
1%
#2100000
0%
#2105000
b11 '
b10 7
1%
#2110000
0%
#2115000
b110101 :
1(
b0 '
b11 7
1%
#2120000
0%
#2125000
1=
0(
b1 '
b0 7
b110101 ;
1%
#2130000
0%
#2135000
b10 '
b1 7
1%
#2140000
0%
#2145000
b11 '
b10 7
1%
#2150000
0%
#2155000
b110110 :
1(
b0 '
b11 7
1%
#2160000
0%
#2165000
1=
0(
b1 '
b0 7
b110110 ;
1%
#2170000
0%
#2175000
b10 '
b1 7
1%
#2180000
0%
#2185000
b11 '
b10 7
1%
#2190000
0%
#2195000
b110111 :
1(
b0 '
b11 7
1%
#2200000
0%
#2205000
1=
0(
b1 '
b0 7
b110111 ;
1%
#2210000
0%
#2215000
b10 '
b1 7
1%
#2220000
0%
#2225000
b11 '
b10 7
1%
#2230000
0%
#2235000
b111000 :
1(
b0 '
b11 7
1%
#2240000
0%
#2245000
1=
0(
b1 '
b0 7
b111000 ;
1%
#2250000
0%
#2255000
b10 '
b1 7
1%
#2260000
0%
#2265000
b11 '
b10 7
1%
#2270000
0%
#2275000
b111001 :
1(
b0 '
b11 7
1%
#2280000
0%
#2285000
1=
0(
b1 '
b0 7
b111001 ;
1%
#2290000
0%
#2295000
b10 '
b1 7
1%
#2300000
0%
#2305000
b11 '
b10 7
1%
#2310000
0%
#2315000
b111010 :
1(
b0 '
b11 7
1%
#2320000
0%
#2325000
1=
0(
b1 '
b0 7
b111010 ;
1%
#2330000
0%
#2335000
b10 '
b1 7
1%
#2340000
0%
#2345000
b11 '
b10 7
1%
#2350000
0%
#2355000
b111011 :
1(
b0 '
b11 7
1%
#2360000
0%
#2365000
1=
0(
b1 '
b0 7
b111011 ;
1%
#2370000
0%
#2375000
b10 '
b1 7
1%
#2380000
0%
#2385000
b11 '
b10 7
1%
#2390000
0%
#2395000
b111100 :
1(
b0 '
b11 7
1%
#2400000
0%
#2405000
1=
0(
b1 '
b0 7
b111100 ;
1%
#2410000
0%
#2415000
b10 '
b1 7
1%
#2420000
0%
#2425000
b11 '
b10 7
1%
#2430000
0%
#2435000
b111101 :
1(
b0 '
b11 7
1%
#2440000
0%
#2445000
1=
0(
b1 '
b0 7
b111101 ;
1%
#2450000
0%
#2455000
b10 '
b1 7
1%
#2460000
0%
#2465000
b11 '
b10 7
1%
#2470000
0%
#2475000
b111110 :
1(
b0 '
b11 7
1%
#2480000
0%
#2485000
1=
0(
b1 '
b0 7
b111110 ;
1%
#2490000
0%
#2495000
b10 '
b1 7
1%
#2500000
0%
#2505000
b11 '
b10 7
1%
#2510000
0%
#2515000
b111111 :
1(
b0 '
b11 7
1%
#2520000
0%
#2525000
1=
0(
b1 '
b0 7
b111111 ;
1%
#2530000
0%
#2535000
b10 '
b1 7
1%
#2540000
0%
#2545000
b11 '
b10 7
1%
#2550000
0%
#2555000
b1000000 :
1(
b0 '
b11 7
1%
#2560000
0%
#2565000
1=
0(
b1 '
b0 7
b1000000 ;
1%
#2570000
0%
#2575000
b10 '
b1 7
1%
#2580000
0%
#2585000
b11 '
b10 7
1%
#2590000
0%
#2595000
b1000001 :
1(
b0 '
b11 7
1%
#2600000
0%
#2605000
1=
0(
b1 '
b0 7
b1000001 ;
1%
#2610000
0%
#2615000
b10 '
b1 7
1%
#2620000
0%
#2625000
b11 '
b10 7
1%
#2630000
0%
#2635000
b1000010 :
1(
b0 '
b11 7
1%
#2640000
0%
#2645000
1=
0(
b1 '
b0 7
b1000010 ;
1%
#2650000
0%
#2655000
b10 '
b1 7
1%
#2660000
0%
#2665000
b11 '
b10 7
1%
#2670000
0%
#2675000
b1000011 :
1(
b0 '
b11 7
1%
#2680000
0%
#2685000
1=
0(
b1 '
b0 7
b1000011 ;
1%
#2690000
0%
#2695000
b10 '
b1 7
1%
#2700000
0%
#2705000
b11 '
b10 7
1%
#2710000
0%
#2715000
b1000100 :
1(
b0 '
b11 7
1%
#2720000
0%
#2725000
1=
0(
b1 '
b0 7
b1000100 ;
1%
#2730000
0%
#2735000
b10 '
b1 7
1%
#2740000
0%
#2745000
b11 '
b10 7
1%
#2750000
0%
#2755000
b1000101 :
1(
b0 '
b11 7
1%
#2760000
0%
#2765000
1=
0(
b1 '
b0 7
b1000101 ;
1%
#2770000
0%
#2775000
b10 '
b1 7
1%
#2780000
0%
#2785000
b11 '
b10 7
1%
#2790000
0%
#2795000
b1000110 :
1(
b0 '
b11 7
1%
#2800000
0%
#2805000
1=
0(
b1 '
b0 7
b1000110 ;
1%
#2810000
0%
#2815000
b10 '
b1 7
1%
#2820000
0%
#2825000
b11 '
b10 7
1%
#2830000
0%
#2835000
b1000111 :
1(
b0 '
b11 7
1%
#2840000
0%
#2845000
1=
0(
b1 '
b0 7
b1000111 ;
1%
#2850000
0%
#2855000
b10 '
b1 7
1%
#2860000
0%
#2865000
b11 '
b10 7
1%
#2870000
0%
#2875000
b1001000 :
1(
b0 '
b11 7
1%
#2880000
0%
#2885000
1=
0(
b1 '
b0 7
b1001000 ;
1%
#2890000
0%
#2895000
b10 '
b1 7
1%
#2900000
0%
#2905000
b11 '
b10 7
1%
#2910000
0%
#2915000
b1001001 :
1(
b0 '
b11 7
1%
#2920000
0%
#2925000
1=
0(
b1 '
b0 7
b1001001 ;
1%
#2930000
0%
#2935000
b10 '
b1 7
1%
#2940000
0%
#2945000
b11 '
b10 7
1%
#2950000
0%
#2955000
b1001010 :
1(
b0 '
b11 7
1%
#2960000
0%
#2965000
1=
0(
b1 '
b0 7
b1001010 ;
1%
#2970000
0%
#2975000
b10 '
b1 7
1%
#2980000
0%
#2985000
b11 '
b10 7
1%
#2990000
0%
#2995000
b1001011 :
1(
b0 '
b11 7
1%
#3000000
0%
#3005000
1=
0(
b1 '
b0 7
b1001011 ;
1%
#3010000
0%
#3015000
b10 '
b1 7
1%
#3020000
0%
#3025000
b11 '
b10 7
1%
#3030000
0%
#3035000
b1001100 :
1(
b0 '
b11 7
1%
#3040000
0%
#3045000
1=
0(
b1 '
b0 7
b1001100 ;
1%
#3050000
0%
#3055000
b10 '
b1 7
1%
#3060000
0%
#3065000
b11 '
b10 7
1%
#3070000
0%
#3075000
b1001101 :
1(
b0 '
b11 7
1%
#3080000
0%
#3085000
1=
0(
b1 '
b0 7
b1001101 ;
1%
#3090000
0%
#3095000
b10 '
b1 7
1%
#3100000
0%
#3105000
b11 '
b10 7
1%
#3110000
0%
#3115000
b1001110 :
1(
b0 '
b11 7
1%
#3120000
0%
#3125000
1=
0(
b1 '
b0 7
b1001110 ;
1%
#3130000
0%
#3135000
b10 '
b1 7
1%
#3140000
0%
#3145000
b11 '
b10 7
1%
#3150000
0%
#3155000
b1001111 :
1(
b0 '
b11 7
1%
#3160000
0%
#3165000
1=
0(
b1 '
b0 7
b1001111 ;
1%
#3170000
0%
#3175000
b10 '
b1 7
1%
#3180000
0%
#3185000
b11 '
b10 7
1%
#3190000
0%
#3195000
b1010000 :
1(
b0 '
b11 7
1%
#3200000
0%
#3205000
1=
0(
b1 '
b0 7
b1010000 ;
1%
#3210000
0%
#3215000
b10 '
b1 7
1%
#3220000
0%
#3225000
b11 '
b10 7
1%
#3230000
0%
#3235000
b1010001 :
1(
b0 '
b11 7
1%
#3240000
0%
#3245000
1=
0(
b1 '
b0 7
b1010001 ;
1%
#3250000
0%
#3255000
b10 '
b1 7
1%
#3260000
0%
#3265000
b11 '
b10 7
1%
#3270000
0%
#3275000
b1010010 :
1(
b0 '
b11 7
1%
#3280000
0%
#3285000
1=
0(
b1 '
b0 7
b1010010 ;
1%
#3290000
0%
#3295000
b10 '
b1 7
1%
#3300000
0%
#3305000
b11 '
b10 7
1%
#3310000
0%
#3315000
b1010011 :
1(
b0 '
b11 7
1%
#3320000
0%
#3325000
1=
0(
b1 '
b0 7
b1010011 ;
1%
#3330000
0%
#3335000
b10 '
b1 7
1%
#3340000
0%
#3345000
b11 '
b10 7
1%
#3350000
0%
#3355000
b1010100 :
1(
b0 '
b11 7
1%
#3360000
0%
#3365000
1=
0(
b1 '
b0 7
b1010100 ;
1%
#3370000
0%
